Workbook

Sheet CF BEST
A1: ФАКТ | B1: Денег на счету | C1: Нал | D1: Баланс на данный момент в безнале | F1: Альфа | G1: ОТП | H1: Совком | J1: =I2+H2+G2-B2 -> -471767.88 | M1: 1371350 | N1: долг рост через альфарм
B2: =SUMIFS(C9:C2880, B9:B2880, "оплачено", E9:E2880, "<>наличные")-SUMIFS(D9:D2880, B9:B2880, "оплачено", E9:E2880, "<>наличные") -> 2200319.3 | C2: =SUMIFS(C9:C2880, B9:B2880, "оплачено", E9:E2880, "наличные")-SUMIFS(D9:D2880, B9:B2880, "оплачено", E9:E2880, "наличные") -> 140067.69 | D2: =B2+C2/0.76 -> 2384618.9 | F2: =SUMIFS(C9:C2880, B9:B2880, "оплачено", E9:E2880, "АльфаБанк")-SUMIFS(D9:D2880, B9:B2880, "оплачено", E9:E2880, "АльфаБанк")+14204002.07-7200 -> 2188332.6 | G2: =SUMIFS(C9:C2880, B9:B2880, "оплачено", E9:E2880, "ОПТ Банк")-SUMIFS(D9:D2880, B9:B2880, "оплачено", E9:E2880, "ОПТ Банк")-14204002.07+7200 -> 9951.98 | H2: =SUMIFS(C9:C2880, B9:B2880, "оплачено", E9:E2880, "Совкомбанк")-SUMIFS(D9:D2880, B9:B2880, "оплачено", E9:E2880, "Совкомбанк") -> 2034.74 | I2: 1716564.7 | J2: =J1*0.76 -> -358543.59 | K2: =C2-J2 -> 498611.28
A4: Прогноз | B4: Нам должны | C4: Мы должны | D4: Баланс прогнозный | M4: 1042062.6
B5: =SUMIF($B$9:$B$5935,"План поступлений",$C$9:$C$5935) -> 69238564 | C5: =SUMIF($B$9:$B$5935,"план оплат",$D$9:$D$5935) -> 60161516 | D5: =B5-C5+D2 -> 11461667 | J5: 3000000 | M5: =M4-905882.4 -> 136180.16
A8: Дата | B8: статус | C8: поступления | D8: списания | E8: Банк | F8: ПЕРИОД | G8: НДС | H8: НДС ФАКТ | I8: Статья | J8: Контрагент | K8: № дс | L8: Счет | M8: Счет от дата | N8: Просрочка дней | O8: Назначение
A9: 45132 | B9: ОПЛАЧЕНО | D9: 20970 | E9: АльфаБанк | F9: июль 2023 | G9: 0 | H9: =SUM(C9:D9)*G9/(G9+100) -> 0 | I9: IT | J9: ООО 1С-Битрикс | O9: Оплата по счет-заказу №5720598 от 25.07.2023 за права на программы для ЭВМ и сервисы. Без налога (НДС) НДС не облагается
A10: 45141 | B10: ОПЛАЧЕНО | D10: 1150 | E10: Наличные | F10: АВГУСТ 2023 | G10: 0 | H10: =SUM(C10:D10)*G10/(G10+100) -> 0 | I10: ПРОЧЕЕ | O10: доставка документов
A11: 45154 | B11: ОПЛАЧЕНО | D11: 1070 | E11: Наличные | F11: АВГУСТ 2023 | G11: 0 | H11: =SUM(C11:D11)*G11/(G11+100) -> 0 | I11: ПРОЧЕЕ | O11: доставка документов
A12: 45162 | B12: ОПЛАЧЕНО | C12: 93672 | E12: АльфаБанк | F12: АВГУСТ 2023 | G12: 20 | H12: =SUM(C12:D12)*G12/(G12+100) -> 15612 | I12: РЕАЛИЗАЦИЯ | J12: ООО РА СА МЕДИА | N12: =A12-IF(M12>0,M12,A12) -> 0 | O12: ОПЛАТА ПО СЧЕТУ №18 ОТ 24.07.2023 ЗА ПРОВЕДЕНИЕ РЕКЛАМНОЙ КАМПАНИИ В ИЮНЕ 23Г, ДОГОВОР №РМ-01-06-23 ОТ 01.06.2023, ДС 1 ОТ 01.06.23 СУММА 93672-00 В Т.Ч. НДС (20%) 15612-00
A13: 45167 | B13: ОПЛАЧЕНО | C13: 1404000 | E13: АльфаБанк | F13: АВГУСТ 2023 | G13: 20 | H13: =SUM(C13:D13)*G13/(G13+100) -> 234000 | I13: РЕАЛИЗАЦИЯ | J13: ООО СТРОНГ АДВЕРТАЙЗИНГ | N13: =A13-IF(M13>0,M13,A13) -> 0 | O13: ОПЛ. ПО СЧЕТУ № 22 ОТ 25.08.23 ЗА УСЛУГИ ПО РАЗМЕЩЕНИЮ РЕКЛАМНЫХ МАТЕРИАЛОВ (БРЕНД "ЭРКАФАРМ СЕВЕРО-ЗАПАД"/ "ОЗЕРКИ"). В Т.Ч. НДС 20 % - 234000.00 РУБ.
A14: 45170 | B14: ОПЛАЧЕНО | D14: 60000 | E14: Наличные | G14: 0 | H14: =SUM(C14:D14)*G14/(G14+100) -> 0 | I14: ПРОЧЕЕ | O14: фрилансер
A15: 45170 | B15: ОПЛАЧЕНО | D15: 28000 | E15: Наличные | G15: 0 | H15: =SUM(C15:D15)*G15/(G15+100) -> 0 | I15: ПРОЧЕЕ | O15: школа дайвинга
A16: 45173 | B16: ОПЛАЧЕНО | D16: 10 | E16: АльфаБанк | G16: 0 | H16: =SUM(C16:D16)*G16/(G16+100) -> 0 | I16: ОРД | J16: ООО ОРД-А | O16: Идентификационный платеж. НДС не облагается
A17: 45176 | B17: ОПЛАЧЕНО | D17: 875000 | E17: АльфаБанк | G17: 20 | H17: =SUM(C17:D17)*G17/(G17+100) -> 145833.33 | I17: ТРАНЗИТ | O17: транзит
A18: 45176 | B18: ОПЛАЧЕНО | C18: 630000 | E18: Наличные | F18: транзит | G18: 0 | H18: =SUM(C18:D18)*G18/(G18+100) -> 0 | I18: ТРАНЗИТ
A19: 45176 | B19: ОПЛАЧЕНО | D19: 630000 | E19: Наличные | G19: 0 | H19: =SUM(C19:D19)*G19/(G19+100) -> 0 | J19: ООО СТРОНГ АДВЕРТАЙЗИНГ | O19: стронг выдача
A20: 45198 | B20: ОПЛАЧЕНО | C20: 1176000 | E20: АльфаБанк | F20: реализация | G20: 20 | H20: =SUM(C20:D20)*G20/(G20+100) -> 196000 | I20: РЕАЛИЗАЦИЯ | J20: ООО СТРОНГ АДВЕРТАЙЗИНГ | N20: =A20-IF(M20>0,M20,A20) -> 0 | O20: Оплата по счету № 25 от 29.09.23 за услуги по размещению рекламных материалов (бренд "Эркафарм Северо-Запад"/ "Озерки"). В том числе НДС 20 % - 196000.00 рублей.
A21: 45203 | B21: ОПЛАЧЕНО | D21: 50750 | E21: Наличные | G21: 0 | H21: =SUM(C21:D21)*G21/(G21+100) -> 0 | I21: ПРЕМИЯ | J21: аккаунт | O21: 5335941005937933
A22: 45203 | B22: ОПЛАЧЕНО | D22: 17255 | E22: Наличные | G22: 0 | H22: =SUM(C22:D22)*G22/(G22+100) -> 0 | I22: ПРЕМИЯ | J22: физик | O22: отрисовка фигмы
A23: 45203 | B23: ОПЛАЧЕНО | C23: 56952 | E23: АльфаБанк | F23: реализация | G23: 20 | H23: =SUM(C23:D23)*G23/(G23+100) -> 9492 | I23: РЕАЛИЗАЦИЯ | N23: =A23-IF(M23>0,M23,A23) -> 0 | O23: ОПЛАТА ПО СЧЕТУ №19 ОТ 24.07.2023 ЗА ПРОВЕДЕНИЕ РЕКЛАМНОЙ КАМПАНИИ В ИЮЛЕ 23Г, ДОГОВОР №РМ-01-06-23 ОТ 01.06.2023, ДС 2 ОТ 01.07.23 СУММА 56952-00 В Т.Ч. НДС (20%) 9492-00
A24: 45203 | B24: ОПЛАЧЕНО | D24: 23730 | E24: АльфаБанк | G24: 20 | H24: =SUM(C24:D24)*G24/(G24+100) -> 3955 | I24: ПРОЧЕЕ | O24: По счету № 93 от 06 июля 2023 г. Услуги РИТ материалов в сети AdCamp в период 01.07.2023-06.07.2023 на основании Договора № ЭКР-2306236 от 23.06.2023 г В том числе НДС 20%, 3955.00 руб.
A25: 45203 | B25: ОПЛАЧЕНО | D25: 39030 | E25: АльфаБанк | G25: 20 | H25: =SUM(C25:D25)*G25/(G25+100) -> 6505 | I25: ПРОЧЕЕ | O25: По счету № 83 от 30 июня 2023 г Услуги РИМ в сети AdCamp в период 25.06.2023-30.06.2023 на основании Договора № ЭКР-2306236 от 23.06.2023 г. В том числе НДС 20%, 6505.00 руб.
A26: 45211 | B26: ОПЛАЧЕНО | D26: 722222 | E26: АльфаБанк | G26: 20 | H26: =SUM(C26:D26)*G26/(G26+100) -> 120370.33 | I26: ТРАНЗИТ | O26: транзит
A27: 45211 | B27: ОПЛАЧЕНО | C27: 519999.84 | E27: Наличные | F27: транзит | G27: 0 | H27: =SUM(C27:D27)*G27/(G27+100) -> 0 | I27: ТРАНЗИТ
A28: 45211 | B28: ОПЛАЧЕНО | D28: 520000 | E28: Наличные | G28: 0 | H28: =SUM(C28:D28)*G28/(G28+100) -> 0 | J28: ООО СТРОНГ АДВЕРТАЙЗИНГ | O28: стронг выдача
A29: 45216 | B29: ОПЛАЧЕНО | D29: 1090 | E29: Наличные | G29: 0 | H29: =SUM(C29:D29)*G29/(G29+100) -> 0 | O29: доставка документов
A30: 45217 | B30: ОПЛАЧЕНО | D30: 97996.24 | E30: АльфаБанк | G30: 0 | H30: =SUM(C30:D30)*G30/(G30+100) -> 0 | I30: ПОДРЯДЧИКИ | J30: ИП Лукин Евгений Витальевич | O30: По счету № 5 от 05 октября 2023 г. Услуги РИМ ОАО "МЮЗ" в сети Интернет по договору No 01/Р/В/23 от 01 сентября 2023 г. за период с 04.09.2023 г. по 30.09.2023 г. НДС не облагается
A31: 45217 | B31: ОПЛАЧЕНО | D31: 5000 | E31: АльфаБанк | G31: 20 | H31: =SUM(C31:D31)*G31/(G31+100) -> 833.33333 | I31: ОРД | J31: ООО ОРД-А | O31: По счету № 597 от 30.09.2023 Услуги по сбору, хранению, обработке и передаче Данных от Поставщика данных в ЕРИР посредством Системы ОРД-А , за сентябрь 2023 г. В том числе НДС 20%, 833.33 руб.
A32: 45217 | B32: ОПЛАЧЕНО | D32: 326388.89 | E32: АльфаБанк | G32: 20 | H32: =SUM(C32:D32)*G32/(G32+100) -> 54398.148 | I32: ТРАНЗИТ | O32: транзит
A33: 45217 | B33: ОПЛАЧЕНО | C33: 235000 | E33: Наличные | F33: транзит | G33: 0 | H33: =SUM(C33:D33)*G33/(G33+100) -> 0 | I33: ТРАНЗИТ
A34: 45217 | B34: ОПЛАЧЕНО | D34: 68729.86 | E34: АльфаБанк | G34: 20 | H34: =SUM(C34:D34)*G34/(G34+100) -> 11454.977 | I34: БОНУСЫ | J34: ООО ПМ | O34: 0.02
A35: 45217 | B35: ОПЛАЧЕНО | D35: 5000 | E35: АльфаБанк | G35: 20 | H35: =SUM(C35:D35)*G35/(G35+100) -> 833.33333 | I35: ОРД | J35: ООО ОРД-А | O35: По счету № 597 от 30.09.2023 Услуги по сбору, хранению, обработке и передаче Данных от Поставщика данных в ЕРИР посредством Системы ОРД-А , за сентябрь 2023 г. В том числе НДС 20%, 833.33 руб.
A36: 45218 | B36: ОПЛАЧЕНО | D36: 23500 | E36: Наличные | G36: 0 | H36: =SUM(C36:D36)*G36/(G36+100) -> 0 | O36: 4377723766690287 Роман Ц.
A37: 45222 | B37: ОПЛАЧЕНО | D37: 50750 | E37: Наличные | G37: 0 | H37: =SUM(C37:D37)*G37/(G37+100) -> 0 | I37: ФОТ | J37: ФОТ | O37: ЗП аккаунту - 5335941005937933
A38: 45223 | B38: ОПЛАЧЕНО | C38: 345869.1 | E38: АльфаБанк | F38: реализация | G38: 20 | H38: =SUM(C38:D38)*G38/(G38+100) -> 57644.85 | I38: РЕАЛИЗАЦИЯ | J38: ООО РА СА МЕДИА | N38: =A38-IF(M38>0,M38,A38) -> 0 | O38: Оплата по счету №30 от 09.10.2023 за услуги по размещению РИМ в сентябре 23г, договор №РМ-01-06-23 от 01.06.2023, ДС 4 от 30.08.23 Сумма 345869-10 В т.ч. НДС (20%) 57644-85
A39: 45231 | B39: ОПЛАЧЕНО | D39: 265229.19 | E39: АльфаБанк | G39: 0 | H39: =SUM(C39:D39)*G39/(G39+100) -> 0 | I39: НАЛОГИ | J39: МИ ФНС РОССИИ ПО УПРАВЛЕНИЮ ДОЛГОМ
A40: 45231 | B40: ОПЛАЧЕНО | D40: 212183.36 | E40: АльфаБанк | G40: 0 | H40: =SUM(C40:D40)*G40/(G40+100) -> 0 | I40: НАЛОГИ | J40: МИ ФНС РОССИИ ПО УПРАВЛЕНИЮ ДОЛГОМ
A41: 45233 | B41: ОПЛАЧЕНО | D41: 23561 | E41: Наличные | G41: 0 | H41: =SUM(C41:D41)*G41/(G41+100) -> 0 | I41: ПРОЧЕЕ | O41: 2200 7001 3648 8748
A42: 45237 | B42: ОПЛАЧЕНО | D42: 24000 | E42: Наличные | G42: 0 | H42: =SUM(C42:D42)*G42/(G42+100) -> 0 | I42: ПРОЧЕЕ | O42: 7 952 773 3683 - тинек, Роман
A43: 45240 | B43: ОПЛАЧЕНО | C43: 846913.92 | E43: АльфаБанк | F43: реализация | G43: 20 | H43: =SUM(C43:D43)*G43/(G43+100) -> 141152.32 | I43: РЕАЛИЗАЦИЯ | J43: ООО ДИДЖИТАЛЬНЫЕ ТЕХНОЛОГИИ | N43: =A43-IF(M43>0,M43,A43) -> 0 | O43: Оплата по сч 34 от 09.11.2023 за Услуги по аналитич. обзору рек. рынка на территории Узбекистан в нояб 2023 г, согл ДС 2 от 1.11.23 к дог PM-13-07-23 от 13.07.23 Сумма 846913-92 В т.ч. НДС (20%) 141152-32
A44: 45243 | B44: ОПЛАЧЕНО | D44: 834798.18 | E44: АльфаБанк | G44: 20 | H44: =SUM(C44:D44)*G44/(G44+100) -> 139133.03 | J44: ООО МЕДИА ПЛАТФОРМА | O44: По счету № 66 от 09 ноября 2023 г. Услуги по аналитическому обзору рекламного рынка на территории республики Узбекистан в ноябре 2023 года В том числе НДС 20%, 139133.03 руб.
A45: 45246 | B45: ОПЛАЧЕНО | D45: 112454.1 | E45: Наличные | G45: 0 | H45: =SUM(C45:D45)*G45/(G45+100) -> 0 | O45: Тиньк 79295953914
A46: 45246 | B46: ОПЛАЧЕНО | D46: 50975 | E46: Наличные | G46: 0 | H46: =SUM(C46:D46)*G46/(G46+100) -> 0 | I46: ФОТ | J46: ФОТ | O46: ЗП аккаунту - 5335941005937933
A47: 45258 | B47: ОПЛАЧЕНО | D47: 100000 | E47: Наличные | G47: 0 | H47: =SUM(C47:D47)*G47/(G47+100) -> 0 | I47: ФОТ | J47: ФОТ | O47: Акимов
A48: 45258 | B48: ОПЛАЧЕНО | D48: 24000 | E48: Наличные | G48: 0 | H48: =SUM(C48:D48)*G48/(G48+100) -> 0 | I48: ФОТ | J48: ФОТ | O48: 7 952 773 3683 - тинек, Роман
A49: 45258 | B49: ОПЛАЧЕНО | D49: 485714.29 | E49: АльфаБанк | G49: 20 | H49: =SUM(C49:D49)*G49/(G49+100) -> 80952.381 | I49: ТРАНЗИТ
A50: 45258 | B50: ОПЛАЧЕНО | C50: 340000 | E50: Наличные | F50: транзит | G50: 0 | H50: =SUM(C50:D50)*G50/(G50+100) -> 0 | I50: ТРАНЗИТ
A51: 45260 | B51: ОПЛАЧЕНО | C51: 796589.1 | E51: АльфаБанк | F51: реализация | G51: 20 | H51: =SUM(C51:D51)*G51/(G51+100) -> 132764.85 | I51: РЕАЛИЗАЦИЯ | J51: ООО РА СА МЕДИА | N51: =A51-IF(M51>0,M51,A51) -> 0 | O51: ОПЛАТА ПО СЧЕТУ №35 ОТ 09.11.2023 ЗА УСЛУГИ ПО РАЗМЕЩЕНИЮ РИМ В ОКТЯБРЕ 23Г, ДОГОВОР №РМ-01-06-23 ОТ 01.06.2023, ДС 6 ОТ 01.10.23 СУММА 796589-10 В Т.Ч. НДС (20%) 132764-85
A52: 45261 | B52: ОПЛАЧЕНО | D52: 6990 | E52: АльфаБанк | G52: 0 | H52: =SUM(C52:D52)*G52/(G52+100) -> 0 | I52: IT | J52: ООО 1С-Битрикс
A53: 45263 | B53: ОПЛАЧЕНО | D53: 100000 | E53: Наличные | G53: 0 | H53: =SUM(C53:D53)*G53/(G53+100) -> 0 | I53: ФОТ | J53: ФОТ | O53: Акимов
A54: 45264 | B54: ОПЛАЧЕНО | D54: 245350 | E54: АльфаБанк | G54: 0 | H54: =SUM(C54:D54)*G54/(G54+100) -> 0 | J54: ИП Веерещагин | O54: адиндекс По счету № 44 от 15 ноября 2023 г Услуги по информационному и коммуникационному сопровождению согласно Приложению №1 от 31.10.2023 г к Договору №07/1023 от 31 октября 2023г. НДС не облагается
A55: 45264 | B55: ОПЛАЧЕНО | D55: 27965.89 | E55: АльфаБанк | G55: 20 | H55: =SUM(C55:D55)*G55/(G55+100) -> 4660.9817 | J55: ООО САПЕ | O55: По счету № БП-468 от 31.10.2023 Услуги в октябре 2023г. доступа к платформе Sape для самостоятельного размещения РИМ, согласно ДОГОВОРА №RTB-29-09/23 от 29.09.2023. В том числе НДС 20%, 4660.98 руб.
A56: 45264 | B56: ОПЛАЧЕНО | D56: 101950 | E56: Наличные | G56: 0 | H56: =SUM(C56:D56)*G56/(G56+100) -> 0 | I56: ФОТ | J56: ФОТ | O56: Дарья
A57: 45266 | B57: ОПЛАЧЕНО | C57: 214155.36 | E57: АльфаБанк | F57: реализация | G57: 20 | H57: =SUM(C57:D57)*G57/(G57+100) -> 35692.56 | I57: РЕАЛИЗАЦИЯ | J57: ООО ТД Лазурит | N57: =A57-IF(M57>0,M57,A57) -> 0
A58: 45266 | B58: ОПЛАЧЕНО | C58: 360000 | E58: АльфаБанк | F58: реализация | G58: 20 | H58: =SUM(C58:D58)*G58/(G58+100) -> 60000 | I58: РЕАЛИЗАЦИЯ | J58: ООО РА СА МЕДИА | N58: =A58-IF(M58>0,M58,A58) -> 0
A59: 45268 | B59: ОПЛАЧЕНО | D59: 130000 | E59: Наличные | G59: 0 | H59: =SUM(C59:D59)*G59/(G59+100) -> 0 | I59: ФОТ | J59: ФОТ | O59: Илья
A60: 45268 | B60: ОПЛАЧЕНО | D60: 40000 | E60: Наличные | G60: 0 | H60: =SUM(C60:D60)*G60/(G60+100) -> 0 | J60: 546956002196517
A61: 45268 | B61: ОПЛАЧЕНО | D61: 25000 | E61: Наличные | G61: 0 | H61: =SUM(C61:D61)*G61/(G61+100) -> 0 | I61: ФОТ | J61: ФОТ | O61: Мария
A62: 45268 | B62: ОПЛАЧЕНО | D62: 808823.53 | E62: АльфаБанк | G62: 20 | H62: =SUM(C62:D62)*G62/(G62+100) -> 134803.92 | I62: ТРАНЗИТ | O62: транзит
A63: 45268 | B63: ОПЛАЧЕНО | C63: 550000 | E63: Наличные | F63: транзит | G63: 0 | H63: =SUM(C63:D63)*G63/(G63+100) -> 0 | I63: ТРАНЗИТ
A64: 45271 | B64: ОПЛАЧЕНО | C64: 473906.52 | E64: АльфаБанк | F64: реализация | G64: 20 | H64: =SUM(C64:D64)*G64/(G64+100) -> 78984.42 | I64: РЕАЛИЗАЦИЯ | J64: ООО ТД Лазурит | N64: =A64-IF(M64>0,M64,A64) -> 0 | O64: Оплата по счету №38 от 06.12.23 Привлечение целевого действия для клиента "Лазурит". В том числе НДС 20% (78984.42 RUB)
A65: 45272 | B65: ОПЛАЧЕНО | D65: 225700.24 | E65: АльфаБанк | G65: 0 | H65: =SUM(C65:D65)*G65/(G65+100) -> 0 | I65: ПОДРЯДЧИКИ | J65: ИП Лукин Евгений Витальевич | O65: По счету №6 от 31.10.2023 Услуги по размещению рекламных материалов ОАО "МЮЗ" в сети Интернет по договору No 01/Р/В/23 от 01 сентября 2023 г. за период с 03.10.2023 г. по 31.10.2023 г НДС не облагается
A66: 45272 | B66: ОПЛАЧЕНО | D66: 171392 | E66: АльфаБанк | G66: 20 | H66: =SUM(C66:D66)*G66/(G66+100) -> 28565.333 | I66: СК ПАРТНЕРСКАЯ | J66: ООО РА СА МЕДИА | O66: По счету № 1344 от 27 октября 2023 г. Премия согласно ДС №1-П от 01.06.2023г к Договору №РМ-01-06-2023 от 01.06.2023 г. Период с 01.06.2023 г по 30.09.2023 г. НДС не облагается
A67: 45272 | B67: ОПЛАЧЕНО | D67: 22935 | E67: АльфаБанк | G67: 20 | H67: =SUM(C67:D67)*G67/(G67+100) -> 3822.5 | J67: Глазков Андрей | O67: По счету № 49 от 30 ноября 2023. Услуги по сопровождению прикладного и серверного по, технического обслуживанию оборудования согласно Договору № РМ 01-10-2023 от 01.10.2023 НДС не облагается
A68: 45272 | B68: ОПЛАЧЕНО | D68: 32217.53 | E68: АльфаБанк | G68: 20 | H68: =SUM(C68:D68)*G68/(G68+100) -> 5369.5883 | I68: ПОДРЯДЧИКИ | J68: ООО САПЕ | O68: По счету № БП-571 от 30.11.2023. Услуги в ноябре 2023г. доступа к платформе Sape для размещения РИМ, согласно ДОГОВОРА №RTB-29-09/23 от 29.09.2023 В том числе НДС 20%, 5369.59 руб.
A69: 45273 | B69: ОПЛАЧЕНО | D69: 30000 | E69: Наличные | G69: 0 | H69: =SUM(C69:D69)*G69/(G69+100) -> 0 | J69: 89169279010 Игорь
A70: 45279 | B70: ОПЛАЧЕНО | D70: 25000 | E70: Наличные | G70: 0 | H70: =SUM(C70:D70)*G70/(G70+100) -> 0 | J70: 79067315001
A71: 45281 | B71: ОПЛАЧЕНО | D71: 100500 | E71: Наличные | G71: 0 | H71: =SUM(C71:D71)*G71/(G71+100) -> 0 | J71: 7 903 611-83-31 - евгений владимирович Б
A72: 45288 | B72: ОПЛАЧЕНО | D72: 500000 | E72: АльфаБанк | G72: 20 | H72: =SUM(C72:D72)*G72/(G72+100) -> 83333.333 | I72: АПТЕКА | J72: ДПД МЕДИА ООО | O72: Счет на оплату № 1 от 20 декабря 2023 г. Услуги по размещению рекламных материалов на ресурсах исполнителя, согласно отчету №.1 к договору №25/08/23 от 25 августа 2023 г. за сентябрь 2023 г. НДС не облагается
A73: 45289 | B73: ОПЛАЧЕНО | D73: 33228 | E73: АльфаБанк | G73: 20 | H73: =SUM(C73:D73)*G73/(G73+100) -> 5538 | J73: Глазков Андрей | O73: По счету № 48 от 31 октября 2023. Услуги по сопровождению прикладного и серверного по, технического обслуживанию оборудования согласно Договору № РМ 01-10-2023 от 01.10.2023 НДС не облагается
A74: 45289 | B74: ОПЛАЧЕНО | C74: 866884.2 | E74: АльфаБанк | G74: 20 | H74: =SUM(C74:D74)*G74/(G74+100) -> 144480.7 | I74: РЕАЛИЗАЦИЯ | J74: ООО РА СА МЕДИА | N74: =A74-IF(M74>0,M74,A74) -> 0 | O74: Оплата по счету №41 от 11.12.2023 за услуги по размещению РИМ в ноябре 23г, договор №РМ-01-06-23 от 01.06.2023, ДС 7 от 01.11.23 Сумма 866884-20 В т.ч. НДС (20%) 144480-70
A75: 45289 | B75: ОПЛАЧЕНО | D75: 245617.19 | E75: АльфаБанк | G75: 0 | H75: =SUM(C75:D75)*G75/(G75+100) -> 0 | J75: ИП Лукин Евгений Витальевич | O75: По счету №9 от 30.11.2023 Услуги по размещению рекламных материалов ОАО "МЮЗ" в сети Интернет по договору No 01/Р/В/23 от 01 сентября 2023 г. за период с 01.11.2023 г. по 30.11.2023 г НДС не облагается
A76: 45289 | B76: ОПЛАЧЕНО | D76: 5000 | E76: АльфаБанк | G76: 20 | H76: =SUM(C76:D76)*G76/(G76+100) -> 833.33333 | I76: ОРД | J76: ООО ОРД-А | O76: По счету № 2528 от 30 ноября 2023 г. Услуги по сбору, хранению, обработке и передаче Данных в ЕРИР посредством Системы ОРД-А , за ноябрь 2023 г. В том числе НДС 20%, 833.33 руб.
A77: 45289 | B77: ОПЛАЧЕНО | D77: 133632.94 | E77: АльфаБанк | G77: 20 | H77: =SUM(C77:D77)*G77/(G77+100) -> 22272.157 | J77: ООО МЕДИА ПЛАТФОРМА
A78: 45289 | B78: ОПЛАЧЕНО | D78: 295717.67 | E78: АльфаБанк | G78: 20 | H78: =SUM(C78:D78)*G78/(G78+100) -> 49286.278 | J78: ООО МЕДИА ПЛАТФОРМА
A79: 45289 | B79: ОПЛАЧЕНО | D79: 6990 | E79: АльфаБанк | G79: 0 | H79: =SUM(C79:D79)*G79/(G79+100) -> 0 | I79: IT | J79: ООО 1С-Битрикс
A80: 45289 | B80: ОПЛАЧЕНО | D80: 170000 | E80: Наличные | G80: 0 | H80: =SUM(C80:D80)*G80/(G80+100) -> 0 | I80: ФОТ | J80: ФОТ | O80: Акимов
A81: 45289 | B81: ОПЛАЧЕНО | D81: 61430.71 | E81: АльфаБанк | G81: 20 | H81: =SUM(C81:D81)*G81/(G81+100) -> 10238.452 | J81: ООО ПМ | O81: 0.02
A82: 45289 | B82: ОПЛАЧЕНО | D82: 130650 | E82: Наличные | G82: 0 | H82: =SUM(C82:D82)*G82/(G82+100) -> 0 | I82: ФОТ | J82: ФОТ | O82: Илья
A83: 45289 | B83: ОПЛАЧЕНО | D83: 625000 | E83: АльфаБанк | G83: 20 | H83: =SUM(C83:D83)*G83/(G83+100) -> 104166.67 | I83: ТРАНЗИТ | O83: транзит
A84: 45289 | B84: ОПЛАЧЕНО | C84: 425000 | E84: Наличные | F84: транзит | G84: 0 | H84: =SUM(C84:D84)*G84/(G84+100) -> 0 | I84: ТРАНЗИТ
A85: 45299 | B85: ОПЛАЧЕНО | D85: 12000 | E85: Наличные | F85: прочее | G85: 0 | H85: =SUM(C85:D85)*G85/(G85+100) -> 0 | I85: IT | J85: хостинг - домены
A86: 45301 | B86: ОПЛАЧЕНО | D86: 100000 | E86: Наличные | G86: 0 | H86: =SUM(C86:D86)*G86/(G86+100) -> 0 | I86: ФОТ | J86: ФОТ | O86: Дарья
A87: 45301 | B87: ОПЛАЧЕНО | D87: 25000 | E87: Наличные | G87: 0 | H87: =SUM(C87:D87)*G87/(G87+100) -> 0 | I87: ФОТ | J87: ФОТ | N87: =A87-IF(M87>0,M87,A87) -> 0 | O87: Мария
A88: 45309 | B88: ОПЛАЧЕНО | C88: 420000 | E88: АльфаБанк | G88: 20 | H88: =SUM(C88:D88)*G88/(G88+100) -> 70000 | I88: РЕАЛИЗАЦИЯ | J88: ООО ЛАЙОН КОММЬЮНИКЕЙШНЗ | N88: =A88-IF(M88>0,M88,A88) -> 0 | O88: Оплата по счету 42 от 13.12.23 за услуги_(билайн), в т.ч. НДС 70000-00
A89: 45309 | B89: ОПЛАЧЕНО | C89: 905883.26 | E89: АльфаБанк | G89: 20 | H89: =SUM(C89:D89)*G89/(G89+100) -> 150980.54 | I89: РЕАЛИЗАЦИЯ | J89: ООО ДИДЖИТАЛЬНЫЕ ТЕХНОЛОГИИ | O89: Оплата по счету 8 от 16.01.2024 за по пополнение баланса рекламного кабинета для бренда "Кагоцел", январь-март 2024г., ДС№3 от 25 декабря 2023 к дог-ру № PM-13-07-23 Сумма 905883-26 В т.ч. НДС (20%) 150980-54
A90: 45310 | B90: ОПЛАЧЕНО | D90: 823530.24 | E90: АльфаБанк | G90: 20 | H90: =SUM(C90:D90)*G90/(G90+100) -> 137255.04 | J90: ООО МЕДИА ПЛАТФОРМА | O90: Услуги по пополнению баланса рекламного кабинета Google на территории Республики Узбекистан для проекта "Кагоцел", в период с 1 января 2024 г. по 31 марта 2024 года. В том числе НДС 20%, 137255.04 руб.
A91: 45313 | B91: ОПЛАЧЕНО | D91: 120000 | E91: АльфаБанк | G91: 20 | H91: =SUM(C91:D91)*G91/(G91+100) -> 20000 | J91: ООО ПБД | O91: По счету № 406 от 31 октября 2023 г. Услуги по формированию и передаче статистического отчета по Заявке №1 от 01.10.23 г. к Договору №Р-3/0723 от 01.07.23 г. В том числе НДС 20%, 20000.00 руб.
A92: 45313 | B92: ОПЛАЧЕНО | D92: 120000 | E92: АльфаБанк | G92: 20 | H92: =SUM(C92:D92)*G92/(G92+100) -> 20000 | J92: ООО Вымпелком | O92: По счету Счет № AR-17961-1 от 31.10.2023 Услуга ТВ аналитика/клиент Ренессанс банк/Октябрь 2023/ДС № 1 к договору №781093761 от 18 января 2021 г. за октябрь 2023г. В том числе НДС 20%, 20000.00 руб.
A93: 45313 | B93: ОПЛАЧЕНО | D93: 5000 | E93: АльфаБанк | G93: 20 | H93: =SUM(C93:D93)*G93/(G93+100) -> 833.33333 | I93: ОРД | J93: ООО ОРД-А | N93: =A93-IF(M93>0,M93,A93) -> 0 | O93: По счету № 3926 от 31 декабря 2023 г. В том числе НДС 20%, 833.33 руб.
A94: 45313 | B94: ОПЛАЧЕНО | C94: 300000 | E94: АльфаБанк | F94: ДЕКАБРЬ 2024 | G94: 20 | H94: =SUM(C94:D94)*G94/(G94+100) -> 50000 | I94: РЕАЛИЗАЦИЯ | J94: ООО ТЕЛЕМИР | N94: =A94-IF(M94>0,M94,A94) -> 0 | O94: Оплата по счету №7 от 16.01.2024, по ДС № 1 к Дог-ру РМ-28/11-23 от 30.11.2023 за услуги по размещению (распространению) рекламных материалов "Alltime", в период с 01.12.2023г. по 31.12.2023г; договор №ДС № 1
A95: 45314 | B95: ОПЛАЧЕНО | C95: 411386.69 | E95: АльфаБанк | F95: ДЕКАБРЬ 2024 | G95: 20 | H95: =SUM(C95:D95)*G95/(G95+100) -> 68564.448 | I95: РЕАЛИЗАЦИЯ | J95: ООО Телемир | O95: ОПЛАТА ПО СЧЕТУ №6 ОТ 16.01.2024, ПО ДС № 2 К ДОГ-РУ РМ-2811-23 ОТ 01.12.2023 ЗА УСЛУГИ ПО РАЗМЕЩЕНИЮ (РАСПРОСТРАНЕНИЮ) РЕКЛАМНЫХ МАТЕРИАЛОВ "ILE DE BEAUTE", В ПЕРИОД С 01.12.2023Г. ПО 31.12.2023Г; ДОГОВОР №ДС
A96: 45323 | B96: ОПЛАЧЕНО | D96: 868055.56 | E96: АльфаБанк | G96: 20 | H96: =SUM(C96:D96)*G96/(G96+100) -> 144675.93 | I96: ТРАНЗИТ
A97: 45323 | B97: ОПЛАЧЕНО | C97: 625000 | E97: Наличные | F97: транзит | G97: 0 | H97: =SUM(C97:D97)*G97/(G97+100) -> 0 | I97: ТРАНЗИТ
A98: 45323 | B98: ОПЛАЧЕНО | D98: 220565.07 | E98: АльфаБанк | G98: 0 | H98: =SUM(C98:D98)*G98/(G98+100) -> 0 | I98: НАЛОГИ | J98: МИ ФНС РОССИИ ПО УПРАВЛЕНИЮ ДОЛГОМ
A99: 45323 | B99: ОПЛАЧЕНО | D99: 130000 | E99: Наличные | G99: 0 | H99: =SUM(C99:D99)*G99/(G99+100) -> 0 | I99: ФОТ | J99: ФОТ | O99: Анна Ким
A100: 45323 | B100: ОПЛАЧЕНО | D100: 170000 | E100: Наличные | G100: 0 | H100: =SUM(C100:D100)*G100/(G100+100) -> 0 | I100: ФОТ | J100: ФОТ | O100: Акимов В
A101: 45323 | B101: ОПЛАЧЕНО | D101: 25000 | E101: Наличные | G101: 0 | H101: =SUM(C101:D101)*G101/(G101+100) -> 0 | I101: ФОТ | J101: ФОТ | N101: =A101-IF(M101>0,M101,A101) -> 0 | O101: Мария О
A102: 45324 | B102: ОПЛАЧЕНО | C102: 674113.2 | E102: АльфаБанк | F102: ДЕКАБРЬ 2024 | G102: 20 | H102: =SUM(C102:D102)*G102/(G102+100) -> 112352.2 | I102: РЕАЛИЗАЦИЯ | J102: ООО ТД Лазурит | O102: Привлечение целевого действия для клиента «Лазурит», в период с 1 декабря 2023г. по 31 декабря 2023г., согласно доп.соглашению № 4 к Договору PM-21-08-23 от 21.08.23
A103: 45332 | B103: ОПЛАЧЕНО | D103: 50000 | E103: Наличные | G103: 0 | H103: =SUM(C103:D103)*G103/(G103+100) -> 0 | I103: ФОТ | J103: ФОТ | O103: Дарья
...

Sheet БДДС 2026
B1: РЕАЛИЗАЦИЯ | C1: =SUM(J1+R1+Z1+AH1) -> 76426216 | D1: =SUM(D7:D41) -> 4788498.2 | F1: =SUM(F7:F41) -> 21363945 | H1: =SUM(H7:H41) -> 29861476 | J1: =SUM(J7:J41) -> 56013919 | L1: =SUM(L7:L41) -> 17354785 | N1: =SUM(N7:N41) -> 57500 | P1: =SUM(P7:P41) -> 3000000 | R1: =SUM(R7:R41) -> 20412285 | T1: =SUM(T7:T41) -> 0 | V1: =SUM(V7:V41) -> 0 | X1: =SUM(X7:X41) -> 0 | Z1: =SUM(Z7:Z41) -> 0 | AB1: =SUM(AB7:AB41) -> 12 | AD1: =SUM(AD7:AD41) -> 0 | AF1: =SUM(AF7:AF41) -> 0 | AH1: =SUM(AH7:AH41) -> 12
B2: РАСХОДЫ | C2: =SUM(J2+R2+Z2+AH2) -> 79668913 | D2: =SUM(E7:E41)-E15-E22 -> 8075496.9 | F2: =SUM(G7:G41)-G15-G22 -> 12308661 | H2: =SUM(I7:I41)-I15-I22 -> 21283997 | J2: =SUM(K7:K41)-K15-K22 -> 54994398 | L2: =SUM(M7:M41)-M15-M22 -> 14948734 | N2: =SUM(O7:O41)-O15-O22 -> 8734780.9 | P2: =SUM(Q7:Q41)-Q15-Q22 -> 885067.52 | R2: =SUM(S7:S41)-S15-S22 -> 24674515 | T2: =SUM(U7:U41)-U15-U22 -> 0 | V2: =SUM(W7:W41)-W15-W22 -> 0 | X2: =SUM(Y7:Y41)-Y15-Y22 -> 0 | Z2: =SUM(AA7:AA41)-AA15-AA22 -> 0 | AB2: =SUM(AC7:AC41)-AC15-AC22 -> 0 | AD2: =SUM(AE7:AE41)-AE15-AE22 -> 0 | AF2: =SUM(AG7:AG41)-AG15-AG22 -> 0 | AH2: =SUM(AI7:AI41)-AI15-AI22 -> 0
B3: Дельта | C3: =SUM(J3+R3+Z3+AH3) -> -3242696.9 | D3: =D1-D2 -> -3286998.8 | F3: =F1-F2 -> 9055283.9 | H3: =H1-H2 -> 8577479.1 | J3: =J1-J2 -> 1019520.3 | L3: =L1-L2 -> 2406051.2 | N3: =N1-N2 -> -8677280.9 | P3: =P1-P2 -> 2114932.5 | R3: =R1-R2 -> -4262229.3 | T3: =T1-T2 -> 0 | V3: =V1-V2 -> 0 | X3: =X1-X2 -> 0 | Z3: =Z1-Z2 -> 0 | AB3: =AB1-AB2 -> 12 | AD3: =AD1-AD2 -> 0 | AF3: =AF1-AF2 -> 0 | AH3: =AH1-AH2 -> 12
C5: 2026 год | E5: ЯНВАРЬ 2026 | G5: ФЕВРАЛЬ 2026 | I5: МАРТ 2026 | K5: 1 квартал 2026 | M5: АПРЕЛЬ 2026 | O5: МАЙ 2026 | Q5: ИЮНЬ 2026 | S5: 2 квартал 2026 | U5: ИЮЛЬ 2026 | W5: АВГУСТ 2026 | Y5: СЕНТЯБРЬ 2026 | AA5: 3 квартал 2026 | AC5: Октябрь 2026 | AE5: НОЯБРЬ 2026 | AG5: ДЕКАБРЬ 2026 | AI5: 4 квартал 2026
D6: поступления | E6: расходы | F6: поступления | G6: расходы | H6: поступления | I6: расходы | J6: поступления | K6: расходы | L6: поступления | M6: расходы | N6: поступления | O6: расходы | P6: поступления | Q6: расходы | R6: поступления | S6: расходы | T6: поступления | U6: расходы | V6: поступления | W6: расходы | X6: поступления | Y6: расходы | Z6: поступления | AA6: расходы | AB6: поступления | AC6: расходы | AD6: поступления | AE6: расходы | AF6: поступления | AG6: расходы | AH6: поступления | AI6: расходы
B7: РЕАЛИЗАЦИЯ | C7: =J7+R7+Z7+AH7 -> 71982438 | D7: =SUMIFS('CF BEST'!$C$9:$C1013, 'CF BEST'!$I$9:$I1013, B7,'CF BEST'!$F$9:$F1013, $E$5) -> 4788498.2 | E7: =SUMIFS('CF BEST'!$D$9:$D1013, 'CF BEST'!$I$9:$I1013, B7,'CF BEST'!$F$9:$F1013, $E$5) -> 0 | F7: =SUMIFS('CF BEST'!$C$9:$C1013, 'CF BEST'!$I$9:$I1013, B7,'CF BEST'!$F$9:$F1013, $G$5) -> 21363945 | G7: =SUMIFS('CF BEST'!$D$9:$D1013, 'CF BEST'!$I$9:$I1013, B7,'CF BEST'!$F$9:$F1013, $G$5) -> 0 | H7: =SUMIFS('CF BEST'!$C$9:$C1013, 'CF BEST'!$I$9:$I1013, B7,'CF BEST'!$F$9:$F1013, $I$5) -> 28475210 | I7: =SUMIFS('CF BEST'!$D$9:$D1013, 'CF BEST'!$I$9:$I1013, B7,'CF BEST'!$F$9:$F1013, $I$5) -> 0 | J7: =SUMIFS('CF BEST'!$C$9:$C1013, 'CF BEST'!$I$9:$I1013, B7,'CF BEST'!$F$9:$F1013, $K$5)+D7+F7+H7 -> 54627653 | K7: =SUMIFS('CF BEST'!$D$9:$D1013, 'CF BEST'!$I$9:$I1013, B7,'CF BEST'!$F$9:$F1013, $K$5)+E7+G7+I7 -> 0 | L7: =SUMIFS('CF BEST'!$C$9:$C1013, 'CF BEST'!$I$9:$I1013, B7,'CF BEST'!$F$9:$F1013, $M$5) -> 17354785 | M7: =SUMIFS('CF BEST'!$D$9:$D1013, 'CF BEST'!$I$9:$I1013, B7,'CF BEST'!$F$9:$F1013, $M$5) -> 0 | N7: =SUMIFS('CF BEST'!$C$9:$C1013, 'CF BEST'!$I$9:$I1013, B7,'CF BEST'!$F$9:$F1013, $O$5) -> 0 | O7: =SUMIFS('CF BEST'!$D$9:$D1013, 'CF BEST'!$I$9:$I1013, B7,'CF BEST'!$F$9:$F1013, $O$5) -> 0 | P7: =SUMIFS('CF BEST'!$C$9:$C1013, 'CF BEST'!$I$9:$I1013, B7,'CF BEST'!$F$9:$F1013, $Q$5) -> 0 | Q7: =SUMIFS('CF BEST'!$D$9:$D1013, 'CF BEST'!$I$9:$I1013, B7,'CF BEST'!$F$9:$F1013, $Q$5) -> 0 | R7: =SUMIFS('CF BEST'!$C$9:$C1013, 'CF BEST'!$I$9:$I1013, B7,'CF BEST'!$F$9:$F1013, $S$5)+L7+N7+P7 -> 17354785 | S7: =SUMIFS('CF BEST'!$D$9:$D1013, 'CF BEST'!$I$9:$I1013, B7,'CF BEST'!$F$9:$F1013, $S$5)+M7+O7+Q7 -> 0 | T7: =SUMIFS('CF BEST'!$C$9:$C1013, 'CF BEST'!$I$9:$I1013, B7,'CF BEST'!$F$9:$F1013, $U$5) -> 0 | U7: =SUMIFS('CF BEST'!$D$9:$D1013, 'CF BEST'!$I$9:$I1013, B7,'CF BEST'!$F$9:$F1013, $U$5) -> 0 | V7: =SUMIFS('CF BEST'!$C$9:$C1013, 'CF BEST'!$I$9:$I1013, B7,'CF BEST'!$F$9:$F1013, $W$5) -> 0 | W7: =SUMIFS('CF BEST'!$D$9:$D1013, 'CF BEST'!$I$9:$I1013, B7,'CF BEST'!$F$9:$F1013, $W$5) -> 0 | X7: =SUMIFS('CF BEST'!$C$9:$C1013, 'CF BEST'!$I$9:$I1013, B7,'CF BEST'!$F$9:$F1013, $Y$5) -> 0 | Y7: =SUMIFS('CF BEST'!$D$9:$D1013, 'CF BEST'!$I$9:$I1013, B7,'CF BEST'!$F$9:$F1013, $Y$5) -> 0 | Z7: =SUMIFS('CF BEST'!$C$9:$C1013, 'CF BEST'!$I$9:$I1013, B7,'CF BEST'!$F$9:$F1013, $AA$5)+T7+V7+X7 -> 0 | AA7: =SUMIFS('CF BEST'!$D$9:$D1013, 'CF BEST'!$I$9:$I1013, B7,'CF BEST'!$F$9:$F1013, $AA$5)+U7+W7+Y7 -> 0 | AB7: =SUMIFS('CF BEST'!$C$9:$C1013, 'CF BEST'!$I$9:$I1013, B7,'CF BEST'!$F$9:$F1013, $AC$5) -> 0 | AC7: =SUMIFS('CF BEST'!$D$9:$D1013, 'CF BEST'!$I$9:$I1013, B7,'CF BEST'!$F$9:$F1013, $AC$5) -> 0 | AD7: =SUMIFS('CF BEST'!$C$9:$C1013, 'CF BEST'!$I$9:$I1013, B7,'CF BEST'!$F$9:$F1013, $AE$5) -> 0 | AE7: =SUMIFS('CF BEST'!$D$9:$D1013, 'CF BEST'!$I$9:$I1013, B7,'CF BEST'!$F$9:$F1013, $AE$5) -> 0 | AF7: =SUMIFS('CF BEST'!$C$9:$C1013, 'CF BEST'!$I$9:$I1013, B7,'CF BEST'!$F$9:$F1013, $AG$5) -> 0 | AG7: =SUMIFS('CF BEST'!$D$9:$D1013, 'CF BEST'!$I$9:$I1013, B7,'CF BEST'!$F$9:$F1013, $AG$5) -> 0 | AH7: =SUMIFS('CF BEST'!$C$9:$C1013, 'CF BEST'!$I$9:$I1013, B7,'CF BEST'!$F$9:$F1013, $AI$5)+AB7+AD7+AF7 -> 0 | AI7: =SUMIFS('CF BEST'!$D$9:$D1013, 'CF BEST'!$I$9:$I1013, B7,'CF BEST'!$F$9:$F1013, $AI$5)+AC7+AE7+AG7 -> 0
A8: =C8/$C$7 -> 0.17799914 | B8: СК АГЕНТСКАЯ | C8: =K8+S8+AA8+AI8 -> 12812812 | D8: =SUMIFS('CF BEST'!$C$9:$C1013, 'CF BEST'!$I$9:$I1013, B8,'CF BEST'!$F$9:$F1013, $E$5) -> 0 | E8: =SUMIFS('CF BEST'!$D$9:$D1013, 'CF BEST'!$I$9:$I1013, B8,'CF BEST'!$F$9:$F1013, $E$5) -> 0 | F8: =SUMIFS('CF BEST'!$C$9:$C1013, 'CF BEST'!$I$9:$I1013, B8,'CF BEST'!$F$9:$F1013, $G$5) -> 0 | G8: =SUMIFS('CF BEST'!$D$9:$D1013, 'CF BEST'!$I$9:$I1013, B8,'CF BEST'!$F$9:$F1013, $G$5) -> 0 | H8: =SUMIFS('CF BEST'!$C$9:$C1013, 'CF BEST'!$I$9:$I1013, B8,'CF BEST'!$F$9:$F1013, $I$5) -> 0 | I8: =SUMIFS('CF BEST'!$D$9:$D1013, 'CF BEST'!$I$9:$I1013, B8,'CF BEST'!$F$9:$F1013, $I$5) -> 0 | J8: =SUMIFS('CF BEST'!$C$9:$C1013, 'CF BEST'!$I$9:$I1013, B8,'CF BEST'!$F$9:$F1013, $K$5)+D8+F8+H8 -> 0 | K8: =SUMIFS('CF BEST'!$D$9:$D1013, 'CF BEST'!$I$9:$I1013, B8,'CF BEST'!$F$9:$F1013, $K$5)+E8+G8+I8 -> 8208812.3 | L8: =SUMIFS('CF BEST'!$C$9:$C1013, 'CF BEST'!$I$9:$I1013, B8,'CF BEST'!$F$9:$F1013, $M$5) -> 0 | M8: =SUMIFS('CF BEST'!$D$9:$D1013, 'CF BEST'!$I$9:$I1013, B8,'CF BEST'!$F$9:$F1013, $M$5) -> 4604000 | N8: =SUMIFS('CF BEST'!$C$9:$C1013, 'CF BEST'!$I$9:$I1013, B8,'CF BEST'!$F$9:$F1013, $O$5) -> 0 | O8: =SUMIFS('CF BEST'!$D$9:$D1013, 'CF BEST'!$I$9:$I1013, B8,'CF BEST'!$F$9:$F1013, $O$5) -> 0 | P8: =SUMIFS('CF BEST'!$C$9:$C1013, 'CF BEST'!$I$9:$I1013, B8,'CF BEST'!$F$9:$F1013, $Q$5) -> 0 | Q8: =SUMIFS('CF BEST'!$D$9:$D1013, 'CF BEST'!$I$9:$I1013, B8,'CF BEST'!$F$9:$F1013, $Q$5) -> 0 | R8: =SUMIFS('CF BEST'!$C$9:$C1013, 'CF BEST'!$I$9:$I1013, B8,'CF BEST'!$F$9:$F1013, $S$5)+L8+N8+P8 -> 0 | S8: =SUMIFS('CF BEST'!$D$9:$D1013, 'CF BEST'!$I$9:$I1013, B8,'CF BEST'!$F$9:$F1013, $S$5)+M8+O8+Q8 -> 4604000 | T8: =SUMIFS('CF BEST'!$C$9:$C1013, 'CF BEST'!$I$9:$I1013, B8,'CF BEST'!$F$9:$F1013, $U$5) -> 0 | U8: =SUMIFS('CF BEST'!$D$9:$D1013, 'CF BEST'!$I$9:$I1013, B8,'CF BEST'!$F$9:$F1013, $U$5) -> 0 | V8: =SUMIFS('CF BEST'!$C$9:$C1013, 'CF BEST'!$I$9:$I1013, B8,'CF BEST'!$F$9:$F1013, $W$5) -> 0 | W8: =SUMIFS('CF BEST'!$D$9:$D1013, 'CF BEST'!$I$9:$I1013, B8,'CF BEST'!$F$9:$F1013, $W$5) -> 0 | X8: =SUMIFS('CF BEST'!$C$9:$C1013, 'CF BEST'!$I$9:$I1013, B8,'CF BEST'!$F$9:$F1013, $Y$5) -> 0 | Y8: =SUMIFS('CF BEST'!$D$9:$D1013, 'CF BEST'!$I$9:$I1013, B8,'CF BEST'!$F$9:$F1013, $Y$5) -> 0 | Z8: =SUMIFS('CF BEST'!$C$9:$C1013, 'CF BEST'!$I$9:$I1013, B8,'CF BEST'!$F$9:$F1013, $AA$5)+T8+V8+X8 -> 0 | AA8: =SUMIFS('CF BEST'!$D$9:$D1013, 'CF BEST'!$I$9:$I1013, B8,'CF BEST'!$F$9:$F1013, $AA$5)+U8+W8+Y8 -> 0 | AB8: =SUMIFS('CF BEST'!$C$9:$C1013, 'CF BEST'!$I$9:$I1013, B8,'CF BEST'!$F$9:$F1013, $AC$5) -> 0 | AC8: =SUMIFS('CF BEST'!$D$9:$D1013, 'CF BEST'!$I$9:$I1013, B8,'CF BEST'!$F$9:$F1013, $AC$5) -> 0 | AD8: =SUMIFS('CF BEST'!$C$9:$C1013, 'CF BEST'!$I$9:$I1013, B8,'CF BEST'!$F$9:$F1013, $AE$5) -> 0 | AE8: =SUMIFS('CF BEST'!$D$9:$D1013, 'CF BEST'!$I$9:$I1013, B8,'CF BEST'!$F$9:$F1013, $AE$5) -> 0 | AF8: =SUMIFS('CF BEST'!$C$9:$C1013, 'CF BEST'!$I$9:$I1013, B8,'CF BEST'!$F$9:$F1013, $AG$5) -> 0 | AG8: =SUMIFS('CF BEST'!$D$9:$D1013, 'CF BEST'!$I$9:$I1013, B8,'CF BEST'!$F$9:$F1013, $AG$5) -> 0 | AH8: =SUMIFS('CF BEST'!$C$9:$C1013, 'CF BEST'!$I$9:$I1013, B8,'CF BEST'!$F$9:$F1013, $AI$5)+AB8+AD8+AF8 -> 0 | AI8: =SUMIFS('CF BEST'!$D$9:$D1013, 'CF BEST'!$I$9:$I1013, B8,'CF BEST'!$F$9:$F1013, $AI$5)+AC8+AE8+AG8 -> 0
A9: =C9/$C$7 -> 0.0038203763 | B9: СК ПАРТНЕРСКАЯ | C9: =K9+S9+AA9+AI9 -> 275000 | D9: =SUMIFS('CF BEST'!$C$9:$C1013, 'CF BEST'!$I$9:$I1013, B9,'CF BEST'!$F$9:$F1013, $E$5) -> 0 | E9: =SUMIFS('CF BEST'!$D$9:$D1013, 'CF BEST'!$I$9:$I1013, B9,'CF BEST'!$F$9:$F1013, $E$5) -> 0 | F9: =SUMIFS('CF BEST'!$C$9:$C1013, 'CF BEST'!$I$9:$I1013, B9,'CF BEST'!$F$9:$F1013, $G$5) -> 0 | G9: =SUMIFS('CF BEST'!$D$9:$D1013, 'CF BEST'!$I$9:$I1013, B9,'CF BEST'!$F$9:$F1013, $G$5) -> 0 | H9: =SUMIFS('CF BEST'!$C$9:$C1013, 'CF BEST'!$I$9:$I1013, B9,'CF BEST'!$F$9:$F1013, $I$5) -> 0 | I9: =SUMIFS('CF BEST'!$D$9:$D1013, 'CF BEST'!$I$9:$I1013, B9,'CF BEST'!$F$9:$F1013, $I$5) -> 0 | J9: =SUMIFS('CF BEST'!$C$9:$C1013, 'CF BEST'!$I$9:$I1013, B9,'CF BEST'!$F$9:$F1013, $K$5)+D9+F9+H9 -> 0 | K9: =SUMIFS('CF BEST'!$D$9:$D1013, 'CF BEST'!$I$9:$I1013, B9,'CF BEST'!$F$9:$F1013, $K$5)+E9+G9+I9 -> 275000 | L9: =SUMIFS('CF BEST'!$C$9:$C1013, 'CF BEST'!$I$9:$I1013, B9,'CF BEST'!$F$9:$F1013, $M$5) -> 0 | M9: =SUMIFS('CF BEST'!$D$9:$D1013, 'CF BEST'!$I$9:$I1013, B9,'CF BEST'!$F$9:$F1013, $M$5) -> 0 | N9: =SUMIFS('CF BEST'!$C$9:$C1013, 'CF BEST'!$I$9:$I1013, B9,'CF BEST'!$F$9:$F1013, $O$5) -> 0 | O9: =SUMIFS('CF BEST'!$D$9:$D1013, 'CF BEST'!$I$9:$I1013, B9,'CF BEST'!$F$9:$F1013, $O$5) -> 0 | P9: =SUMIFS('CF BEST'!$C$9:$C1013, 'CF BEST'!$I$9:$I1013, B9,'CF BEST'!$F$9:$F1013, $Q$5) -> 0 | Q9: =SUMIFS('CF BEST'!$D$9:$D1013, 'CF BEST'!$I$9:$I1013, B9,'CF BEST'!$F$9:$F1013, $Q$5) -> 0 | R9: =SUMIFS('CF BEST'!$C$9:$C1013, 'CF BEST'!$I$9:$I1013, B9,'CF BEST'!$F$9:$F1013, $S$5)+L9+N9+P9 -> 0 | S9: =SUMIFS('CF BEST'!$D$9:$D1013, 'CF BEST'!$I$9:$I1013, B9,'CF BEST'!$F$9:$F1013, $S$5)+M9+O9+Q9 -> 0 | T9: =SUMIFS('CF BEST'!$C$9:$C1013, 'CF BEST'!$I$9:$I1013, B9,'CF BEST'!$F$9:$F1013, $U$5) -> 0 | U9: =SUMIFS('CF BEST'!$D$9:$D1013, 'CF BEST'!$I$9:$I1013, B9,'CF BEST'!$F$9:$F1013, $U$5) -> 0 | V9: =SUMIFS('CF BEST'!$C$9:$C1013, 'CF BEST'!$I$9:$I1013, B9,'CF BEST'!$F$9:$F1013, $W$5) -> 0 | W9: =SUMIFS('CF BEST'!$D$9:$D1013, 'CF BEST'!$I$9:$I1013, B9,'CF BEST'!$F$9:$F1013, $W$5) -> 0 | X9: =SUMIFS('CF BEST'!$C$9:$C1013, 'CF BEST'!$I$9:$I1013, B9,'CF BEST'!$F$9:$F1013, $Y$5) -> 0 | Y9: =SUMIFS('CF BEST'!$D$9:$D1013, 'CF BEST'!$I$9:$I1013, B9,'CF BEST'!$F$9:$F1013, $Y$5) -> 0 | Z9: =SUMIFS('CF BEST'!$C$9:$C1013, 'CF BEST'!$I$9:$I1013, B9,'CF BEST'!$F$9:$F1013, $AA$5)+T9+V9+X9 -> 0 | AA9: =SUMIFS('CF BEST'!$D$9:$D1013, 'CF BEST'!$I$9:$I1013, B9,'CF BEST'!$F$9:$F1013, $AA$5)+U9+W9+Y9 -> 0 | AB9: =SUMIFS('CF BEST'!$C$9:$C1013, 'CF BEST'!$I$9:$I1013, B9,'CF BEST'!$F$9:$F1013, $AC$5) -> 0 | AC9: =SUMIFS('CF BEST'!$D$9:$D1013, 'CF BEST'!$I$9:$I1013, B9,'CF BEST'!$F$9:$F1013, $AC$5) -> 0 | AD9: =SUMIFS('CF BEST'!$C$9:$C1013, 'CF BEST'!$I$9:$I1013, B9,'CF BEST'!$F$9:$F1013, $AE$5) -> 0 | AE9: =SUMIFS('CF BEST'!$D$9:$D1013, 'CF BEST'!$I$9:$I1013, B9,'CF BEST'!$F$9:$F1013, $AE$5) -> 0 | AF9: =SUMIFS('CF BEST'!$C$9:$C1013, 'CF BEST'!$I$9:$I1013, B9,'CF BEST'!$F$9:$F1013, $AG$5) -> 0 | AG9: =SUMIFS('CF BEST'!$D$9:$D1013, 'CF BEST'!$I$9:$I1013, B9,'CF BEST'!$F$9:$F1013, $AG$5) -> 0 | AH9: =SUMIFS('CF BEST'!$C$9:$C1013, 'CF BEST'!$I$9:$I1013, B9,'CF BEST'!$F$9:$F1013, $AI$5)+AB9+AD9+AF9 -> 0 | AI9: =SUMIFS('CF BEST'!$D$9:$D1013, 'CF BEST'!$I$9:$I1013, B9,'CF BEST'!$F$9:$F1013, $AI$5)+AC9+AE9+AG9 -> 0
A10: =C10/$C$7 -> 0.20966114 | B10: АПТЕКА | C10: =K10+S10+AA10+AI10 -> 15091920 | D10: =SUMIFS('CF BEST'!$C$9:$C1013, 'CF BEST'!$I$9:$I1013, B10,'CF BEST'!$F$9:$F1013, $E$5) -> 0 | E10: =SUMIFS('CF BEST'!$D$9:$D1013, 'CF BEST'!$I$9:$I1013, B10,'CF BEST'!$F$9:$F1013, $E$5) -> 1530063.2 | F10: =SUMIFS('CF BEST'!$C$9:$C1013, 'CF BEST'!$I$9:$I1013, B10,'CF BEST'!$F$9:$F1013, $G$5) -> 0 | G10: =SUMIFS('CF BEST'!$D$9:$D1013, 'CF BEST'!$I$9:$I1013, B10,'CF BEST'!$F$9:$F1013, $G$5) -> 3151697.2 | H10: =SUMIFS('CF BEST'!$C$9:$C1013, 'CF BEST'!$I$9:$I1013, B10,'CF BEST'!$F$9:$F1013, $I$5) -> 0 | I10: =SUMIFS('CF BEST'!$D$9:$D1013, 'CF BEST'!$I$9:$I1013, B10,'CF BEST'!$F$9:$F1013, $I$5) -> 6225997.1 | J10: =SUMIFS('CF BEST'!$C$9:$C1013, 'CF BEST'!$I$9:$I1013, B10,'CF BEST'!$F$9:$F1013, $K$5)+D10+F10+H10 -> 0 | K10: =SUMIFS('CF BEST'!$D$9:$D1013, 'CF BEST'!$I$9:$I1013, B10,'CF BEST'!$F$9:$F1013, $K$5)+E10+G10+I10 -> 10907758 | L10: =SUMIFS('CF BEST'!$C$9:$C1013, 'CF BEST'!$I$9:$I1013, B10,'CF BEST'!$F$9:$F1013, $M$5) -> 0 | M10: =SUMIFS('CF BEST'!$D$9:$D1013, 'CF BEST'!$I$9:$I1013, B10,'CF BEST'!$F$9:$F1013, $M$5) -> 2755386.2 | N10: =SUMIFS('CF BEST'!$C$9:$C1013, 'CF BEST'!$I$9:$I1013, B10,'CF BEST'!$F$9:$F1013, $O$5) -> 0 | O10: =SUMIFS('CF BEST'!$D$9:$D1013, 'CF BEST'!$I$9:$I1013, B10,'CF BEST'!$F$9:$F1013, $O$5) -> 1278776.6 | P10: =SUMIFS('CF BEST'!$C$9:$C1013, 'CF BEST'!$I$9:$I1013, B10,'CF BEST'!$F$9:$F1013, $Q$5) -> 0 | Q10: =SUMIFS('CF BEST'!$D$9:$D1013, 'CF BEST'!$I$9:$I1013, B10,'CF BEST'!$F$9:$F1013, $Q$5) -> 150000 | R10: =SUMIFS('CF BEST'!$C$9:$C1013, 'CF BEST'!$I$9:$I1013, B10,'CF BEST'!$F$9:$F1013, $S$5)+L10+N10+P10 -> 0 | S10: =SUMIFS('CF BEST'!$D$9:$D1013, 'CF BEST'!$I$9:$I1013, B10,'CF BEST'!$F$9:$F1013, $S$5)+M10+O10+Q10 -> 4184162.8 | T10: =SUMIFS('CF BEST'!$C$9:$C1013, 'CF BEST'!$I$9:$I1013, B10,'CF BEST'!$F$9:$F1013, $U$5) -> 0 | U10: =SUMIFS('CF BEST'!$D$9:$D1013, 'CF BEST'!$I$9:$I1013, B10,'CF BEST'!$F$9:$F1013, $U$5) -> 0 | V10: =SUMIFS('CF BEST'!$C$9:$C1013, 'CF BEST'!$I$9:$I1013, B10,'CF BEST'!$F$9:$F1013, $W$5) -> 0 | W10: =SUMIFS('CF BEST'!$D$9:$D1013, 'CF BEST'!$I$9:$I1013, B10,'CF BEST'!$F$9:$F1013, $W$5) -> 0 | X10: =SUMIFS('CF BEST'!$C$9:$C1013, 'CF BEST'!$I$9:$I1013, B10,'CF BEST'!$F$9:$F1013, $Y$5) -> 0 | Y10: =SUMIFS('CF BEST'!$D$9:$D1013, 'CF BEST'!$I$9:$I1013, B10,'CF BEST'!$F$9:$F1013, $Y$5) -> 0 | Z10: =SUMIFS('CF BEST'!$C$9:$C1013, 'CF BEST'!$I$9:$I1013, B10,'CF BEST'!$F$9:$F1013, $AA$5)+T10+V10+X10 -> 0 | AA10: =SUMIFS('CF BEST'!$D$9:$D1013, 'CF BEST'!$I$9:$I1013, B10,'CF BEST'!$F$9:$F1013, $AA$5)+U10+W10+Y10 -> 0 | AB10: =SUMIFS('CF BEST'!$C$9:$C1013, 'CF BEST'!$I$9:$I1013, B10,'CF BEST'!$F$9:$F1013, $AC$5) -> 0 | AC10: =SUMIFS('CF BEST'!$D$9:$D1013, 'CF BEST'!$I$9:$I1013, B10,'CF BEST'!$F$9:$F1013, $AC$5) -> 0 | AD10: =SUMIFS('CF BEST'!$C$9:$C1013, 'CF BEST'!$I$9:$I1013, B10,'CF BEST'!$F$9:$F1013, $AE$5) -> 0 | AE10: =SUMIFS('CF BEST'!$D$9:$D1013, 'CF BEST'!$I$9:$I1013, B10,'CF BEST'!$F$9:$F1013, $AE$5) -> 0 | AF10: =SUMIFS('CF BEST'!$C$9:$C1013, 'CF BEST'!$I$9:$I1013, B10,'CF BEST'!$F$9:$F1013, $AG$5) -> 0 | AG10: =SUMIFS('CF BEST'!$D$9:$D1013, 'CF BEST'!$I$9:$I1013, B10,'CF BEST'!$F$9:$F1013, $AG$5) -> 0 | AH10: =SUMIFS('CF BEST'!$C$9:$C1013, 'CF BEST'!$I$9:$I1013, B10,'CF BEST'!$F$9:$F1013, $AI$5)+AB10+AD10+AF10 -> 0 | AI10: =SUMIFS('CF BEST'!$D$9:$D1013, 'CF BEST'!$I$9:$I1013, B10,'CF BEST'!$F$9:$F1013, $AI$5)+AC10+AE10+AG10 -> 0
A11: =C11/$C$7 -> 0.072564764 | B11: ПАБЛИШЕР | C11: =K11+S11+AA11+AI11 -> 5223388.6 | D11: =SUMIFS('CF BEST'!$C$9:$C1013, 'CF BEST'!$I$9:$I1013, B11,'CF BEST'!$F$9:$F1013, $E$5) -> 0 | E11: =SUMIFS('CF BEST'!$D$9:$D1013, 'CF BEST'!$I$9:$I1013, B11,'CF BEST'!$F$9:$F1013, $E$5) -> 390512.39 | F11: =SUMIFS('CF BEST'!$C$9:$C1013, 'CF BEST'!$I$9:$I1013, B11,'CF BEST'!$F$9:$F1013, $G$5) -> 0 | G11: =SUMIFS('CF BEST'!$D$9:$D1013, 'CF BEST'!$I$9:$I1013, B11,'CF BEST'!$F$9:$F1013, $G$5) -> 2241357.2 | H11: =SUMIFS('CF BEST'!$C$9:$C1013, 'CF BEST'!$I$9:$I1013, B11,'CF BEST'!$F$9:$F1013, $I$5) -> 0 | I11: =SUMIFS('CF BEST'!$D$9:$D1013, 'CF BEST'!$I$9:$I1013, B11,'CF BEST'!$F$9:$F1013, $I$5) -> 2150444 | J11: =SUMIFS('CF BEST'!$C$9:$C1013, 'CF BEST'!$I$9:$I1013, B11,'CF BEST'!$F$9:$F1013, $K$5)+D11+F11+H11 -> 0 | K11: =SUMIFS('CF BEST'!$D$9:$D1013, 'CF BEST'!$I$9:$I1013, B11,'CF BEST'!$F$9:$F1013, $K$5)+E11+G11+I11 -> 4782313.5 | L11: =SUMIFS('CF BEST'!$C$9:$C1013, 'CF BEST'!$I$9:$I1013, B11,'CF BEST'!$F$9:$F1013, $M$5) -> 0 | M11: =SUMIFS('CF BEST'!$D$9:$D1013, 'CF BEST'!$I$9:$I1013, B11,'CF BEST'!$F$9:$F1013, $M$5) -> 441075.07 | N11: =SUMIFS('CF BEST'!$C$9:$C1013, 'CF BEST'!$I$9:$I1013, B11,'CF BEST'!$F$9:$F1013, $O$5) -> 0 | O11: =SUMIFS('CF BEST'!$D$9:$D1013, 'CF BEST'!$I$9:$I1013, B11,'CF BEST'!$F$9:$F1013, $O$5) -> 0 | P11: =SUMIFS('CF BEST'!$C$9:$C1013, 'CF BEST'!$I$9:$I1013, B11,'CF BEST'!$F$9:$F1013, $Q$5) -> 0 | Q11: =SUMIFS('CF BEST'!$D$9:$D1013, 'CF BEST'!$I$9:$I1013, B11,'CF BEST'!$F$9:$F1013, $Q$5) -> 0 | R11: =SUMIFS('CF BEST'!$C$9:$C1013, 'CF BEST'!$I$9:$I1013, B11,'CF BEST'!$F$9:$F1013, $S$5)+L11+N11+P11 -> 0 | S11: =SUMIFS('CF BEST'!$D$9:$D1013, 'CF BEST'!$I$9:$I1013, B11,'CF BEST'!$F$9:$F1013, $S$5)+M11+O11+Q11 -> 441075.07 | T11: =SUMIFS('CF BEST'!$C$9:$C1013, 'CF BEST'!$I$9:$I1013, B11,'CF BEST'!$F$9:$F1013, $U$5) -> 0 | U11: =SUMIFS('CF BEST'!$D$9:$D1013, 'CF BEST'!$I$9:$I1013, B11,'CF BEST'!$F$9:$F1013, $U$5) -> 0 | V11: =SUMIFS('CF BEST'!$C$9:$C1013, 'CF BEST'!$I$9:$I1013, B11,'CF BEST'!$F$9:$F1013, $W$5) -> 0 | W11: =SUMIFS('CF BEST'!$D$9:$D1013, 'CF BEST'!$I$9:$I1013, B11,'CF BEST'!$F$9:$F1013, $W$5) -> 0 | X11: =SUMIFS('CF BEST'!$C$9:$C1013, 'CF BEST'!$I$9:$I1013, B11,'CF BEST'!$F$9:$F1013, $Y$5) -> 0 | Y11: =SUMIFS('CF BEST'!$D$9:$D1013, 'CF BEST'!$I$9:$I1013, B11,'CF BEST'!$F$9:$F1013, $Y$5) -> 0 | Z11: =SUMIFS('CF BEST'!$C$9:$C1013, 'CF BEST'!$I$9:$I1013, B11,'CF BEST'!$F$9:$F1013, $AA$5)+T11+V11+X11 -> 0 | AA11: =SUMIFS('CF BEST'!$D$9:$D1013, 'CF BEST'!$I$9:$I1013, B11,'CF BEST'!$F$9:$F1013, $AA$5)+U11+W11+Y11 -> 0 | AB11: =SUMIFS('CF BEST'!$C$9:$C1013, 'CF BEST'!$I$9:$I1013, B11,'CF BEST'!$F$9:$F1013, $AC$5) -> 0 | AC11: =SUMIFS('CF BEST'!$D$9:$D1013, 'CF BEST'!$I$9:$I1013, B11,'CF BEST'!$F$9:$F1013, $AC$5) -> 0 | AD11: =SUMIFS('CF BEST'!$C$9:$C1013, 'CF BEST'!$I$9:$I1013, B11,'CF BEST'!$F$9:$F1013, $AE$5) -> 0 | AE11: =SUMIFS('CF BEST'!$D$9:$D1013, 'CF BEST'!$I$9:$I1013, B11,'CF BEST'!$F$9:$F1013, $AE$5) -> 0 | AF11: =SUMIFS('CF BEST'!$C$9:$C1013, 'CF BEST'!$I$9:$I1013, B11,'CF BEST'!$F$9:$F1013, $AG$5) -> 0 | AG11: =SUMIFS('CF BEST'!$D$9:$D1013, 'CF BEST'!$I$9:$I1013, B11,'CF BEST'!$F$9:$F1013, $AG$5) -> 0 | AH11: =SUMIFS('CF BEST'!$C$9:$C1013, 'CF BEST'!$I$9:$I1013, B11,'CF BEST'!$F$9:$F1013, $AI$5)+AB11+AD11+AF11 -> 0 | AI11: =SUMIFS('CF BEST'!$D$9:$D1013, 'CF BEST'!$I$9:$I1013, B11,'CF BEST'!$F$9:$F1013, $AI$5)+AC11+AE11+AG11 -> 0
A12: =C12/$C$7 -> 0.0072309304 | B12: БАННЕРЫ | C12: =K12+S12+AA12+AI12 -> 520500 | D12: =SUMIFS('CF BEST'!$C$9:$C1013, 'CF BEST'!$I$9:$I1013, B12,'CF BEST'!$F$9:$F1013, $E$5) -> 0 | E12: =SUMIFS('CF BEST'!$D$9:$D1013, 'CF BEST'!$I$9:$I1013, B12,'CF BEST'!$F$9:$F1013, $E$5) -> 140000 | F12: =SUMIFS('CF BEST'!$C$9:$C1013, 'CF BEST'!$I$9:$I1013, B12,'CF BEST'!$F$9:$F1013, $G$5) -> 0 | G12: =SUMIFS('CF BEST'!$D$9:$D1013, 'CF BEST'!$I$9:$I1013, B12,'CF BEST'!$F$9:$F1013, $G$5) -> 117000 | H12: =SUMIFS('CF BEST'!$C$9:$C1013, 'CF BEST'!$I$9:$I1013, B12,'CF BEST'!$F$9:$F1013, $I$5) -> 0 | I12: =SUMIFS('CF BEST'!$D$9:$D1013, 'CF BEST'!$I$9:$I1013, B12,'CF BEST'!$F$9:$F1013, $I$5) -> 143000 | J12: =SUMIFS('CF BEST'!$C$9:$C1013, 'CF BEST'!$I$9:$I1013, B12,'CF BEST'!$F$9:$F1013, $K$5)+D12+F12+H12 -> 0 | K12: =SUMIFS('CF BEST'!$D$9:$D1013, 'CF BEST'!$I$9:$I1013, B12,'CF BEST'!$F$9:$F1013, $K$5)+E12+G12+I12 -> 400000 | L12: =SUMIFS('CF BEST'!$C$9:$C1013, 'CF BEST'!$I$9:$I1013, B12,'CF BEST'!$F$9:$F1013, $M$5) -> 0 | M12: =SUMIFS('CF BEST'!$D$9:$D1013, 'CF BEST'!$I$9:$I1013, B12,'CF BEST'!$F$9:$F1013, $M$5) -> 120500 | N12: =SUMIFS('CF BEST'!$C$9:$C1013, 'CF BEST'!$I$9:$I1013, B12,'CF BEST'!$F$9:$F1013, $O$5) -> 0 | O12: =SUMIFS('CF BEST'!$D$9:$D1013, 'CF BEST'!$I$9:$I1013, B12,'CF BEST'!$F$9:$F1013, $O$5) -> 0 | P12: =SUMIFS('CF BEST'!$C$9:$C1013, 'CF BEST'!$I$9:$I1013, B12,'CF BEST'!$F$9:$F1013, $Q$5) -> 0 | Q12: =SUMIFS('CF BEST'!$D$9:$D1013, 'CF BEST'!$I$9:$I1013, B12,'CF BEST'!$F$9:$F1013, $Q$5) -> 0 | R12: =SUMIFS('CF BEST'!$C$9:$C1013, 'CF BEST'!$I$9:$I1013, B12,'CF BEST'!$F$9:$F1013, $S$5)+L12+N12+P12 -> 0 | S12: =SUMIFS('CF BEST'!$D$9:$D1013, 'CF BEST'!$I$9:$I1013, B12,'CF BEST'!$F$9:$F1013, $S$5)+M12+O12+Q12 -> 120500 | T12: =SUMIFS('CF BEST'!$C$9:$C1013, 'CF BEST'!$I$9:$I1013, B12,'CF BEST'!$F$9:$F1013, $U$5) -> 0 | U12: =SUMIFS('CF BEST'!$D$9:$D1013, 'CF BEST'!$I$9:$I1013, B12,'CF BEST'!$F$9:$F1013, $U$5) -> 0 | V12: =SUMIFS('CF BEST'!$C$9:$C1013, 'CF BEST'!$I$9:$I1013, B12,'CF BEST'!$F$9:$F1013, $W$5) -> 0 | W12: =SUMIFS('CF BEST'!$D$9:$D1013, 'CF BEST'!$I$9:$I1013, B12,'CF BEST'!$F$9:$F1013, $W$5) -> 0 | X12: =SUMIFS('CF BEST'!$C$9:$C1013, 'CF BEST'!$I$9:$I1013, B12,'CF BEST'!$F$9:$F1013, $Y$5) -> 0 | Y12: =SUMIFS('CF BEST'!$D$9:$D1013, 'CF BEST'!$I$9:$I1013, B12,'CF BEST'!$F$9:$F1013, $Y$5) -> 0 | Z12: =SUMIFS('CF BEST'!$C$9:$C1013, 'CF BEST'!$I$9:$I1013, B12,'CF BEST'!$F$9:$F1013, $AA$5)+T12+V12+X12 -> 0 | AA12: =SUMIFS('CF BEST'!$D$9:$D1013, 'CF BEST'!$I$9:$I1013, B12,'CF BEST'!$F$9:$F1013, $AA$5)+U12+W12+Y12 -> 0 | AB12: =SUMIFS('CF BEST'!$C$9:$C1013, 'CF BEST'!$I$9:$I1013, B12,'CF BEST'!$F$9:$F1013, $AC$5) -> 0 | AC12: =SUMIFS('CF BEST'!$D$9:$D1013, 'CF BEST'!$I$9:$I1013, B12,'CF BEST'!$F$9:$F1013, $AC$5) -> 0 | AD12: =SUMIFS('CF BEST'!$C$9:$C1013, 'CF BEST'!$I$9:$I1013, B12,'CF BEST'!$F$9:$F1013, $AE$5) -> 0 | AE12: =SUMIFS('CF BEST'!$D$9:$D1013, 'CF BEST'!$I$9:$I1013, B12,'CF BEST'!$F$9:$F1013, $AE$5) -> 0 | AF12: =SUMIFS('CF BEST'!$C$9:$C1013, 'CF BEST'!$I$9:$I1013, B12,'CF BEST'!$F$9:$F1013, $AG$5) -> 0 | AG12: =SUMIFS('CF BEST'!$D$9:$D1013, 'CF BEST'!$I$9:$I1013, B12,'CF BEST'!$F$9:$F1013, $AG$5) -> 0 | AH12: =SUMIFS('CF BEST'!$C$9:$C1013, 'CF BEST'!$I$9:$I1013, B12,'CF BEST'!$F$9:$F1013, $AI$5)+AB12+AD12+AF12 -> 0 | AI12: =SUMIFS('CF BEST'!$D$9:$D1013, 'CF BEST'!$I$9:$I1013, B12,'CF BEST'!$F$9:$F1013, $AI$5)+AC12+AE12+AG12 -> 0
A13: =C13/$C$7 -> 0.017496364 | B13: ОРД | C13: =K13+S13+AA13+AI13 -> 1259431 | D13: =SUMIFS('CF BEST'!$C$9:$C1013, 'CF BEST'!$I$9:$I1013, B13,'CF BEST'!$F$9:$F1013, $E$5) -> 0 | E13: =SUMIFS('CF BEST'!$D$9:$D1013, 'CF BEST'!$I$9:$I1013, B13,'CF BEST'!$F$9:$F1013, $E$5) -> 510511.04 | F13: =SUMIFS('CF BEST'!$C$9:$C1013, 'CF BEST'!$I$9:$I1013, B13,'CF BEST'!$F$9:$F1013, $G$5) -> 0 | G13: =SUMIFS('CF BEST'!$D$9:$D1013, 'CF BEST'!$I$9:$I1013, B13,'CF BEST'!$F$9:$F1013, $G$5) -> 56466.18 | H13: =SUMIFS('CF BEST'!$C$9:$C1013, 'CF BEST'!$I$9:$I1013, B13,'CF BEST'!$F$9:$F1013, $I$5) -> 0 | I13: =SUMIFS('CF BEST'!$D$9:$D1013, 'CF BEST'!$I$9:$I1013, B13,'CF BEST'!$F$9:$F1013, $I$5) -> 220838.1 | J13: =SUMIFS('CF BEST'!$C$9:$C1013, 'CF BEST'!$I$9:$I1013, B13,'CF BEST'!$F$9:$F1013, $K$5)+D13+F13+H13 -> 0 | K13: =SUMIFS('CF BEST'!$D$9:$D1013, 'CF BEST'!$I$9:$I1013, B13,'CF BEST'!$F$9:$F1013, $K$5)+E13+G13+I13 -> 787815.32 | L13: =SUMIFS('CF BEST'!$C$9:$C1013, 'CF BEST'!$I$9:$I1013, B13,'CF BEST'!$F$9:$F1013, $M$5) -> 0 | M13: =SUMIFS('CF BEST'!$D$9:$D1013, 'CF BEST'!$I$9:$I1013, B13,'CF BEST'!$F$9:$F1013, $M$5) -> 314484.06 | N13: =SUMIFS('CF BEST'!$C$9:$C1013, 'CF BEST'!$I$9:$I1013, B13,'CF BEST'!$F$9:$F1013, $O$5) -> 0 | O13: =SUMIFS('CF BEST'!$D$9:$D1013, 'CF BEST'!$I$9:$I1013, B13,'CF BEST'!$F$9:$F1013, $O$5) -> 157131.58 | P13: =SUMIFS('CF BEST'!$C$9:$C1013, 'CF BEST'!$I$9:$I1013, B13,'CF BEST'!$F$9:$F1013, $Q$5) -> 0 | Q13: =SUMIFS('CF BEST'!$D$9:$D1013, 'CF BEST'!$I$9:$I1013, B13,'CF BEST'!$F$9:$F1013, $Q$5) -> 0 | R13: =SUMIFS('CF BEST'!$C$9:$C1013, 'CF BEST'!$I$9:$I1013, B13,'CF BEST'!$F$9:$F1013, $S$5)+L13+N13+P13 -> 0 | S13: =SUMIFS('CF BEST'!$D$9:$D1013, 'CF BEST'!$I$9:$I1013, B13,'CF BEST'!$F$9:$F1013, $S$5)+M13+O13+Q13 -> 471615.64 | T13: =SUMIFS('CF BEST'!$C$9:$C1013, 'CF BEST'!$I$9:$I1013, B13,'CF BEST'!$F$9:$F1013, $U$5) -> 0 | U13: =SUMIFS('CF BEST'!$D$9:$D1013, 'CF BEST'!$I$9:$I1013, B13,'CF BEST'!$F$9:$F1013, $U$5) -> 0 | V13: =SUMIFS('CF BEST'!$C$9:$C1013, 'CF BEST'!$I$9:$I1013, B13,'CF BEST'!$F$9:$F1013, $W$5) -> 0 | W13: =SUMIFS('CF BEST'!$D$9:$D1013, 'CF BEST'!$I$9:$I1013, B13,'CF BEST'!$F$9:$F1013, $W$5) -> 0 | X13: =SUMIFS('CF BEST'!$C$9:$C1013, 'CF BEST'!$I$9:$I1013, B13,'CF BEST'!$F$9:$F1013, $Y$5) -> 0 | Y13: =SUMIFS('CF BEST'!$D$9:$D1013, 'CF BEST'!$I$9:$I1013, B13,'CF BEST'!$F$9:$F1013, $Y$5) -> 0 | Z13: =SUMIFS('CF BEST'!$C$9:$C1013, 'CF BEST'!$I$9:$I1013, B13,'CF BEST'!$F$9:$F1013, $AA$5)+T13+V13+X13 -> 0 | AA13: =SUMIFS('CF BEST'!$D$9:$D1013, 'CF BEST'!$I$9:$I1013, B13,'CF BEST'!$F$9:$F1013, $AA$5)+U13+W13+Y13 -> 0 | AB13: =SUMIFS('CF BEST'!$C$9:$C1013, 'CF BEST'!$I$9:$I1013, B13,'CF BEST'!$F$9:$F1013, $AC$5) -> 0 | AC13: =SUMIFS('CF BEST'!$D$9:$D1013, 'CF BEST'!$I$9:$I1013, B13,'CF BEST'!$F$9:$F1013, $AC$5) -> 0 | AD13: =SUMIFS('CF BEST'!$C$9:$C1013, 'CF BEST'!$I$9:$I1013, B13,'CF BEST'!$F$9:$F1013, $AE$5) -> 0 | AE13: =SUMIFS('CF BEST'!$D$9:$D1013, 'CF BEST'!$I$9:$I1013, B13,'CF BEST'!$F$9:$F1013, $AE$5) -> 0 | AF13: =SUMIFS('CF BEST'!$C$9:$C1013, 'CF BEST'!$I$9:$I1013, B13,'CF BEST'!$F$9:$F1013, $AG$5) -> 0 | AG13: =SUMIFS('CF BEST'!$D$9:$D1013, 'CF BEST'!$I$9:$I1013, B13,'CF BEST'!$F$9:$F1013, $AG$5) -> 0 | AH13: =SUMIFS('CF BEST'!$C$9:$C1013, 'CF BEST'!$I$9:$I1013, B13,'CF BEST'!$F$9:$F1013, $AI$5)+AB13+AD13+AF13 -> 0 | AI13: =SUMIFS('CF BEST'!$D$9:$D1013, 'CF BEST'!$I$9:$I1013, B13,'CF BEST'!$F$9:$F1013, $AI$5)+AC13+AE13+AG13 -> 0
A14: =C14/$C$7 -> 0.035681725 | B14: ПОДРЯДЧИКИ | C14: =K14+S14+AA14+AI14 -> 2568457.6 | D14: =SUMIFS('CF BEST'!$C$9:$C1013, 'CF BEST'!$I$9:$I1013, B14,'CF BEST'!$F$9:$F1013, $E$5) -> 0 | E14: =SUMIFS('CF BEST'!$D$9:$D1013, 'CF BEST'!$I$9:$I1013, B14,'CF BEST'!$F$9:$F1013, $E$5) -> 359279.44 | F14: =SUMIFS('CF BEST'!$C$9:$C1013, 'CF BEST'!$I$9:$I1013, B14,'CF BEST'!$F$9:$F1013, $G$5) -> 0 | G14: =SUMIFS('CF BEST'!$D$9:$D1013, 'CF BEST'!$I$9:$I1013, B14,'CF BEST'!$F$9:$F1013, $G$5) -> 664488.66 | H14: =SUMIFS('CF BEST'!$C$9:$C1013, 'CF BEST'!$I$9:$I1013, B14,'CF BEST'!$F$9:$F1013, $I$5) -> 0 | I14: =SUMIFS('CF BEST'!$D$9:$D1013, 'CF BEST'!$I$9:$I1013, B14,'CF BEST'!$F$9:$F1013, $I$5) -> 184185.32 | J14: =SUMIFS('CF BEST'!$C$9:$C1013, 'CF BEST'!$I$9:$I1013, B14,'CF BEST'!$F$9:$F1013, $K$5)+D14+F14+H14 -> 0 | K14: =SUMIFS('CF BEST'!$D$9:$D1013, 'CF BEST'!$I$9:$I1013, B14,'CF BEST'!$F$9:$F1013, $K$5)+E14+G14+I14 -> 1207953.4 | L14: =SUMIFS('CF BEST'!$C$9:$C1013, 'CF BEST'!$I$9:$I1013, B14,'CF BEST'!$F$9:$F1013, $M$5) -> 0 | M14: =SUMIFS('CF BEST'!$D$9:$D1013, 'CF BEST'!$I$9:$I1013, B14,'CF BEST'!$F$9:$F1013, $M$5) -> 1052953.8 | N14: =SUMIFS('CF BEST'!$C$9:$C1013, 'CF BEST'!$I$9:$I1013, B14,'CF BEST'!$F$9:$F1013, $O$5) -> 0 | O14: =SUMIFS('CF BEST'!$D$9:$D1013, 'CF BEST'!$I$9:$I1013, B14,'CF BEST'!$F$9:$F1013, $O$5) -> 307550.35 | P14: =SUMIFS('CF BEST'!$C$9:$C1013, 'CF BEST'!$I$9:$I1013, B14,'CF BEST'!$F$9:$F1013, $Q$5) -> 0 | Q14: =SUMIFS('CF BEST'!$D$9:$D1013, 'CF BEST'!$I$9:$I1013, B14,'CF BEST'!$F$9:$F1013, $Q$5) -> 0 | R14: =SUMIFS('CF BEST'!$C$9:$C1013, 'CF BEST'!$I$9:$I1013, B14,'CF BEST'!$F$9:$F1013, $S$5)+L14+N14+P14 -> 0 | S14: =SUMIFS('CF BEST'!$D$9:$D1013, 'CF BEST'!$I$9:$I1013, B14,'CF BEST'!$F$9:$F1013, $S$5)+M14+O14+Q14 -> 1360504.2 | T14: =SUMIFS('CF BEST'!$C$9:$C1013, 'CF BEST'!$I$9:$I1013, B14,'CF BEST'!$F$9:$F1013, $U$5) -> 0 | U14: =SUMIFS('CF BEST'!$D$9:$D1013, 'CF BEST'!$I$9:$I1013, B14,'CF BEST'!$F$9:$F1013, $U$5) -> 0 | V14: =SUMIFS('CF BEST'!$C$9:$C1013, 'CF BEST'!$I$9:$I1013, B14,'CF BEST'!$F$9:$F1013, $W$5) -> 0 | W14: =SUMIFS('CF BEST'!$D$9:$D1013, 'CF BEST'!$I$9:$I1013, B14,'CF BEST'!$F$9:$F1013, $W$5) -> 0 | X14: =SUMIFS('CF BEST'!$C$9:$C1013, 'CF BEST'!$I$9:$I1013, B14,'CF BEST'!$F$9:$F1013, $Y$5) -> 0 | Y14: =SUMIFS('CF BEST'!$D$9:$D1013, 'CF BEST'!$I$9:$I1013, B14,'CF BEST'!$F$9:$F1013, $Y$5) -> 0 | Z14: =SUMIFS('CF BEST'!$C$9:$C1013, 'CF BEST'!$I$9:$I1013, B14,'CF BEST'!$F$9:$F1013, $AA$5)+T14+V14+X14 -> 0 | AA14: =SUMIFS('CF BEST'!$D$9:$D1013, 'CF BEST'!$I$9:$I1013, B14,'CF BEST'!$F$9:$F1013, $AA$5)+U14+W14+Y14 -> 0 | AB14: =SUMIFS('CF BEST'!$C$9:$C1013, 'CF BEST'!$I$9:$I1013, B14,'CF BEST'!$F$9:$F1013, $AC$5) -> 0 | AC14: =SUMIFS('CF BEST'!$D$9:$D1013, 'CF BEST'!$I$9:$I1013, B14,'CF BEST'!$F$9:$F1013, $AC$5) -> 0 | AD14: =SUMIFS('CF BEST'!$C$9:$C1013, 'CF BEST'!$I$9:$I1013, B14,'CF BEST'!$F$9:$F1013, $AE$5) -> 0 | AE14: =SUMIFS('CF BEST'!$D$9:$D1013, 'CF BEST'!$I$9:$I1013, B14,'CF BEST'!$F$9:$F1013, $AE$5) -> 0 | AF14: =SUMIFS('CF BEST'!$C$9:$C1013, 'CF BEST'!$I$9:$I1013, B14,'CF BEST'!$F$9:$F1013, $AG$5) -> 0 | AG14: =SUMIFS('CF BEST'!$D$9:$D1013, 'CF BEST'!$I$9:$I1013, B14,'CF BEST'!$F$9:$F1013, $AG$5) -> 0 | AH14: =SUMIFS('CF BEST'!$C$9:$C1013, 'CF BEST'!$I$9:$I1013, B14,'CF BEST'!$F$9:$F1013, $AI$5)+AB14+AD14+AF14 -> 0 | AI14: =SUMIFS('CF BEST'!$D$9:$D1013, 'CF BEST'!$I$9:$I1013, B14,'CF BEST'!$F$9:$F1013, $AI$5)+AC14+AE14+AG14 -> 0
A15: =C15/$C$7 -> 0.31952385 | B15: СОТРУДНИКИ | C15: =SUM(C16:C21) -> 23000105 | D15: =SUM(D16:D21) -> 0 | E15: =SUM(E16:E21) -> 3154281.8 | F15: =SUM(F16:F21) -> 0 | G15: =SUM(G16:G21) -> 3888226.7 | H15: =SUM(H16:H21) -> 0 | I15: =SUM(I16:I21) -> 6541904.8 | J15: =SUM(J16:J21) -> 0 | ... AI15: =SUM(AI16:AI21) -> 0
A16: =C16/$C$7 -> 0.070140195 | B16: АВАНС | C16: =K16+S16+AA16+AI16 -> 5048862.2 | D16: =SUMIFS('CF BEST'!$C$9:$C1013, 'CF BEST'!$I$9:$I1013, B16,'CF BEST'!$F$9:$F1013, $E$5) -> 0 | E16: =SUMIFS('CF BEST'!$D$9:$D1013, 'CF BEST'!$I$9:$I1013, B16,'CF BEST'!$F$9:$F1013, $E$5) -> 0 | F16: =SUMIFS('CF BEST'!$C$9:$C1013, 'CF BEST'!$I$9:$I1013, B16,'CF BEST'!$F$9:$F1013, $G$5) -> 0 | G16: =SUMIFS('CF BEST'!$D$9:$D1013, 'CF BEST'!$I$9:$I1013, B16,'CF BEST'!$F$9:$F1013, $G$5) -> 1124709.7 | H16: =SUMIFS('CF BEST'!$C$9:$C1013, 'CF BEST'!$I$9:$I1013, B16,'CF BEST'!$F$9:$F1013, $I$5) -> 0 | I16: =SUMIFS('CF BEST'!$D$9:$D1013, 'CF BEST'!$I$9:$I1013, B16,'CF BEST'!$F$9:$F1013, $I$5) -> 1219879.6 | J16: =SUMIFS('CF BEST'!$C$9:$C1013, 'CF BEST'!$I$9:$I1013, B16,'CF BEST'!$F$9:$F1013, $K$5)+D16+F16+H16 -> 0 | K16: =SUMIFS('CF BEST'!$D$9:$D1013, 'CF BEST'!$I$9:$I1013, B16,'CF BEST'!$F$9:$F1013, $K$5)+E16+G16+I16 -> 2344589.3 | L16: =SUMIFS('CF BEST'!$C$9:$C1013, 'CF BEST'!$I$9:$I1013, B16,'CF BEST'!$F$9:$F1013, $M$5) -> 0 | M16: =SUMIFS('CF BEST'!$D$9:$D1013, 'CF BEST'!$I$9:$I1013, B16,'CF BEST'!$F$9:$F1013, $M$5) -> 1213990 | N16: =SUMIFS('CF BEST'!$C$9:$C1013, 'CF BEST'!$I$9:$I1013, B16,'CF BEST'!$F$9:$F1013, $O$5) -> 0 | O16: =SUMIFS('CF BEST'!$D$9:$D1013, 'CF BEST'!$I$9:$I1013, B16,'CF BEST'!$F$9:$F1013, $O$5) -> 1256867 | P16: =SUMIFS('CF BEST'!$C$9:$C1013, 'CF BEST'!$I$9:$I1013, B16,'CF BEST'!$F$9:$F1013, $Q$5) -> 0 | Q16: =SUMIFS('CF BEST'!$D$9:$D1013, 'CF BEST'!$I$9:$I1013, B16,'CF BEST'!$F$9:$F1013, $Q$5) -> 233415.92 | R16: =SUMIFS('CF BEST'!$C$9:$C1013, 'CF BEST'!$I$9:$I1013, B16,'CF BEST'!$F$9:$F1013, $S$5)+L16+N16+P16 -> 0 | S16: =SUMIFS('CF BEST'!$D$9:$D1013, 'CF BEST'!$I$9:$I1013, B16,'CF BEST'!$F$9:$F1013, $S$5)+M16+O16+Q16 -> 2704272.9 | T16: =SUMIFS('CF BEST'!$C$9:$C1013, 'CF BEST'!$I$9:$I1013, B16,'CF BEST'!$F$9:$F1013, $U$5) -> 0 | U16: =SUMIFS('CF BEST'!$D$9:$D1013, 'CF BEST'!$I$9:$I1013, B16,'CF BEST'!$F$9:$F1013, $U$5) -> 0 | V16: =SUMIFS('CF BEST'!$C$9:$C1013, 'CF BEST'!$I$9:$I1013, B16,'CF BEST'!$F$9:$F1013, $W$5) -> 0 | W16: =SUMIFS('CF BEST'!$D$9:$D1013, 'CF BEST'!$I$9:$I1013, B16,'CF BEST'!$F$9:$F1013, $W$5) -> 0 | X16: =SUMIFS('CF BEST'!$C$9:$C1013, 'CF BEST'!$I$9:$I1013, B16,'CF BEST'!$F$9:$F1013, $Y$5) -> 0 | Y16: =SUMIFS('CF BEST'!$D$9:$D1013, 'CF BEST'!$I$9:$I1013, B16,'CF BEST'!$F$9:$F1013, $Y$5) -> 0 | Z16: =SUMIFS('CF BEST'!$C$9:$C1013, 'CF BEST'!$I$9:$I1013, B16,'CF BEST'!$F$9:$F1013, $AA$5)+T16+V16+X16 -> 0 | AA16: =SUMIFS('CF BEST'!$D$9:$D1013, 'CF BEST'!$I$9:$I1013, B16,'CF BEST'!$F$9:$F1013, $AA$5)+U16+W16+Y16 -> 0 | AB16: =SUMIFS('CF BEST'!$C$9:$C1013, 'CF BEST'!$I$9:$I1013, B16,'CF BEST'!$F$9:$F1013, $AC$5) -> 0 | AC16: =SUMIFS('CF BEST'!$D$9:$D1013, 'CF BEST'!$I$9:$I1013, B16,'CF BEST'!$F$9:$F1013, $AC$5) -> 0 | AD16: =SUMIFS('CF BEST'!$C$9:$C1013, 'CF BEST'!$I$9:$I1013, B16,'CF BEST'!$F$9:$F1013, $AE$5) -> 0 | AE16: =SUMIFS('CF BEST'!$D$9:$D1013, 'CF BEST'!$I$9:$I1013, B16,'CF BEST'!$F$9:$F1013, $AE$5) -> 0 | AF16: =SUMIFS('CF BEST'!$C$9:$C1013, 'CF BEST'!$I$9:$I1013, B16,'CF BEST'!$F$9:$F1013, $AG$5) -> 0 | AG16: =SUMIFS('CF BEST'!$D$9:$D1013, 'CF BEST'!$I$9:$I1013, B16,'CF BEST'!$F$9:$F1013, $AG$5) -> 0 | AH16: =SUMIFS('CF BEST'!$C$9:$C1013, 'CF BEST'!$I$9:$I1013, B16,'CF BEST'!$F$9:$F1013, $AI$5)+AB16+AD16+AF16 -> 0 | AI16: =SUMIFS('CF BEST'!$D$9:$D1013, 'CF BEST'!$I$9:$I1013, B16,'CF BEST'!$F$9:$F1013, $AI$5)+AC16+AE16+AG16 -> 0
A17: =C17/$C$7 -> 0.13939586 | B17: ФОТ | C17: =K17+S17+AA17+AI17 -> 10034054 | D17: =SUMIFS('CF BEST'!$C$9:$C1013, 'CF BEST'!$I$9:$I1013, B17,'CF BEST'!$F$9:$F1013, $E$5) -> 0 | E17: =SUMIFS('CF BEST'!$D$9:$D1013, 'CF BEST'!$I$9:$I1013, B17,'CF BEST'!$F$9:$F1013, $E$5) -> 2046076.8 | F17: =SUMIFS('CF BEST'!$C$9:$C1013, 'CF BEST'!$I$9:$I1013, B17,'CF BEST'!$F$9:$F1013, $G$5) -> 0 | G17: =SUMIFS('CF BEST'!$D$9:$D1013, 'CF BEST'!$I$9:$I1013, B17,'CF BEST'!$F$9:$F1013, $G$5) -> 1973345.4 | H17: =SUMIFS('CF BEST'!$C$9:$C1013, 'CF BEST'!$I$9:$I1013, B17,'CF BEST'!$F$9:$F1013, $I$5) -> 0 | I17: =SUMIFS('CF BEST'!$D$9:$D1013, 'CF BEST'!$I$9:$I1013, B17,'CF BEST'!$F$9:$F1013, $I$5) -> 2009208.4 | J17: =SUMIFS('CF BEST'!$C$9:$C1013, 'CF BEST'!$I$9:$I1013, B17,'CF BEST'!$F$9:$F1013, $K$5)+D17+F17+H17 -> 0 | K17: =SUMIFS('CF BEST'!$D$9:$D1013, 'CF BEST'!$I$9:$I1013, B17,'CF BEST'!$F$9:$F1013, $K$5)+E17+G17+I17 -> 6028630.6 | L17: =SUMIFS('CF BEST'!$C$9:$C1013, 'CF BEST'!$I$9:$I1013, B17,'CF BEST'!$F$9:$F1013, $M$5) -> 0 | M17: =SUMIFS('CF BEST'!$D$9:$D1013, 'CF BEST'!$I$9:$I1013, B17,'CF BEST'!$F$9:$F1013, $M$5) -> 1897282.7 | N17: =SUMIFS('CF BEST'!$C$9:$C1013, 'CF BEST'!$I$9:$I1013, B17,'CF BEST'!$F$9:$F1013, $O$5) -> 0 | O17: =SUMIFS('CF BEST'!$D$9:$D1013, 'CF BEST'!$I$9:$I1013, B17,'CF BEST'!$F$9:$F1013, $O$5) -> 2074332.4 | P17: =SUMIFS('CF BEST'!$C$9:$C1013, 'CF BEST'!$I$9:$I1013, B17,'CF BEST'!$F$9:$F1013, $Q$5) -> 0 | Q17: =SUMIFS('CF BEST'!$D$9:$D1013, 'CF BEST'!$I$9:$I1013, B17,'CF BEST'!$F$9:$F1013, $Q$5) -> 33808.22 | R17: =SUMIFS('CF BEST'!$C$9:$C1013, 'CF BEST'!$I$9:$I1013, B17,'CF BEST'!$F$9:$F1013, $S$5)+L17+N17+P17 -> 0 | S17: =SUMIFS('CF BEST'!$D$9:$D1013, 'CF BEST'!$I$9:$I1013, B17,'CF BEST'!$F$9:$F1013, $S$5)+M17+O17+Q17 -> 4005423.3 | T17: =SUMIFS('CF BEST'!$C$9:$C1013, 'CF BEST'!$I$9:$I1013, B17,'CF BEST'!$F$9:$F1013, $U$5) -> 0 | U17: =SUMIFS('CF BEST'!$D$9:$D1013, 'CF BEST'!$I$9:$I1013, B17,'CF BEST'!$F$9:$F1013, $U$5) -> 0 | V17: =SUMIFS('CF BEST'!$C$9:$C1013, 'CF BEST'!$I$9:$I1013, B17,'CF BEST'!$F$9:$F1013, $W$5) -> 0 | W17: =SUMIFS('CF BEST'!$D$9:$D1013, 'CF BEST'!$I$9:$I1013, B17,'CF BEST'!$F$9:$F1013, $W$5) -> 0 | X17: =SUMIFS('CF BEST'!$C$9:$C1013, 'CF BEST'!$I$9:$I1013, B17,'CF BEST'!$F$9:$F1013, $Y$5) -> 0 | Y17: =SUMIFS('CF BEST'!$D$9:$D1013, 'CF BEST'!$I$9:$I1013, B17,'CF BEST'!$F$9:$F1013, $Y$5) -> 0 | Z17: =SUMIFS('CF BEST'!$C$9:$C1013, 'CF BEST'!$I$9:$I1013, B17,'CF BEST'!$F$9:$F1013, $AA$5)+T17+V17+X17 -> 0 | AA17: =SUMIFS('CF BEST'!$D$9:$D1013, 'CF BEST'!$I$9:$I1013, B17,'CF BEST'!$F$9:$F1013, $AA$5)+U17+W17+Y17 -> 0 | AB17: =SUMIFS('CF BEST'!$C$9:$C1013, 'CF BEST'!$I$9:$I1013, B17,'CF BEST'!$F$9:$F1013, $AC$5) -> 0 | AC17: =SUMIFS('CF BEST'!$D$9:$D1013, 'CF BEST'!$I$9:$I1013, B17,'CF BEST'!$F$9:$F1013, $AC$5) -> 0 | AD17: =SUMIFS('CF BEST'!$C$9:$C1013, 'CF BEST'!$I$9:$I1013, B17,'CF BEST'!$F$9:$F1013, $AE$5) -> 0 | AE17: =SUMIFS('CF BEST'!$D$9:$D1013, 'CF BEST'!$I$9:$I1013, B17,'CF BEST'!$F$9:$F1013, $AE$5) -> 0 | AF17: =SUMIFS('CF BEST'!$C$9:$C1013, 'CF BEST'!$I$9:$I1013, B17,'CF BEST'!$F$9:$F1013, $AG$5) -> 0 | AG17: =SUMIFS('CF BEST'!$D$9:$D1013, 'CF BEST'!$I$9:$I1013, B17,'CF BEST'!$F$9:$F1013, $AG$5) -> 0 | AH17: =SUMIFS('CF BEST'!$C$9:$C1013, 'CF BEST'!$I$9:$I1013, B17,'CF BEST'!$F$9:$F1013, $AI$5)+AB17+AD17+AF17 -> 0 | AI17: =SUMIFS('CF BEST'!$D$9:$D1013, 'CF BEST'!$I$9:$I1013, B17,'CF BEST'!$F$9:$F1013, $AI$5)+AC17+AE17+AG17 -> 0
A18: =C18/$C$7 -> 0.027992939 | B18: ПРЕМИЯ | C18: =K18+S18+AA18+AI18 -> 2015000 | D18: =SUMIFS('CF BEST'!$C$9:$C1013, 'CF BEST'!$I$9:$I1013, B18,'CF BEST'!$F$9:$F1013, $E$5) -> 0 | E18: =SUMIFS('CF BEST'!$D$9:$D1013, 'CF BEST'!$I$9:$I1013, B18,'CF BEST'!$F$9:$F1013, $E$5) -> 480000 | F18: =SUMIFS('CF BEST'!$C$9:$C1013, 'CF BEST'!$I$9:$I1013, B18,'CF BEST'!$F$9:$F1013, $G$5) -> 0 | G18: =SUMIFS('CF BEST'!$D$9:$D1013, 'CF BEST'!$I$9:$I1013, B18,'CF BEST'!$F$9:$F1013, $G$5) -> 400000 | H18: =SUMIFS('CF BEST'!$C$9:$C1013, 'CF BEST'!$I$9:$I1013, B18,'CF BEST'!$F$9:$F1013, $I$5) -> 0 | I18: =SUMIFS('CF BEST'!$D$9:$D1013, 'CF BEST'!$I$9:$I1013, B18,'CF BEST'!$F$9:$F1013, $I$5) -> 395000 | J18: =SUMIFS('CF BEST'!$C$9:$C1013, 'CF BEST'!$I$9:$I1013, B18,'CF BEST'!$F$9:$F1013, $K$5)+D18+F18+H18 -> 0 | K18: =SUMIFS('CF BEST'!$D$9:$D1013, 'CF BEST'!$I$9:$I1013, B18,'CF BEST'!$F$9:$F1013, $K$5)+E18+G18+I18 -> 1275000 | L18: =SUMIFS('CF BEST'!$C$9:$C1013, 'CF BEST'!$I$9:$I1013, B18,'CF BEST'!$F$9:$F1013, $M$5) -> 0 | M18: =SUMIFS('CF BEST'!$D$9:$D1013, 'CF BEST'!$I$9:$I1013, B18,'CF BEST'!$F$9:$F1013, $M$5) -> 380000 | N18: =SUMIFS('CF BEST'!$C$9:$C1013, 'CF BEST'!$I$9:$I1013, B18,'CF BEST'!$F$9:$F1013, $O$5) -> 0 | O18: =SUMIFS('CF BEST'!$D$9:$D1013, 'CF BEST'!$I$9:$I1013, B18,'CF BEST'!$F$9:$F1013, $O$5) -> 330000 | P18: =SUMIFS('CF BEST'!$C$9:$C1013, 'CF BEST'!$I$9:$I1013, B18,'CF BEST'!$F$9:$F1013, $Q$5) -> 0 | Q18: =SUMIFS('CF BEST'!$D$9:$D1013, 'CF BEST'!$I$9:$I1013, B18,'CF BEST'!$F$9:$F1013, $Q$5) -> 30000 | R18: =SUMIFS('CF BEST'!$C$9:$C1013, 'CF BEST'!$I$9:$I1013, B18,'CF BEST'!$F$9:$F1013, $S$5)+L18+N18+P18 -> 0 | S18: =SUMIFS('CF BEST'!$D$9:$D1013, 'CF BEST'!$I$9:$I1013, B18,'CF BEST'!$F$9:$F1013, $S$5)+M18+O18+Q18 -> 740000 | T18: =SUMIFS('CF BEST'!$C$9:$C1013, 'CF BEST'!$I$9:$I1013, B18,'CF BEST'!$F$9:$F1013, $U$5) -> 0 | U18: =SUMIFS('CF BEST'!$D$9:$D1013, 'CF BEST'!$I$9:$I1013, B18,'CF BEST'!$F$9:$F1013, $U$5) -> 0 | V18: =SUMIFS('CF BEST'!$C$9:$C1013, 'CF BEST'!$I$9:$I1013, B18,'CF BEST'!$F$9:$F1013, $W$5) -> 0 | W18: =SUMIFS('CF BEST'!$D$9:$D1013, 'CF BEST'!$I$9:$I1013, B18,'CF BEST'!$F$9:$F1013, $W$5) -> 0 | X18: =SUMIFS('CF BEST'!$C$9:$C1013, 'CF BEST'!$I$9:$I1013, B18,'CF BEST'!$F$9:$F1013, $Y$5) -> 0 | Y18: =SUMIFS('CF BEST'!$D$9:$D1013, 'CF BEST'!$I$9:$I1013, B18,'CF BEST'!$F$9:$F1013, $Y$5) -> 0 | Z18: =SUMIFS('CF BEST'!$C$9:$C1013, 'CF BEST'!$I$9:$I1013, B18,'CF BEST'!$F$9:$F1013, $AA$5)+T18+V18+X18 -> 0 | AA18: =SUMIFS('CF BEST'!$D$9:$D1013, 'CF BEST'!$I$9:$I1013, B18,'CF BEST'!$F$9:$F1013, $AA$5)+U18+W18+Y18 -> 0 | AB18: =SUMIFS('CF BEST'!$C$9:$C1013, 'CF BEST'!$I$9:$I1013, B18,'CF BEST'!$F$9:$F1013, $AC$5) -> 0 | AC18: =SUMIFS('CF BEST'!$D$9:$D1013, 'CF BEST'!$I$9:$I1013, B18,'CF BEST'!$F$9:$F1013, $AC$5) -> 0 | AD18: =SUMIFS('CF BEST'!$C$9:$C1013, 'CF BEST'!$I$9:$I1013, B18,'CF BEST'!$F$9:$F1013, $AE$5) -> 0 | AE18: =SUMIFS('CF BEST'!$D$9:$D1013, 'CF BEST'!$I$9:$I1013, B18,'CF BEST'!$F$9:$F1013, $AE$5) -> 0 | AF18: =SUMIFS('CF BEST'!$C$9:$C1013, 'CF BEST'!$I$9:$I1013, B18,'CF BEST'!$F$9:$F1013, $AG$5) -> 0 | AG18: =SUMIFS('CF BEST'!$D$9:$D1013, 'CF BEST'!$I$9:$I1013, B18,'CF BEST'!$F$9:$F1013, $AG$5) -> 0 | AH18: =SUMIFS('CF BEST'!$C$9:$C1013, 'CF BEST'!$I$9:$I1013, B18,'CF BEST'!$F$9:$F1013, $AI$5)+AB18+AD18+AF18 -> 0 | AI18: =SUMIFS('CF BEST'!$D$9:$D1013, 'CF BEST'!$I$9:$I1013, B18,'CF BEST'!$F$9:$F1013, $AI$5)+AC18+AE18+AG18 -> 0
A19: =C19/$C$7 -> 0.010000332 | B19: БОНУСЫ | C19: =K19+S19+AA19+AI19 -> 719848.3 | D19: =SUMIFS('CF BEST'!$C$9:$C1013, 'CF BEST'!$I$9:$I1013, B19,'CF BEST'!$F$9:$F1013, $E$5) -> 0 | E19: =SUMIFS('CF BEST'!$D$9:$D1013, 'CF BEST'!$I$9:$I1013, B19,'CF BEST'!$F$9:$F1013, $E$5) -> 0 | F19: =SUMIFS('CF BEST'!$C$9:$C1013, 'CF BEST'!$I$9:$I1013, B19,'CF BEST'!$F$9:$F1013, $G$5) -> 0 | G19: =SUMIFS('CF BEST'!$D$9:$D1013, 'CF BEST'!$I$9:$I1013, B19,'CF BEST'!$F$9:$F1013, $G$5) -> 0 | H19: =SUMIFS('CF BEST'!$C$9:$C1013, 'CF BEST'!$I$9:$I1013, B19,'CF BEST'!$F$9:$F1013, $I$5) -> 0 | I19: =SUMIFS('CF BEST'!$D$9:$D1013, 'CF BEST'!$I$9:$I1013, B19,'CF BEST'!$F$9:$F1013, $I$5) -> 85000 | J19: =SUMIFS('CF BEST'!$C$9:$C1013, 'CF BEST'!$I$9:$I1013, B19,'CF BEST'!$F$9:$F1013, $K$5)+D19+F19+H19 -> 0 | K19: =SUMIFS('CF BEST'!$D$9:$D1013, 'CF BEST'!$I$9:$I1013, B19,'CF BEST'!$F$9:$F1013, $K$5)+E19+G19+I19 -> 569848.3 | L19: =SUMIFS('CF BEST'!$C$9:$C1013, 'CF BEST'!$I$9:$I1013, B19,'CF BEST'!$F$9:$F1013, $M$5) -> 0 | M19: =SUMIFS('CF BEST'!$D$9:$D1013, 'CF BEST'!$I$9:$I1013, B19,'CF BEST'!$F$9:$F1013, $M$5) -> 150000 | N19: =SUMIFS('CF BEST'!$C$9:$C1013, 'CF BEST'!$I$9:$I1013, B19,'CF BEST'!$F$9:$F1013, $O$5) -> 0 | O19: =SUMIFS('CF BEST'!$D$9:$D1013, 'CF BEST'!$I$9:$I1013, B19,'CF BEST'!$F$9:$F1013, $O$5) -> 0 | P19: =SUMIFS('CF BEST'!$C$9:$C1013, 'CF BEST'!$I$9:$I1013, B19,'CF BEST'!$F$9:$F1013, $Q$5) -> 0 | Q19: =SUMIFS('CF BEST'!$D$9:$D1013, 'CF BEST'!$I$9:$I1013, B19,'CF BEST'!$F$9:$F1013, $Q$5) -> 0 | R19: =SUMIFS('CF BEST'!$C$9:$C1013, 'CF BEST'!$I$9:$I1013, B19,'CF BEST'!$F$9:$F1013, $S$5)+L19+N19+P19 -> 0 | S19: =SUMIFS('CF BEST'!$D$9:$D1013, 'CF BEST'!$I$9:$I1013, B19,'CF BEST'!$F$9:$F1013, $S$5)+M19+O19+Q19 -> 150000 | T19: =SUMIFS('CF BEST'!$C$9:$C1013, 'CF BEST'!$I$9:$I1013, B19,'CF BEST'!$F$9:$F1013, $U$5) -> 0 | U19: =SUMIFS('CF BEST'!$D$9:$D1013, 'CF BEST'!$I$9:$I1013, B19,'CF BEST'!$F$9:$F1013, $U$5) -> 0 | V19: =SUMIFS('CF BEST'!$C$9:$C1013, 'CF BEST'!$I$9:$I1013, B19,'CF BEST'!$F$9:$F1013, $W$5) -> 0 | W19: =SUMIFS('CF BEST'!$D$9:$D1013, 'CF BEST'!$I$9:$I1013, B19,'CF BEST'!$F$9:$F1013, $W$5) -> 0 | X19: =SUMIFS('CF BEST'!$C$9:$C1013, 'CF BEST'!$I$9:$I1013, B19,'CF BEST'!$F$9:$F1013, $Y$5) -> 0 | Y19: =SUMIFS('CF BEST'!$D$9:$D1013, 'CF BEST'!$I$9:$I1013, B19,'CF BEST'!$F$9:$F1013, $Y$5) -> 0 | Z19: =SUMIFS('CF BEST'!$C$9:$C1013, 'CF BEST'!$I$9:$I1013, B19,'CF BEST'!$F$9:$F1013, $AA$5)+T19+V19+X19 -> 0 | AA19: =SUMIFS('CF BEST'!$D$9:$D1013, 'CF BEST'!$I$9:$I1013, B19,'CF BEST'!$F$9:$F1013, $AA$5)+U19+W19+Y19 -> 0 | AB19: =SUMIFS('CF BEST'!$C$9:$C1013, 'CF BEST'!$I$9:$I1013, B19,'CF BEST'!$F$9:$F1013, $AC$5) -> 0 | AC19: =SUMIFS('CF BEST'!$D$9:$D1013, 'CF BEST'!$I$9:$I1013, B19,'CF BEST'!$F$9:$F1013, $AC$5) -> 0 | AD19: =SUMIFS('CF BEST'!$C$9:$C1013, 'CF BEST'!$I$9:$I1013, B19,'CF BEST'!$F$9:$F1013, $AE$5) -> 0 | AE19: =SUMIFS('CF BEST'!$D$9:$D1013, 'CF BEST'!$I$9:$I1013, B19,'CF BEST'!$F$9:$F1013, $AE$5) -> 0 | AF19: =SUMIFS('CF BEST'!$C$9:$C1013, 'CF BEST'!$I$9:$I1013, B19,'CF BEST'!$F$9:$F1013, $AG$5) -> 0 | AG19: =SUMIFS('CF BEST'!$D$9:$D1013, 'CF BEST'!$I$9:$I1013, B19,'CF BEST'!$F$9:$F1013, $AG$5) -> 0 | AH19: =SUMIFS('CF BEST'!$C$9:$C1013, 'CF BEST'!$I$9:$I1013, B19,'CF BEST'!$F$9:$F1013, $AI$5)+AB19+AD19+AF19 -> 0 | AI19: =SUMIFS('CF BEST'!$D$9:$D1013, 'CF BEST'!$I$9:$I1013, B19,'CF BEST'!$F$9:$F1013, $AI$5)+AC19+AE19+AG19 -> 0
A20: =C20/$C$7 -> 0.024355941 | B20: НАЛОГИ | НДФЛ | C20: =K20+S20+AA20+AI20 -> 1753200 | D20: =SUMIFS('CF BEST'!$C$9:$C1013, 'CF BEST'!$I$9:$I1013, B20,'CF BEST'!$F$9:$F1013, $E$5) -> 0 | E20: =SUMIFS('CF BEST'!$D$9:$D1013, 'CF BEST'!$I$9:$I1013, B20,'CF BEST'!$F$9:$F1013, $E$5) -> 0 | F20: =SUMIFS('CF BEST'!$C$9:$C1013, 'CF BEST'!$I$9:$I1013, B20,'CF BEST'!$F$9:$F1013, $G$5) -> 0 | G20: =SUMIFS('CF BEST'!$D$9:$D1013, 'CF BEST'!$I$9:$I1013, B20,'CF BEST'!$F$9:$F1013, $G$5) -> 367827 | H20: =SUMIFS('CF BEST'!$C$9:$C1013, 'CF BEST'!$I$9:$I1013, B20,'CF BEST'!$F$9:$F1013, $I$5) -> 0 | I20: =SUMIFS('CF BEST'!$D$9:$D1013, 'CF BEST'!$I$9:$I1013, B20,'CF BEST'!$F$9:$F1013, $I$5) -> 729894 | J20: =SUMIFS('CF BEST'!$C$9:$C1013, 'CF BEST'!$I$9:$I1013, B20,'CF BEST'!$F$9:$F1013, $K$5)+D20+F20+H20 -> 0 | K20: =SUMIFS('CF BEST'!$D$9:$D1013, 'CF BEST'!$I$9:$I1013, B20,'CF BEST'!$F$9:$F1013, $K$5)+E20+G20+I20 -> 1097721 | L20: =SUMIFS('CF BEST'!$C$9:$C1013, 'CF BEST'!$I$9:$I1013, B20,'CF BEST'!$F$9:$F1013, $M$5) -> 0 | M20: =SUMIFS('CF BEST'!$D$9:$D1013, 'CF BEST'!$I$9:$I1013, B20,'CF BEST'!$F$9:$F1013, $M$5) -> 181342 | N20: =SUMIFS('CF BEST'!$C$9:$C1013, 'CF BEST'!$I$9:$I1013, B20,'CF BEST'!$F$9:$F1013, $O$5) -> 0 | O20: =SUMIFS('CF BEST'!$D$9:$D1013, 'CF BEST'!$I$9:$I1013, B20,'CF BEST'!$F$9:$F1013, $O$5) -> 474137 | P20: =SUMIFS('CF BEST'!$C$9:$C1013, 'CF BEST'!$I$9:$I1013, B20,'CF BEST'!$F$9:$F1013, $Q$5) -> 0 | Q20: =SUMIFS('CF BEST'!$D$9:$D1013, 'CF BEST'!$I$9:$I1013, B20,'CF BEST'!$F$9:$F1013, $Q$5) -> 0 | R20: =SUMIFS('CF BEST'!$C$9:$C1013, 'CF BEST'!$I$9:$I1013, B20,'CF BEST'!$F$9:$F1013, $S$5)+L20+N20+P20 -> 0 | S20: =SUMIFS('CF BEST'!$D$9:$D1013, 'CF BEST'!$I$9:$I1013, B20,'CF BEST'!$F$9:$F1013, $S$5)+M20+O20+Q20 -> 655479 | T20: =SUMIFS('CF BEST'!$C$9:$C1013, 'CF BEST'!$I$9:$I1013, B20,'CF BEST'!$F$9:$F1013, $U$5) -> 0 | U20: =SUMIFS('CF BEST'!$D$9:$D1013, 'CF BEST'!$I$9:$I1013, B20,'CF BEST'!$F$9:$F1013, $U$5) -> 0 | V20: =SUMIFS('CF BEST'!$C$9:$C1013, 'CF BEST'!$I$9:$I1013, B20,'CF BEST'!$F$9:$F1013, $W$5) -> 0 | W20: =SUMIFS('CF BEST'!$D$9:$D1013, 'CF BEST'!$I$9:$I1013, B20,'CF BEST'!$F$9:$F1013, $W$5) -> 0 | X20: =SUMIFS('CF BEST'!$C$9:$C1013, 'CF BEST'!$I$9:$I1013, B20,'CF BEST'!$F$9:$F1013, $Y$5) -> 0 | Y20: =SUMIFS('CF BEST'!$D$9:$D1013, 'CF BEST'!$I$9:$I1013, B20,'CF BEST'!$F$9:$F1013, $Y$5) -> 0 | Z20: =SUMIFS('CF BEST'!$C$9:$C1013, 'CF BEST'!$I$9:$I1013, B20,'CF BEST'!$F$9:$F1013, $AA$5)+T20+V20+X20 -> 0 | AA20: =SUMIFS('CF BEST'!$D$9:$D1013, 'CF BEST'!$I$9:$I1013, B20,'CF BEST'!$F$9:$F1013, $AA$5)+U20+W20+Y20 -> 0 | AB20: =SUMIFS('CF BEST'!$C$9:$C1013, 'CF BEST'!$I$9:$I1013, B20,'CF BEST'!$F$9:$F1013, $AC$5) -> 0 | AC20: =SUMIFS('CF BEST'!$D$9:$D1013, 'CF BEST'!$I$9:$I1013, B20,'CF BEST'!$F$9:$F1013, $AC$5) -> 0 | AD20: =SUMIFS('CF BEST'!$C$9:$C1013, 'CF BEST'!$I$9:$I1013, B20,'CF BEST'!$F$9:$F1013, $AE$5) -> 0 | AE20: =SUMIFS('CF BEST'!$D$9:$D1013, 'CF BEST'!$I$9:$I1013, B20,'CF BEST'!$F$9:$F1013, $AE$5) -> 0 | AF20: =SUMIFS('CF BEST'!$C$9:$C1013, 'CF BEST'!$I$9:$I1013, B20,'CF BEST'!$F$9:$F1013, $AG$5) -> 0 | AG20: =SUMIFS('CF BEST'!$D$9:$D1013, 'CF BEST'!$I$9:$I1013, B20,'CF BEST'!$F$9:$F1013, $AG$5) -> 0 | AH20: =SUMIFS('CF BEST'!$C$9:$C1013, 'CF BEST'!$I$9:$I1013, B20,'CF BEST'!$F$9:$F1013, $AI$5)+AB20+AD20+AF20 -> 0 | AI20: =SUMIFS('CF BEST'!$D$9:$D1013, 'CF BEST'!$I$9:$I1013, B20,'CF BEST'!$F$9:$F1013, $AI$5)+AC20+AE20+AG20 -> 0
A21: =C21/$C$7 -> 0.047638578 | B21: НАЛОГИ | Страх.Взносы | C21: =K21+S21+AA21+AI21 -> 3429141 | D21: =SUMIFS('CF BEST'!$C$9:$C1013, 'CF BEST'!$I$9:$I1013, B21,'CF BEST'!$F$9:$F1013, $E$5) -> 0 | E21: =SUMIFS('CF BEST'!$D$9:$D1013, 'CF BEST'!$I$9:$I1013, B21,'CF BEST'!$F$9:$F1013, $E$5) -> 628205 | F21: =SUMIFS('CF BEST'!$C$9:$C1013, 'CF BEST'!$I$9:$I1013, B21,'CF BEST'!$F$9:$F1013, $G$5) -> 0 | G21: =SUMIFS('CF BEST'!$D$9:$D1013, 'CF BEST'!$I$9:$I1013, B21,'CF BEST'!$F$9:$F1013, $G$5) -> 22344.67 | H21: =SUMIFS('CF BEST'!$C$9:$C1013, 'CF BEST'!$I$9:$I1013, B21,'CF BEST'!$F$9:$F1013, $I$5) -> 0 | I21: =SUMIFS('CF BEST'!$D$9:$D1013, 'CF BEST'!$I$9:$I1013, B21,'CF BEST'!$F$9:$F1013, $I$5) -> 2102922.7 | J21: =SUMIFS('CF BEST'!$C$9:$C1013, 'CF BEST'!$I$9:$I1013, B21,'CF BEST'!$F$9:$F1013, $K$5)+D21+F21+H21 -> 0 | K21: =SUMIFS('CF BEST'!$D$9:$D1013, 'CF BEST'!$I$9:$I1013, B21,'CF BEST'!$F$9:$F1013, $K$5)+E21+G21+I21 -> 2753472.4 | L21: =SUMIFS('CF BEST'!$C$9:$C1013, 'CF BEST'!$I$9:$I1013, B21,'CF BEST'!$F$9:$F1013, $M$5) -> 0 | M21: =SUMIFS('CF BEST'!$D$9:$D1013, 'CF BEST'!$I$9:$I1013, B21,'CF BEST'!$F$9:$F1013, $M$5) -> 7270.73 | N21: =SUMIFS('CF BEST'!$C$9:$C1013, 'CF BEST'!$I$9:$I1013, B21,'CF BEST'!$F$9:$F1013, $O$5) -> 0 | O21: =SUMIFS('CF BEST'!$D$9:$D1013, 'CF BEST'!$I$9:$I1013, B21,'CF BEST'!$F$9:$F1013, $O$5) -> 668397.88 | P21: =SUMIFS('CF BEST'!$C$9:$C1013, 'CF BEST'!$I$9:$I1013, B21,'CF BEST'!$F$9:$F1013, $Q$5) -> 0 | Q21: =SUMIFS('CF BEST'!$D$9:$D1013, 'CF BEST'!$I$9:$I1013, B21,'CF BEST'!$F$9:$F1013, $Q$5) -> 0 | R21: =SUMIFS('CF BEST'!$C$9:$C1013, 'CF BEST'!$I$9:$I1013, B21,'CF BEST'!$F$9:$F1013, $S$5)+L21+N21+P21 -> 0 | S21: =SUMIFS('CF BEST'!$D$9:$D1013, 'CF BEST'!$I$9:$I1013, B21,'CF BEST'!$F$9:$F1013, $S$5)+M21+O21+Q21 -> 675668.61 | T21: =SUMIFS('CF BEST'!$C$9:$C1013, 'CF BEST'!$I$9:$I1013, B21,'CF BEST'!$F$9:$F1013, $U$5) -> 0 | U21: =SUMIFS('CF BEST'!$D$9:$D1013, 'CF BEST'!$I$9:$I1013, B21,'CF BEST'!$F$9:$F1013, $U$5) -> 0 | V21: =SUMIFS('CF BEST'!$C$9:$C1013, 'CF BEST'!$I$9:$I1013, B21,'CF BEST'!$F$9:$F1013, $W$5) -> 0 | W21: =SUMIFS('CF BEST'!$D$9:$D1013, 'CF BEST'!$I$9:$I1013, B21,'CF BEST'!$F$9:$F1013, $W$5) -> 0 | X21: =SUMIFS('CF BEST'!$C$9:$C1013, 'CF BEST'!$I$9:$I1013, B21,'CF BEST'!$F$9:$F1013, $Y$5) -> 0 | Y21: =SUMIFS('CF BEST'!$D$9:$D1013, 'CF BEST'!$I$9:$I1013, B21,'CF BEST'!$F$9:$F1013, $Y$5) -> 0 | Z21: =SUMIFS('CF BEST'!$C$9:$C1013, 'CF BEST'!$I$9:$I1013, B21,'CF BEST'!$F$9:$F1013, $AA$5)+T21+V21+X21 -> 0 | AA21: =SUMIFS('CF BEST'!$D$9:$D1013, 'CF BEST'!$I$9:$I1013, B21,'CF BEST'!$F$9:$F1013, $AA$5)+U21+W21+Y21 -> 0 | AB21: =SUMIFS('CF BEST'!$C$9:$C1013, 'CF BEST'!$I$9:$I1013, B21,'CF BEST'!$F$9:$F1013, $AC$5) -> 0 | AC21: =SUMIFS('CF BEST'!$D$9:$D1013, 'CF BEST'!$I$9:$I1013, B21,'CF BEST'!$F$9:$F1013, $AC$5) -> 0 | AD21: =SUMIFS('CF BEST'!$C$9:$C1013, 'CF BEST'!$I$9:$I1013, B21,'CF BEST'!$F$9:$F1013, $AE$5) -> 0 | AE21: =SUMIFS('CF BEST'!$D$9:$D1013, 'CF BEST'!$I$9:$I1013, B21,'CF BEST'!$F$9:$F1013, $AE$5) -> 0 | AF21: =SUMIFS('CF BEST'!$C$9:$C1013, 'CF BEST'!$I$9:$I1013, B21,'CF BEST'!$F$9:$F1013, $AG$5) -> 0 | AG21: =SUMIFS('CF BEST'!$D$9:$D1013, 'CF BEST'!$I$9:$I1013, B21,'CF BEST'!$F$9:$F1013, $AG$5) -> 0 | AH21: =SUMIFS('CF BEST'!$C$9:$C1013, 'CF BEST'!$I$9:$I1013, B21,'CF BEST'!$F$9:$F1013, $AI$5)+AB21+AD21+AF21 -> 0 | AI21: =SUMIFS('CF BEST'!$D$9:$D1013, 'CF BEST'!$I$9:$I1013, B21,'CF BEST'!$F$9:$F1013, $AI$5)+AC21+AE21+AG21 -> 0
A22: =C22/$C$7 -> 0.062019677 | B22: НАЛОГИ | C22: =K22+S22+AA22+AI22 -> 4464327.5 | D22: =SUMIFS('CF BEST'!$C$9:$C1013, 'CF BEST'!$I$9:$I1013, B22,'CF BEST'!$F$9:$F1013, $E$5) -> 0 | E22: =SUM(E23:E27) -> 0 | F22: =SUM(F23:F27) -> 0 | G22: =SUM(G23:G27) -> 181.17 | H22: =SUM(H23:H27) -> 0 | I22: =SUM(I23:I27) -> 7346 | J22: =SUM(J23:J27) -> 0 | K22: =SUM(K23:K27) -> 4358395.5 | L22: =SUM(L23:L27) -> 0 | ... AI22: =SUM(AI23:AI27) -> 0
A23: =C23/$C$7 -> 0.0056974592 | B23: НАЛОГИ | Прибыль | C23: =K23+S23+AA23+AI23 -> 410117 | D23: =SUMIFS('CF BEST'!$C$9:$C1013, 'CF BEST'!$I$9:$I1013, B23,'CF BEST'!$F$9:$F1013, $E$5) -> 0 | E23: =SUMIFS('CF BEST'!$D$9:$D1013, 'CF BEST'!$I$9:$I1013, B23,'CF BEST'!$F$9:$F1013, $E$5) -> 0 | F23: =SUMIFS('CF BEST'!$C$9:$C1013, 'CF BEST'!$I$9:$I1013, B23,'CF BEST'!$F$9:$F1013, $G$5) -> 0 | G23: =SUMIFS('CF BEST'!$D$9:$D1013, 'CF BEST'!$I$9:$I1013, B23,'CF BEST'!$F$9:$F1013, $G$5) -> 0 | H23: =SUMIFS('CF BEST'!$C$9:$C1013, 'CF BEST'!$I$9:$I1013, B23,'CF BEST'!$F$9:$F1013, $I$5) -> 0 | I23: =SUMIFS('CF BEST'!$D$9:$D1013, 'CF BEST'!$I$9:$I1013, B23,'CF BEST'!$F$9:$F1013, $I$5) -> 0 | J23: =SUMIFS('CF BEST'!$C$9:$C1013, 'CF BEST'!$I$9:$I1013, B23,'CF BEST'!$F$9:$F1013, $K$5)+D23+F23+H23 -> 0 | K23: =SUMIFS('CF BEST'!$D$9:$D1013, 'CF BEST'!$I$9:$I1013, B23,'CF BEST'!$F$9:$F1013, $K$5)+E23+G23+I23 -> 304185 | L23: =SUMIFS('CF BEST'!$C$9:$C1013, 'CF BEST'!$I$9:$I1013, B23,'CF BEST'!$F$9:$F1013, $M$5) -> 0 | M23: =SUMIFS('CF BEST'!$D$9:$D1013, 'CF BEST'!$I$9:$I1013, B23,'CF BEST'!$F$9:$F1013, $M$5) -> 0 | N23: =SUMIFS('CF BEST'!$C$9:$C1013, 'CF BEST'!$I$9:$I1013, B23,'CF BEST'!$F$9:$F1013, $O$5) -> 0 | O23: =SUMIFS('CF BEST'!$D$9:$D1013, 'CF BEST'!$I$9:$I1013, B23,'CF BEST'!$F$9:$F1013, $O$5) -> 0 | P23: =SUMIFS('CF BEST'!$C$9:$C1013, 'CF BEST'!$I$9:$I1013, B23,'CF BEST'!$F$9:$F1013, $Q$5) -> 0 | Q23: =SUMIFS('CF BEST'!$D$9:$D1013, 'CF BEST'!$I$9:$I1013, B23,'CF BEST'!$F$9:$F1013, $Q$5) -> 0 | R23: =SUMIFS('CF BEST'!$C$9:$C1013, 'CF BEST'!$I$9:$I1013, B23,'CF BEST'!$F$9:$F1013, $S$5)+L23+N23+P23 -> 0 | S23: =SUMIFS('CF BEST'!$D$9:$D1013, 'CF BEST'!$I$9:$I1013, B23,'CF BEST'!$F$9:$F1013, $S$5)+M23+O23+Q23 -> 105932 | T23: =SUMIFS('CF BEST'!$C$9:$C1013, 'CF BEST'!$I$9:$I1013, B23,'CF BEST'!$F$9:$F1013, $U$5) -> 0 | U23: =SUMIFS('CF BEST'!$D$9:$D1013, 'CF BEST'!$I$9:$I1013, B23,'CF BEST'!$F$9:$F1013, $U$5) -> 0 | V23: =SUMIFS('CF BEST'!$C$9:$C1013, 'CF BEST'!$I$9:$I1013, B23,'CF BEST'!$F$9:$F1013, $W$5) -> 0 | W23: =SUMIFS('CF BEST'!$D$9:$D1013, 'CF BEST'!$I$9:$I1013, B23,'CF BEST'!$F$9:$F1013, $W$5) -> 0 | X23: =SUMIFS('CF BEST'!$C$9:$C1013, 'CF BEST'!$I$9:$I1013, B23,'CF BEST'!$F$9:$F1013, $Y$5) -> 0 | Y23: =SUMIFS('CF BEST'!$D$9:$D1013, 'CF BEST'!$I$9:$I1013, B23,'CF BEST'!$F$9:$F1013, $Y$5) -> 0 | Z23: =SUMIFS('CF BEST'!$C$9:$C1013, 'CF BEST'!$I$9:$I1013, B23,'CF BEST'!$F$9:$F1013, $AA$5)+T23+V23+X23 -> 0 | AA23: =SUMIFS('CF BEST'!$D$9:$D1013, 'CF BEST'!$I$9:$I1013, B23,'CF BEST'!$F$9:$F1013, $AA$5)+U23+W23+Y23 -> 0 | AB23: =SUMIFS('CF BEST'!$C$9:$C1013, 'CF BEST'!$I$9:$I1013, B23,'CF BEST'!$F$9:$F1013, $AC$5) -> 0 | AC23: =SUMIFS('CF BEST'!$D$9:$D1013, 'CF BEST'!$I$9:$I1013, B23,'CF BEST'!$F$9:$F1013, $AC$5) -> 0 | AD23: =SUMIFS('CF BEST'!$C$9:$C1013, 'CF BEST'!$I$9:$I1013, B23,'CF BEST'!$F$9:$F1013, $AE$5) -> 0 | AE23: =SUMIFS('CF BEST'!$D$9:$D1013, 'CF BEST'!$I$9:$I1013, B23,'CF BEST'!$F$9:$F1013, $AE$5) -> 0 | AF23: =SUMIFS('CF BEST'!$C$9:$C1013, 'CF BEST'!$I$9:$I1013, B23,'CF BEST'!$F$9:$F1013, $AG$5) -> 0 | AG23: =SUMIFS('CF BEST'!$D$9:$D1013, 'CF BEST'!$I$9:$I1013, B23,'CF BEST'!$F$9:$F1013, $AG$5) -> 0 | AH23: =SUMIFS('CF BEST'!$C$9:$C1013, 'CF BEST'!$I$9:$I1013, B23,'CF BEST'!$F$9:$F1013, $AI$5)+AB23+AD23+AF23 -> 0 | AI23: =SUMIFS('CF BEST'!$D$9:$D1013, 'CF BEST'!$I$9:$I1013, B23,'CF BEST'!$F$9:$F1013, $AI$5)+AC23+AE23+AG23 -> 0
A24: =C24/$C$7 -> 2.5168639e-06 | B24: НАЛОГИ | Пени | C24: =K24+S24+AA24+AI24 -> 181.17 | D24: =SUMIFS('CF BEST'!$C$9:$C1013, 'CF BEST'!$I$9:$I1013, B24,'CF BEST'!$F$9:$F1013, $E$5) -> 0 | E24: =SUMIFS('CF BEST'!$D$9:$D1013, 'CF BEST'!$I$9:$I1013, B24,'CF BEST'!$F$9:$F1013, $E$5) -> 0 | F24: =SUMIFS('CF BEST'!$C$9:$C1013, 'CF BEST'!$I$9:$I1013, B24,'CF BEST'!$F$9:$F1013, $G$5) -> 0 | G24: =SUMIFS('CF BEST'!$D$9:$D1013, 'CF BEST'!$I$9:$I1013, B24,'CF BEST'!$F$9:$F1013, $G$5) -> 181.17 | H24: =SUMIFS('CF BEST'!$C$9:$C1013, 'CF BEST'!$I$9:$I1013, B24,'CF BEST'!$F$9:$F1013, $I$5) -> 0 | I24: =SUMIFS('CF BEST'!$D$9:$D1013, 'CF BEST'!$I$9:$I1013, B24,'CF BEST'!$F$9:$F1013, $I$5) -> 0 | J24: =SUMIFS('CF BEST'!$C$9:$C1013, 'CF BEST'!$I$9:$I1013, B24,'CF BEST'!$F$9:$F1013, $K$5)+D24+F24+H24 -> 0 | K24: =SUMIFS('CF BEST'!$D$9:$D1013, 'CF BEST'!$I$9:$I1013, B24,'CF BEST'!$F$9:$F1013, $K$5)+E24+G24+I24 -> 181.17 | L24: =SUMIFS('CF BEST'!$C$9:$C1013, 'CF BEST'!$I$9:$I1013, B24,'CF BEST'!$F$9:$F1013, $M$5) -> 0 | M24: =SUMIFS('CF BEST'!$D$9:$D1013, 'CF BEST'!$I$9:$I1013, B24,'CF BEST'!$F$9:$F1013, $M$5) -> 0 | N24: =SUMIFS('CF BEST'!$C$9:$C1013, 'CF BEST'!$I$9:$I1013, B24,'CF BEST'!$F$9:$F1013, $O$5) -> 0 | O24: =SUMIFS('CF BEST'!$D$9:$D1013, 'CF BEST'!$I$9:$I1013, B24,'CF BEST'!$F$9:$F1013, $O$5) -> 0 | P24: =SUMIFS('CF BEST'!$C$9:$C1013, 'CF BEST'!$I$9:$I1013, B24,'CF BEST'!$F$9:$F1013, $Q$5) -> 0 | Q24: =SUMIFS('CF BEST'!$D$9:$D1013, 'CF BEST'!$I$9:$I1013, B24,'CF BEST'!$F$9:$F1013, $Q$5) -> 0 | R24: =SUMIFS('CF BEST'!$C$9:$C1013, 'CF BEST'!$I$9:$I1013, B24,'CF BEST'!$F$9:$F1013, $S$5)+L24+N24+P24 -> 0 | S24: =SUMIFS('CF BEST'!$D$9:$D1013, 'CF BEST'!$I$9:$I1013, B24,'CF BEST'!$F$9:$F1013, $S$5)+M24+O24+Q24 -> 0 | T24: =SUMIFS('CF BEST'!$C$9:$C1013, 'CF BEST'!$I$9:$I1013, B24,'CF BEST'!$F$9:$F1013, $U$5) -> 0 | U24: =SUMIFS('CF BEST'!$D$9:$D1013, 'CF BEST'!$I$9:$I1013, B24,'CF BEST'!$F$9:$F1013, $U$5) -> 0 | V24: =SUMIFS('CF BEST'!$C$9:$C1013, 'CF BEST'!$I$9:$I1013, B24,'CF BEST'!$F$9:$F1013, $W$5) -> 0 | W24: =SUMIFS('CF BEST'!$D$9:$D1013, 'CF BEST'!$I$9:$I1013, B24,'CF BEST'!$F$9:$F1013, $W$5) -> 0 | X24: =SUMIFS('CF BEST'!$C$9:$C1013, 'CF BEST'!$I$9:$I1013, B24,'CF BEST'!$F$9:$F1013, $Y$5) -> 0 | Y24: =SUMIFS('CF BEST'!$D$9:$D1013, 'CF BEST'!$I$9:$I1013, B24,'CF BEST'!$F$9:$F1013, $Y$5) -> 0 | Z24: =SUMIFS('CF BEST'!$C$9:$C1013, 'CF BEST'!$I$9:$I1013, B24,'CF BEST'!$F$9:$F1013, $AA$5)+T24+V24+X24 -> 0 | AA24: =SUMIFS('CF BEST'!$D$9:$D1013, 'CF BEST'!$I$9:$I1013, B24,'CF BEST'!$F$9:$F1013, $AA$5)+U24+W24+Y24 -> 0 | AB24: =SUMIFS('CF BEST'!$C$9:$C1013, 'CF BEST'!$I$9:$I1013, B24,'CF BEST'!$F$9:$F1013, $AC$5) -> 0 | AC24: =SUMIFS('CF BEST'!$D$9:$D1013, 'CF BEST'!$I$9:$I1013, B24,'CF BEST'!$F$9:$F1013, $AC$5) -> 0 | AD24: =SUMIFS('CF BEST'!$C$9:$C1013, 'CF BEST'!$I$9:$I1013, B24,'CF BEST'!$F$9:$F1013, $AE$5) -> 0 | AE24: =SUMIFS('CF BEST'!$D$9:$D1013, 'CF BEST'!$I$9:$I1013, B24,'CF BEST'!$F$9:$F1013, $AE$5) -> 0 | AF24: =SUMIFS('CF BEST'!$C$9:$C1013, 'CF BEST'!$I$9:$I1013, B24,'CF BEST'!$F$9:$F1013, $AG$5) -> 0 | AG24: =SUMIFS('CF BEST'!$D$9:$D1013, 'CF BEST'!$I$9:$I1013, B24,'CF BEST'!$F$9:$F1013, $AG$5) -> 0 | AH24: =SUMIFS('CF BEST'!$C$9:$C1013, 'CF BEST'!$I$9:$I1013, B24,'CF BEST'!$F$9:$F1013, $AI$5)+AB24+AD24+AF24 -> 0 | AI24: =SUMIFS('CF BEST'!$D$9:$D1013, 'CF BEST'!$I$9:$I1013, B24,'CF BEST'!$F$9:$F1013, $AI$5)+AC24+AE24+AG24 -> 0
A25: =C25/$C$7 -> 0.045979285 | B25: НАЛОГИ | НДС | C25: =K25+S25+AA25+AI25 -> 3309701 | D25: =SUMIFS('CF BEST'!$C$9:$C1013, 'CF BEST'!$I$9:$I1013, B25,'CF BEST'!$F$9:$F1013, $E$5) -> 0 | E25: =SUMIFS('CF BEST'!$D$9:$D1013, 'CF BEST'!$I$9:$I1013, B25,'CF BEST'!$F$9:$F1013, $E$5) -> 0 | F25: =SUMIFS('CF BEST'!$C$9:$C1013, 'CF BEST'!$I$9:$I1013, B25,'CF BEST'!$F$9:$F1013, $G$5) -> 0 | G25: =SUMIFS('CF BEST'!$D$9:$D1013, 'CF BEST'!$I$9:$I1013, B25,'CF BEST'!$F$9:$F1013, $G$5) -> 0 | H25: =SUMIFS('CF BEST'!$C$9:$C1013, 'CF BEST'!$I$9:$I1013, B25,'CF BEST'!$F$9:$F1013, $I$5) -> 0 | I25: =SUMIFS('CF BEST'!$D$9:$D1013, 'CF BEST'!$I$9:$I1013, B25,'CF BEST'!$F$9:$F1013, $I$5) -> 0 | J25: =SUMIFS('CF BEST'!$C$9:$C1013, 'CF BEST'!$I$9:$I1013, B25,'CF BEST'!$F$9:$F1013, $K$5)+D25+F25+H25 -> 0 | K25: =SUMIFS('CF BEST'!$D$9:$D1013, 'CF BEST'!$I$9:$I1013, B25,'CF BEST'!$F$9:$F1013, $K$5)+E25+G25+I25 -> 3309701 | L25: =SUMIFS('CF BEST'!$C$9:$C1013, 'CF BEST'!$I$9:$I1013, B25,'CF BEST'!$F$9:$F1013, $M$5) -> 0 | M25: =SUMIFS('CF BEST'!$D$9:$D1013, 'CF BEST'!$I$9:$I1013, B25,'CF BEST'!$F$9:$F1013, $M$5) -> 0 | N25: =SUMIFS('CF BEST'!$C$9:$C1013, 'CF BEST'!$I$9:$I1013, B25,'CF BEST'!$F$9:$F1013, $O$5) -> 0 | O25: =SUMIFS('CF BEST'!$D$9:$D1013, 'CF BEST'!$I$9:$I1013, B25,'CF BEST'!$F$9:$F1013, $O$5) -> 0 | P25: =SUMIFS('CF BEST'!$C$9:$C1013, 'CF BEST'!$I$9:$I1013, B25,'CF BEST'!$F$9:$F1013, $Q$5) -> 0 | Q25: =SUMIFS('CF BEST'!$D$9:$D1013, 'CF BEST'!$I$9:$I1013, B25,'CF BEST'!$F$9:$F1013, $Q$5) -> 0 | R25: =SUMIFS('CF BEST'!$C$9:$C1013, 'CF BEST'!$I$9:$I1013, B25,'CF BEST'!$F$9:$F1013, $S$5)+L25+N25+P25 -> 0 | S25: =SUMIFS('CF BEST'!$D$9:$D1013, 'CF BEST'!$I$9:$I1013, B25,'CF BEST'!$F$9:$F1013, $S$5)+M25+O25+Q25 -> 0 | T25: =SUMIFS('CF BEST'!$C$9:$C1013, 'CF BEST'!$I$9:$I1013, B25,'CF BEST'!$F$9:$F1013, $U$5) -> 0 | U25: =SUMIFS('CF BEST'!$D$9:$D1013, 'CF BEST'!$I$9:$I1013, B25,'CF BEST'!$F$9:$F1013, $U$5) -> 0 | V25: =SUMIFS('CF BEST'!$C$9:$C1013, 'CF BEST'!$I$9:$I1013, B25,'CF BEST'!$F$9:$F1013, $W$5) -> 0 | W25: =SUMIFS('CF BEST'!$D$9:$D1013, 'CF BEST'!$I$9:$I1013, B25,'CF BEST'!$F$9:$F1013, $W$5) -> 0 | X25: =SUMIFS('CF BEST'!$C$9:$C1013, 'CF BEST'!$I$9:$I1013, B25,'CF BEST'!$F$9:$F1013, $Y$5) -> 0 | Y25: =SUMIFS('CF BEST'!$D$9:$D1013, 'CF BEST'!$I$9:$I1013, B25,'CF BEST'!$F$9:$F1013, $Y$5) -> 0 | Z25: =SUMIFS('CF BEST'!$C$9:$C1013, 'CF BEST'!$I$9:$I1013, B25,'CF BEST'!$F$9:$F1013, $AA$5)+T25+V25+X25 -> 0 | AA25: =SUMIFS('CF BEST'!$D$9:$D1013, 'CF BEST'!$I$9:$I1013, B25,'CF BEST'!$F$9:$F1013, $AA$5)+U25+W25+Y25 -> 0 | AB25: =SUMIFS('CF BEST'!$C$9:$C1013, 'CF BEST'!$I$9:$I1013, B25,'CF BEST'!$F$9:$F1013, $AC$5) -> 0 | AC25: =SUMIFS('CF BEST'!$D$9:$D1013, 'CF BEST'!$I$9:$I1013, B25,'CF BEST'!$F$9:$F1013, $AC$5) -> 0 | AD25: =SUMIFS('CF BEST'!$C$9:$C1013, 'CF BEST'!$I$9:$I1013, B25,'CF BEST'!$F$9:$F1013, $AE$5) -> 0 | AE25: =SUMIFS('CF BEST'!$D$9:$D1013, 'CF BEST'!$I$9:$I1013, B25,'CF BEST'!$F$9:$F1013, $AE$5) -> 0 | AF25: =SUMIFS('CF BEST'!$C$9:$C1013, 'CF BEST'!$I$9:$I1013, B25,'CF BEST'!$F$9:$F1013, $AG$5) -> 0 | AG25: =SUMIFS('CF BEST'!$D$9:$D1013, 'CF BEST'!$I$9:$I1013, B25,'CF BEST'!$F$9:$F1013, $AG$5) -> 0 | AH25: =SUMIFS('CF BEST'!$C$9:$C1013, 'CF BEST'!$I$9:$I1013, B25,'CF BEST'!$F$9:$F1013, $AI$5)+AB25+AD25+AF25 -> 0 | AI25: =SUMIFS('CF BEST'!$D$9:$D1013, 'CF BEST'!$I$9:$I1013, B25,'CF BEST'!$F$9:$F1013, $AI$5)+AC25+AE25+AG25 -> 0
A26: =C26/$C$7 -> 0.00010205267 | B26: НАЛОГИ | ПРОЧИЕ | C26: =K26+S26+AA26+AI26 -> 7346 | D26: =SUMIFS('CF BEST'!$C$9:$C1013, 'CF BEST'!$I$9:$I1013, B26,'CF BEST'!$F$9:$F1013, $E$5) -> 0 | E26: =SUMIFS('CF BEST'!$D$9:$D1013, 'CF BEST'!$I$9:$I1013, B26,'CF BEST'!$F$9:$F1013, $E$5) -> 0 | F26: =SUMIFS('CF BEST'!$C$9:$C1013, 'CF BEST'!$I$9:$I1013, B26,'CF BEST'!$F$9:$F1013, $G$5) -> 0 | G26: =SUMIFS('CF BEST'!$D$9:$D1013, 'CF BEST'!$I$9:$I1013, B26,'CF BEST'!$F$9:$F1013, $G$5) -> 0 | H26: =SUMIFS('CF BEST'!$C$9:$C1013, 'CF BEST'!$I$9:$I1013, B26,'CF BEST'!$F$9:$F1013, $I$5) -> 0 | I26: =SUMIFS('CF BEST'!$D$9:$D1013, 'CF BEST'!$I$9:$I1013, B26,'CF BEST'!$F$9:$F1013, $I$5) -> 7346 | J26: =SUMIFS('CF BEST'!$C$9:$C1013, 'CF BEST'!$I$9:$I1013, B26,'CF BEST'!$F$9:$F1013, $K$5)+D26+F26+H26 -> 0 | K26: =SUMIFS('CF BEST'!$D$9:$D1013, 'CF BEST'!$I$9:$I1013, B26,'CF BEST'!$F$9:$F1013, $K$5)+E26+G26+I26 -> 7346 | L26: =SUMIFS('CF BEST'!$C$9:$C1013, 'CF BEST'!$I$9:$I1013, B26,'CF BEST'!$F$9:$F1013, $M$5) -> 0 | M26: =SUMIFS('CF BEST'!$D$9:$D1013, 'CF BEST'!$I$9:$I1013, B26,'CF BEST'!$F$9:$F1013, $M$5) -> 0 | N26: =SUMIFS('CF BEST'!$C$9:$C1013, 'CF BEST'!$I$9:$I1013, B26,'CF BEST'!$F$9:$F1013, $O$5) -> 0 | O26: =SUMIFS('CF BEST'!$D$9:$D1013, 'CF BEST'!$I$9:$I1013, B26,'CF BEST'!$F$9:$F1013, $O$5) -> 0 | P26: =SUMIFS('CF BEST'!$C$9:$C1013, 'CF BEST'!$I$9:$I1013, B26,'CF BEST'!$F$9:$F1013, $Q$5) -> 0 | Q26: =SUMIFS('CF BEST'!$D$9:$D1013, 'CF BEST'!$I$9:$I1013, B26,'CF BEST'!$F$9:$F1013, $Q$5) -> 0 | R26: =SUMIFS('CF BEST'!$C$9:$C1013, 'CF BEST'!$I$9:$I1013, B26,'CF BEST'!$F$9:$F1013, $S$5)+L26+N26+P26 -> 0 | S26: =SUMIFS('CF BEST'!$D$9:$D1013, 'CF BEST'!$I$9:$I1013, B26,'CF BEST'!$F$9:$F1013, $S$5)+M26+O26+Q26 -> 0 | T26: =SUMIFS('CF BEST'!$C$9:$C1013, 'CF BEST'!$I$9:$I1013, B26,'CF BEST'!$F$9:$F1013, $U$5) -> 0 | U26: =SUMIFS('CF BEST'!$D$9:$D1013, 'CF BEST'!$I$9:$I1013, B26,'CF BEST'!$F$9:$F1013, $U$5) -> 0 | V26: =SUMIFS('CF BEST'!$C$9:$C1013, 'CF BEST'!$I$9:$I1013, B26,'CF BEST'!$F$9:$F1013, $W$5) -> 0 | W26: =SUMIFS('CF BEST'!$D$9:$D1013, 'CF BEST'!$I$9:$I1013, B26,'CF BEST'!$F$9:$F1013, $W$5) -> 0 | X26: =SUMIFS('CF BEST'!$C$9:$C1013, 'CF BEST'!$I$9:$I1013, B26,'CF BEST'!$F$9:$F1013, $Y$5) -> 0 | Y26: =SUMIFS('CF BEST'!$D$9:$D1013, 'CF BEST'!$I$9:$I1013, B26,'CF BEST'!$F$9:$F1013, $Y$5) -> 0 | Z26: =SUMIFS('CF BEST'!$C$9:$C1013, 'CF BEST'!$I$9:$I1013, B26,'CF BEST'!$F$9:$F1013, $AA$5)+T26+V26+X26 -> 0 | AA26: =SUMIFS('CF BEST'!$D$9:$D1013, 'CF BEST'!$I$9:$I1013, B26,'CF BEST'!$F$9:$F1013, $AA$5)+U26+W26+Y26 -> 0 | AB26: =SUMIFS('CF BEST'!$C$9:$C1013, 'CF BEST'!$I$9:$I1013, B26,'CF BEST'!$F$9:$F1013, $AC$5) -> 0 | AC26: =SUMIFS('CF BEST'!$D$9:$D1013, 'CF BEST'!$I$9:$I1013, B26,'CF BEST'!$F$9:$F1013, $AC$5) -> 0 | AD26: =SUMIFS('CF BEST'!$C$9:$C1013, 'CF BEST'!$I$9:$I1013, B26,'CF BEST'!$F$9:$F1013, $AE$5) -> 0 | AE26: =SUMIFS('CF BEST'!$D$9:$D1013, 'CF BEST'!$I$9:$I1013, B26,'CF BEST'!$F$9:$F1013, $AE$5) -> 0 | AF26: =SUMIFS('CF BEST'!$C$9:$C1013, 'CF BEST'!$I$9:$I1013, B26,'CF BEST'!$F$9:$F1013, $AG$5) -> 0 | AG26: =SUMIFS('CF BEST'!$D$9:$D1013, 'CF BEST'!$I$9:$I1013, B26,'CF BEST'!$F$9:$F1013, $AG$5) -> 0 | AH26: =SUMIFS('CF BEST'!$C$9:$C1013, 'CF BEST'!$I$9:$I1013, B26,'CF BEST'!$F$9:$F1013, $AI$5)+AB26+AD26+AF26 -> 0 | AI26: =SUMIFS('CF BEST'!$D$9:$D1013, 'CF BEST'!$I$9:$I1013, B26,'CF BEST'!$F$9:$F1013, $AI$5)+AC26+AE26+AG26 -> 0
A27: =C27/$C$7 -> 0.010238364 | B27: НАЛОГИ | Реклама | C27: =K27+S27+AA27+AI27 -> 736982.37 | D27: =SUMIFS('CF BEST'!$C$9:$C1013, 'CF BEST'!$I$9:$I1013, B27,'CF BEST'!$F$9:$F1013, $E$5) -> 0 | E27: =SUMIFS('CF BEST'!$D$9:$D1013, 'CF BEST'!$I$9:$I1013, B27,'CF BEST'!$F$9:$F1013, $E$5) -> 0 | F27: =SUMIFS('CF BEST'!$C$9:$C1013, 'CF BEST'!$I$9:$I1013, B27,'CF BEST'!$F$9:$F1013, $G$5) -> 0 | G27: =SUMIFS('CF BEST'!$D$9:$D1013, 'CF BEST'!$I$9:$I1013, B27,'CF BEST'!$F$9:$F1013, $G$5) -> 0 | H27: =SUMIFS('CF BEST'!$C$9:$C1013, 'CF BEST'!$I$9:$I1013, B27,'CF BEST'!$F$9:$F1013, $I$5) -> 0 | I27: =SUMIFS('CF BEST'!$D$9:$D1013, 'CF BEST'!$I$9:$I1013, B27,'CF BEST'!$F$9:$F1013, $I$5) -> 0 | J27: =SUMIFS('CF BEST'!$C$9:$C1013, 'CF BEST'!$I$9:$I1013, B27,'CF BEST'!$F$9:$F1013, $K$5)+D27+F27+H27 -> 0 | K27: =SUMIFS('CF BEST'!$D$9:$D1013, 'CF BEST'!$I$9:$I1013, B27,'CF BEST'!$F$9:$F1013, $K$5)+E27+G27+I27 -> 736982.37 | L27: =SUMIFS('CF BEST'!$C$9:$C1013, 'CF BEST'!$I$9:$I1013, B27,'CF BEST'!$F$9:$F1013, $M$5) -> 0 | M27: =SUMIFS('CF BEST'!$D$9:$D1013, 'CF BEST'!$I$9:$I1013, B27,'CF BEST'!$F$9:$F1013, $M$5) -> 0 | N27: =SUMIFS('CF BEST'!$C$9:$C1013, 'CF BEST'!$I$9:$I1013, B27,'CF BEST'!$F$9:$F1013, $O$5) -> 0 | O27: =SUMIFS('CF BEST'!$D$9:$D1013, 'CF BEST'!$I$9:$I1013, B27,'CF BEST'!$F$9:$F1013, $O$5) -> 0 | P27: =SUMIFS('CF BEST'!$C$9:$C1013, 'CF BEST'!$I$9:$I1013, B27,'CF BEST'!$F$9:$F1013, $Q$5) -> 0 | Q27: =SUMIFS('CF BEST'!$D$9:$D1013, 'CF BEST'!$I$9:$I1013, B27,'CF BEST'!$F$9:$F1013, $Q$5) -> 0 | R27: =SUMIFS('CF BEST'!$C$9:$C1013, 'CF BEST'!$I$9:$I1013, B27,'CF BEST'!$F$9:$F1013, $S$5)+L27+N27+P27 -> 0 | S27: =SUMIFS('CF BEST'!$D$9:$D1013, 'CF BEST'!$I$9:$I1013, B27,'CF BEST'!$F$9:$F1013, $S$5)+M27+O27+Q27 -> 0 | T27: =SUMIFS('CF BEST'!$C$9:$C1013, 'CF BEST'!$I$9:$I1013, B27,'CF BEST'!$F$9:$F1013, $U$5) -> 0 | U27: =SUMIFS('CF BEST'!$D$9:$D1013, 'CF BEST'!$I$9:$I1013, B27,'CF BEST'!$F$9:$F1013, $U$5) -> 0 | V27: =SUMIFS('CF BEST'!$C$9:$C1013, 'CF BEST'!$I$9:$I1013, B27,'CF BEST'!$F$9:$F1013, $W$5) -> 0 | W27: =SUMIFS('CF BEST'!$D$9:$D1013, 'CF BEST'!$I$9:$I1013, B27,'CF BEST'!$F$9:$F1013, $W$5) -> 0 | X27: =SUMIFS('CF BEST'!$C$9:$C1013, 'CF BEST'!$I$9:$I1013, B27,'CF BEST'!$F$9:$F1013, $Y$5) -> 0 | Y27: =SUMIFS('CF BEST'!$D$9:$D1013, 'CF BEST'!$I$9:$I1013, B27,'CF BEST'!$F$9:$F1013, $Y$5) -> 0 | Z27: =SUMIFS('CF BEST'!$C$9:$C1013, 'CF BEST'!$I$9:$I1013, B27,'CF BEST'!$F$9:$F1013, $AA$5)+T27+V27+X27 -> 0 | AA27: =SUMIFS('CF BEST'!$D$9:$D1013, 'CF BEST'!$I$9:$I1013, B27,'CF BEST'!$F$9:$F1013, $AA$5)+U27+W27+Y27 -> 0 | AB27: =SUMIFS('CF BEST'!$C$9:$C1013, 'CF BEST'!$I$9:$I1013, B27,'CF BEST'!$F$9:$F1013, $AC$5) -> 0 | AC27: =SUMIFS('CF BEST'!$D$9:$D1013, 'CF BEST'!$I$9:$I1013, B27,'CF BEST'!$F$9:$F1013, $AC$5) -> 0 | AD27: =SUMIFS('CF BEST'!$C$9:$C1013, 'CF BEST'!$I$9:$I1013, B27,'CF BEST'!$F$9:$F1013, $AE$5) -> 0 | AE27: =SUMIFS('CF BEST'!$D$9:$D1013, 'CF BEST'!$I$9:$I1013, B27,'CF BEST'!$F$9:$F1013, $AE$5) -> 0 | AF27: =SUMIFS('CF BEST'!$C$9:$C1013, 'CF BEST'!$I$9:$I1013, B27,'CF BEST'!$F$9:$F1013, $AG$5) -> 0 | AG27: =SUMIFS('CF BEST'!$D$9:$D1013, 'CF BEST'!$I$9:$I1013, B27,'CF BEST'!$F$9:$F1013, $AG$5) -> 0 | AH27: =SUMIFS('CF BEST'!$C$9:$C1013, 'CF BEST'!$I$9:$I1013, B27,'CF BEST'!$F$9:$F1013, $AI$5)+AB27+AD27+AF27 -> 0 | AI27: =SUMIFS('CF BEST'!$D$9:$D1013, 'CF BEST'!$I$9:$I1013, B27,'CF BEST'!$F$9:$F1013, $AI$5)+AC27+AE27+AG27 -> 0
A28: =C28/$C$7 -> 0 | B28: ДИВИДЕНТЫ | C28: =K28+S28+AA28+AI28 -> 0 | D28: =SUMIFS('CF BEST'!$C$9:$C1013, 'CF BEST'!$I$9:$I1013, B28,'CF BEST'!$F$9:$F1013, $E$5) -> 0 | E28: =SUMIFS('CF BEST'!$D$9:$D1013, 'CF BEST'!$I$9:$I1013, B28,'CF BEST'!$F$9:$F1013, $E$5) -> 0 | F28: =SUMIFS('CF BEST'!$C$9:$C1013, 'CF BEST'!$I$9:$I1013, B28,'CF BEST'!$F$9:$F1013, $G$5) -> 0 | G28: =SUMIFS('CF BEST'!$D$9:$D1013, 'CF BEST'!$I$9:$I1013, B28,'CF BEST'!$F$9:$F1013, $G$5) -> 0 | H28: =SUMIFS('CF BEST'!$C$9:$C1013, 'CF BEST'!$I$9:$I1013, B28,'CF BEST'!$F$9:$F1013, $I$5) -> 0 | I28: =SUMIFS('CF BEST'!$D$9:$D1013, 'CF BEST'!$I$9:$I1013, B28,'CF BEST'!$F$9:$F1013, $I$5) -> 0 | J28: =SUMIFS('CF BEST'!$C$9:$C1013, 'CF BEST'!$I$9:$I1013, B28,'CF BEST'!$F$9:$F1013, $K$5)+D28+F28+H28 -> 0 | K28: =SUMIFS('CF BEST'!$D$9:$D1013, 'CF BEST'!$I$9:$I1013, B28,'CF BEST'!$F$9:$F1013, $K$5)+E28+G28+I28 -> 0 | L28: =SUMIFS('CF BEST'!$C$9:$C1013, 'CF BEST'!$I$9:$I1013, B28,'CF BEST'!$F$9:$F1013, $M$5) -> 0 | M28: =SUMIFS('CF BEST'!$D$9:$D1013, 'CF BEST'!$I$9:$I1013, B28,'CF BEST'!$F$9:$F1013, $M$5) -> 0 | N28: =SUMIFS('CF BEST'!$C$9:$C1013, 'CF BEST'!$I$9:$I1013, B28,'CF BEST'!$F$9:$F1013, $O$5) -> 0 | O28: =SUMIFS('CF BEST'!$D$9:$D1013, 'CF BEST'!$I$9:$I1013, B28,'CF BEST'!$F$9:$F1013, $O$5) -> 0 | P28: =SUMIFS('CF BEST'!$C$9:$C1013, 'CF BEST'!$I$9:$I1013, B28,'CF BEST'!$F$9:$F1013, $Q$5) -> 0 | Q28: =SUMIFS('CF BEST'!$D$9:$D1013, 'CF BEST'!$I$9:$I1013, B28,'CF BEST'!$F$9:$F1013, $Q$5) -> 0 | R28: =SUMIFS('CF BEST'!$C$9:$C1013, 'CF BEST'!$I$9:$I1013, B28,'CF BEST'!$F$9:$F1013, $S$5)+L28+N28+P28 -> 0 | S28: =SUMIFS('CF BEST'!$D$9:$D1013, 'CF BEST'!$I$9:$I1013, B28,'CF BEST'!$F$9:$F1013, $S$5)+M28+O28+Q28 -> 0 | T28: =SUMIFS('CF BEST'!$C$9:$C1013, 'CF BEST'!$I$9:$I1013, B28,'CF BEST'!$F$9:$F1013, $U$5) -> 0 | U28: =SUMIFS('CF BEST'!$D$9:$D1013, 'CF BEST'!$I$9:$I1013, B28,'CF BEST'!$F$9:$F1013, $U$5) -> 0 | V28: =SUMIFS('CF BEST'!$C$9:$C1013, 'CF BEST'!$I$9:$I1013, B28,'CF BEST'!$F$9:$F1013, $W$5) -> 0 | W28: =SUMIFS('CF BEST'!$D$9:$D1013, 'CF BEST'!$I$9:$I1013, B28,'CF BEST'!$F$9:$F1013, $W$5) -> 0 | X28: =SUMIFS('CF BEST'!$C$9:$C1013, 'CF BEST'!$I$9:$I1013, B28,'CF BEST'!$F$9:$F1013, $Y$5) -> 0 | Y28: =SUMIFS('CF BEST'!$D$9:$D1013, 'CF BEST'!$I$9:$I1013, B28,'CF BEST'!$F$9:$F1013, $Y$5) -> 0 | Z28: =SUMIFS('CF BEST'!$C$9:$C1013, 'CF BEST'!$I$9:$I1013, B28,'CF BEST'!$F$9:$F1013, $AA$5)+T28+V28+X28 -> 0 | AA28: =SUMIFS('CF BEST'!$D$9:$D1013, 'CF BEST'!$I$9:$I1013, B28,'CF BEST'!$F$9:$F1013, $AA$5)+U28+W28+Y28 -> 0 | AB28: =SUMIFS('CF BEST'!$C$9:$C1013, 'CF BEST'!$I$9:$I1013, B28,'CF BEST'!$F$9:$F1013, $AC$5) -> 0 | AC28: =SUMIFS('CF BEST'!$D$9:$D1013, 'CF BEST'!$I$9:$I1013, B28,'CF BEST'!$F$9:$F1013, $AC$5) -> 0 | AD28: =SUMIFS('CF BEST'!$C$9:$C1013, 'CF BEST'!$I$9:$I1013, B28,'CF BEST'!$F$9:$F1013, $AE$5) -> 0 | AE28: =SUMIFS('CF BEST'!$D$9:$D1013, 'CF BEST'!$I$9:$I1013, B28,'CF BEST'!$F$9:$F1013, $AE$5) -> 0 | AF28: =SUMIFS('CF BEST'!$C$9:$C1013, 'CF BEST'!$I$9:$I1013, B28,'CF BEST'!$F$9:$F1013, $AG$5) -> 0 | AG28: =SUMIFS('CF BEST'!$D$9:$D1013, 'CF BEST'!$I$9:$I1013, B28,'CF BEST'!$F$9:$F1013, $AG$5) -> 0 | AH28: =SUMIFS('CF BEST'!$C$9:$C1013, 'CF BEST'!$I$9:$I1013, B28,'CF BEST'!$F$9:$F1013, $AI$5)+AB28+AD28+AF28 -> 0 | AI28: =SUMIFS('CF BEST'!$D$9:$D1013, 'CF BEST'!$I$9:$I1013, B28,'CF BEST'!$F$9:$F1013, $AI$5)+AC28+AE28+AG28 -> 0
A29: =C29/$C$7 -> 0.028626608 | B29: ТРАНЗИТ | C29: =(K29+S29+AA29+AI29)-AH29-Z29-R29-J29 -> 2060613 | D29: 0 | E29: =SUMIFS('CF BEST'!$D$9:$D1013, 'CF BEST'!$I$9:$I1013, $B$29,'CF BEST'!$F$9:$F1013, E5)-SUMIFS('CF BEST'!$C$9:$C1013, 'CF BEST'!$I$9:$I1013, $B$29,'CF BEST'!$F$9:$F1013, E5) -> 900000 | F29: 0 | G29: =SUMIFS('CF BEST'!$D$9:$D1013, 'CF BEST'!$I$9:$I1013, $B$29,'CF BEST'!$F$9:$F1013, G5)-SUMIFS('CF BEST'!$C$9:$C1013, 'CF BEST'!$I$9:$I1013, $B$29,'CF BEST'!$F$9:$F1013, G5) -> 0 | H29: 0 | I29: =SUMIFS('CF BEST'!$D$9:$D1013, 'CF BEST'!$I$9:$I1013, $B$29,'CF BEST'!$F$9:$F1013, I5)-SUMIFS('CF BEST'!$C$9:$C1013, 'CF BEST'!$I$9:$I1013, $B$29,'CF BEST'!$F$9:$F1013, I5) -> 492000 | J29: =SUMIFS('CF BEST'!$C$9:$C1013, 'CF BEST'!$I$9:$I1013, B29,'CF BEST'!$F$9:$F1013, $K$5)+D29+F29+H29 -> 0 | K29: =SUMIFS('CF BEST'!$D$9:$D1013, 'CF BEST'!$I$9:$I1013, B29,'CF BEST'!$F$9:$F1013, $K$5)+E29+G29+I29 -> 1392000 | L29: 0 | M29: =SUMIFS('CF BEST'!$D$9:$D1013, 'CF BEST'!$I$9:$I1013, $B$29,'CF BEST'!$F$9:$F1013, M5)-SUMIFS('CF BEST'!$C$9:$C1013, 'CF BEST'!$I$9:$I1013, $B$29,'CF BEST'!$F$9:$F1013, M5) -> 0 | N29: 0 | O29: =SUMIFS('CF BEST'!$D$9:$D1013, 'CF BEST'!$I$9:$I1013, $B$29,'CF BEST'!$F$9:$F1013, O5)-SUMIFS('CF BEST'!$C$9:$C1013, 'CF BEST'!$I$9:$I1013, $B$29,'CF BEST'!$F$9:$F1013, O5) -> 668625 | P29: 0 | Q29: =SUMIFS('CF BEST'!$D$9:$D1013, 'CF BEST'!$I$9:$I1013, $B$29,'CF BEST'!$F$9:$F1013, Q5)-SUMIFS('CF BEST'!$C$9:$C1013, 'CF BEST'!$I$9:$I1013, $B$29,'CF BEST'!$F$9:$F1013, Q5) -> 0 | R29: =SUMIFS('CF BEST'!$C$9:$C1013, 'CF BEST'!$I$9:$I1013, B29,'CF BEST'!$F$9:$F1013, $S$5)+L29+N29+P29 -> 0 | S29: =SUMIFS('CF BEST'!$D$9:$D1013, 'CF BEST'!$I$9:$I1013, B29,'CF BEST'!$F$9:$F1013, $S$5)+M29+O29+Q29 -> 668625 | T29: 0 | U29: =SUMIFS('CF BEST'!$D$9:$D1013, 'CF BEST'!$I$9:$I1013, $B$29,'CF BEST'!$F$9:$F1013, U5)-SUMIFS('CF BEST'!$C$9:$C1013, 'CF BEST'!$I$9:$I1013, $B$29,'CF BEST'!$F$9:$F1013, U5) -> 0 | V29: 0 | W29: =SUMIFS('CF BEST'!$D$9:$D1013, 'CF BEST'!$I$9:$I1013, $B$29,'CF BEST'!$F$9:$F1013, W5)-SUMIFS('CF BEST'!$C$9:$C1013, 'CF BEST'!$I$9:$I1013, $B$29,'CF BEST'!$F$9:$F1013, W5) -> 0 | X29: 0 | Y29: =SUMIFS('CF BEST'!$D$9:$D1013, 'CF BEST'!$I$9:$I1013, $B$29,'CF BEST'!$F$9:$F1013, Y5)-SUMIFS('CF BEST'!$C$9:$C1013, 'CF BEST'!$I$9:$I1013, $B$29,'CF BEST'!$F$9:$F1013, Y5) -> 0 | Z29: =SUMIFS('CF BEST'!$C$9:$C1013, 'CF BEST'!$I$9:$I1013, B29,'CF BEST'!$F$9:$F1013, $AA$5)+T29+V29+X29 -> 0 | AA29: =SUMIFS('CF BEST'!$D$9:$D1013, 'CF BEST'!$I$9:$I1013, B29,'CF BEST'!$F$9:$F1013, $AA$5)+U29+W29+Y29 -> 0 | AB29: 12 | AC29: =SUMIFS('CF BEST'!$D$9:$D1013, 'CF BEST'!$I$9:$I1013, $B$29,'CF BEST'!$F$9:$F1013, AC5)-SUMIFS('CF BEST'!$C$9:$C1013, 'CF BEST'!$I$9:$I1013, $B$29,'CF BEST'!$F$9:$F1013, AC5) -> 0 | AD29: 0 | AE29: =SUMIFS('CF BEST'!$D$9:$D1013, 'CF BEST'!$I$9:$I1013, $B$29,'CF BEST'!$F$9:$F1013, AE5)-SUMIFS('CF BEST'!$C$9:$C1013, 'CF BEST'!$I$9:$I1013, $B$29,'CF BEST'!$F$9:$F1013, AE5) -> 0 | AF29: 0 | AG29: =SUMIFS('CF BEST'!$D$9:$D1013, 'CF BEST'!$I$9:$I1013, $B$29,'CF BEST'!$F$9:$F1013, AG5)-SUMIFS('CF BEST'!$C$9:$C1013, 'CF BEST'!$I$9:$I1013, $B$29,'CF BEST'!$F$9:$F1013, AG5) -> 0 | AH29: =SUMIFS('CF BEST'!$C$9:$C1013, 'CF BEST'!$I$9:$I1013, B29,'CF BEST'!$F$9:$F1013, $AI$5)+AB29+AD29+AF29 -> 12 | AI29: =SUMIFS('CF BEST'!$D$9:$D1013, 'CF BEST'!$I$9:$I1013, B29,'CF BEST'!$F$9:$F1013, $AI$5)+AC29+AE29+AG29 -> 0
A30: =C30/$C$7 -> 0.00048970834 | B30: БАНК | C30: =K30+S30+AA30+AI30 -> 35250.4 | D30: =SUMIFS('CF BEST'!$C$9:$C1013, 'CF BEST'!$I$9:$I1013, B30,'CF BEST'!$F$9:$F1013, $E$5) -> 0 | E30: =SUMIFS('CF BEST'!$D$9:$D1013, 'CF BEST'!$I$9:$I1013, B30,'CF BEST'!$F$9:$F1013, $E$5) -> 3473.33 | F30: =SUMIFS('CF BEST'!$C$9:$C1013, 'CF BEST'!$I$9:$I1013, B30,'CF BEST'!$F$9:$F1013, $G$5) -> 0 | G30: =SUMIFS('CF BEST'!$D$9:$D1013, 'CF BEST'!$I$9:$I1013, B30,'CF BEST'!$F$9:$F1013, $G$5) -> 0 | H30: =SUMIFS('CF BEST'!$C$9:$C1013, 'CF BEST'!$I$9:$I1013, B30,'CF BEST'!$F$9:$F1013, $I$5) -> 0 | I30: =SUMIFS('CF BEST'!$D$9:$D1013, 'CF BEST'!$I$9:$I1013, B30,'CF BEST'!$F$9:$F1013, $I$5) -> 16162.07 | J30: =SUMIFS('CF BEST'!$C$9:$C1013, 'CF BEST'!$I$9:$I1013, B30,'CF BEST'!$F$9:$F1013, $K$5)+D30+F30+H30 -> 0 | K30: =SUMIFS('CF BEST'!$D$9:$D1013, 'CF BEST'!$I$9:$I1013, B30,'CF BEST'!$F$9:$F1013, $K$5)+E30+G30+I30 -> 26350.4 | L30: =SUMIFS('CF BEST'!$C$9:$C1013, 'CF BEST'!$I$9:$I1013, B30,'CF BEST'!$F$9:$F1013, $M$5) -> 0 | M30: =SUMIFS('CF BEST'!$D$9:$D1013, 'CF BEST'!$I$9:$I1013, B30,'CF BEST'!$F$9:$F1013, $M$5) -> 8900 | N30: =SUMIFS('CF BEST'!$C$9:$C1013, 'CF BEST'!$I$9:$I1013, B30,'CF BEST'!$F$9:$F1013, $O$5) -> 0 | O30: =SUMIFS('CF BEST'!$D$9:$D1013, 'CF BEST'!$I$9:$I1013, B30,'CF BEST'!$F$9:$F1013, $O$5) -> 0 | P30: =SUMIFS('CF BEST'!$C$9:$C1013, 'CF BEST'!$I$9:$I1013, B30,'CF BEST'!$F$9:$F1013, $Q$5) -> 0 | Q30: =SUMIFS('CF BEST'!$D$9:$D1013, 'CF BEST'!$I$9:$I1013, B30,'CF BEST'!$F$9:$F1013, $Q$5) -> 0 | R30: =SUMIFS('CF BEST'!$C$9:$C1013, 'CF BEST'!$I$9:$I1013, B30,'CF BEST'!$F$9:$F1013, $S$5)+L30+N30+P30 -> 0 | S30: =SUMIFS('CF BEST'!$D$9:$D1013, 'CF BEST'!$I$9:$I1013, B30,'CF BEST'!$F$9:$F1013, $S$5)+M30+O30+Q30 -> 8900 | T30: =SUMIFS('CF BEST'!$C$9:$C1013, 'CF BEST'!$I$9:$I1013, B30,'CF BEST'!$F$9:$F1013, $U$5) -> 0 | U30: =SUMIFS('CF BEST'!$D$9:$D1013, 'CF BEST'!$I$9:$I1013, B30,'CF BEST'!$F$9:$F1013, $U$5) -> 0 | V30: =SUMIFS('CF BEST'!$C$9:$C1013, 'CF BEST'!$I$9:$I1013, B30,'CF BEST'!$F$9:$F1013, $W$5) -> 0 | W30: =SUMIFS('CF BEST'!$D$9:$D1013, 'CF BEST'!$I$9:$I1013, B30,'CF BEST'!$F$9:$F1013, $W$5) -> 0 | X30: =SUMIFS('CF BEST'!$C$9:$C1013, 'CF BEST'!$I$9:$I1013, B30,'CF BEST'!$F$9:$F1013, $Y$5) -> 0 | Y30: =SUMIFS('CF BEST'!$D$9:$D1013, 'CF BEST'!$I$9:$I1013, B30,'CF BEST'!$F$9:$F1013, $Y$5) -> 0 | Z30: =SUMIFS('CF BEST'!$C$9:$C1013, 'CF BEST'!$I$9:$I1013, B30,'CF BEST'!$F$9:$F1013, $AA$5)+T30+V30+X30 -> 0 | AA30: =SUMIFS('CF BEST'!$D$9:$D1013, 'CF BEST'!$I$9:$I1013, B30,'CF BEST'!$F$9:$F1013, $AA$5)+U30+W30+Y30 -> 0 | AB30: =SUMIFS('CF BEST'!$C$9:$C1013, 'CF BEST'!$I$9:$I1013, B30,'CF BEST'!$F$9:$F1013, $AC$5) -> 0 | AC30: =SUMIFS('CF BEST'!$D$9:$D1013, 'CF BEST'!$I$9:$I1013, B30,'CF BEST'!$F$9:$F1013, $AC$5) -> 0 | AD30: =SUMIFS('CF BEST'!$C$9:$C1013, 'CF BEST'!$I$9:$I1013, B30,'CF BEST'!$F$9:$F1013, $AE$5) -> 0 | AE30: =SUMIFS('CF BEST'!$D$9:$D1013, 'CF BEST'!$I$9:$I1013, B30,'CF BEST'!$F$9:$F1013, $AE$5) -> 0 | AF30: =SUMIFS('CF BEST'!$C$9:$C1013, 'CF BEST'!$I$9:$I1013, B30,'CF BEST'!$F$9:$F1013, $AG$5) -> 0 | AG30: =SUMIFS('CF BEST'!$D$9:$D1013, 'CF BEST'!$I$9:$I1013, B30,'CF BEST'!$F$9:$F1013, $AG$5) -> 0 | AH30: =SUMIFS('CF BEST'!$C$9:$C1013, 'CF BEST'!$I$9:$I1013, B30,'CF BEST'!$F$9:$F1013, $AI$5)+AB30+AD30+AF30 -> 0 | AI30: =SUMIFS('CF BEST'!$D$9:$D1013, 'CF BEST'!$I$9:$I1013, B30,'CF BEST'!$F$9:$F1013, $AI$5)+AC30+AE30+AG30 -> 0
A31: =C31/$C$7 -> 0.053011758 | B31: КРЕДИТЫ | C31: =K31+S31+AA31+AI31 -> 3815915.6 | D31: =SUMIFS('CF BEST'!$C$9:$C1013, 'CF BEST'!$I$9:$I1013, B31,'CF BEST'!$F$9:$F1013, $E$5) -> 0 | E31: =SUMIFS('CF BEST'!$D$9:$D1013, 'CF BEST'!$I$9:$I1013, B31,'CF BEST'!$F$9:$F1013, $E$5) -> 52861.37 | F31: =SUMIFS('CF BEST'!$C$9:$C1013, 'CF BEST'!$I$9:$I1013, B31,'CF BEST'!$F$9:$F1013, $G$5) -> 0 | G31: =SUMIFS('CF BEST'!$D$9:$D1013, 'CF BEST'!$I$9:$I1013, B31,'CF BEST'!$F$9:$F1013, $G$5) -> 81916.16 | H31: =SUMIFS('CF BEST'!$C$9:$C1013, 'CF BEST'!$I$9:$I1013, B31,'CF BEST'!$F$9:$F1013, $I$5) -> 0 | I31: =SUMIFS('CF BEST'!$D$9:$D1013, 'CF BEST'!$I$9:$I1013, B31,'CF BEST'!$F$9:$F1013, $I$5) -> 3649917.9 | J31: =SUMIFS('CF BEST'!$C$9:$C1013, 'CF BEST'!$I$9:$I1013, B31,'CF BEST'!$F$9:$F1013, $K$5)+D31+F31+H31 -> 0 | K31: =SUMIFS('CF BEST'!$D$9:$D1013, 'CF BEST'!$I$9:$I1013, B31,'CF BEST'!$F$9:$F1013, $K$5)+E31+G31+I31 -> 3784695.4 | L31: =SUMIFS('CF BEST'!$C$9:$C1013, 'CF BEST'!$I$9:$I1013, B31,'CF BEST'!$F$9:$F1013, $M$5) -> 0 | M31: =SUMIFS('CF BEST'!$D$9:$D1013, 'CF BEST'!$I$9:$I1013, B31,'CF BEST'!$F$9:$F1013, $M$5) -> 31220.2 | N31: =SUMIFS('CF BEST'!$C$9:$C1013, 'CF BEST'!$I$9:$I1013, B31,'CF BEST'!$F$9:$F1013, $O$5) -> 0 | O31: =SUMIFS('CF BEST'!$D$9:$D1013, 'CF BEST'!$I$9:$I1013, B31,'CF BEST'!$F$9:$F1013, $O$5) -> 0 | P31: =SUMIFS('CF BEST'!$C$9:$C1013, 'CF BEST'!$I$9:$I1013, B31,'CF BEST'!$F$9:$F1013, $Q$5) -> 3000000 | Q31: =SUMIFS('CF BEST'!$D$9:$D1013, 'CF BEST'!$I$9:$I1013, B31,'CF BEST'!$F$9:$F1013, $Q$5) -> 0 | R31: =SUMIFS('CF BEST'!$C$9:$C1013, 'CF BEST'!$I$9:$I1013, B31,'CF BEST'!$F$9:$F1013, $S$5)+L31+N31+P31 -> 3000000 | S31: =SUMIFS('CF BEST'!$D$9:$D1013, 'CF BEST'!$I$9:$I1013, B31,'CF BEST'!$F$9:$F1013, $S$5)+M31+O31+Q31 -> 31220.2 | T31: =SUMIFS('CF BEST'!$C$9:$C1013, 'CF BEST'!$I$9:$I1013, B31,'CF BEST'!$F$9:$F1013, $U$5) -> 0 | U31: =SUMIFS('CF BEST'!$D$9:$D1013, 'CF BEST'!$I$9:$I1013, B31,'CF BEST'!$F$9:$F1013, $U$5) -> 0 | V31: =SUMIFS('CF BEST'!$C$9:$C1013, 'CF BEST'!$I$9:$I1013, B31,'CF BEST'!$F$9:$F1013, $W$5) -> 0 | W31: =SUMIFS('CF BEST'!$D$9:$D1013, 'CF BEST'!$I$9:$I1013, B31,'CF BEST'!$F$9:$F1013, $W$5) -> 0 | X31: =SUMIFS('CF BEST'!$C$9:$C1013, 'CF BEST'!$I$9:$I1013, B31,'CF BEST'!$F$9:$F1013, $Y$5) -> 0 | Y31: =SUMIFS('CF BEST'!$D$9:$D1013, 'CF BEST'!$I$9:$I1013, B31,'CF BEST'!$F$9:$F1013, $Y$5) -> 0 | Z31: =SUMIFS('CF BEST'!$C$9:$C1013, 'CF BEST'!$I$9:$I1013, B31,'CF BEST'!$F$9:$F1013, $AA$5)+T31+V31+X31 -> 0 | AA31: =SUMIFS('CF BEST'!$D$9:$D1013, 'CF BEST'!$I$9:$I1013, B31,'CF BEST'!$F$9:$F1013, $AA$5)+U31+W31+Y31 -> 0 | AB31: =SUMIFS('CF BEST'!$C$9:$C1013, 'CF BEST'!$I$9:$I1013, B31,'CF BEST'!$F$9:$F1013, $AC$5) -> 0 | AC31: =SUMIFS('CF BEST'!$D$9:$D1013, 'CF BEST'!$I$9:$I1013, B31,'CF BEST'!$F$9:$F1013, $AC$5) -> 0 | AD31: =SUMIFS('CF BEST'!$C$9:$C1013, 'CF BEST'!$I$9:$I1013, B31,'CF BEST'!$F$9:$F1013, $AE$5) -> 0 | AE31: =SUMIFS('CF BEST'!$D$9:$D1013, 'CF BEST'!$I$9:$I1013, B31,'CF BEST'!$F$9:$F1013, $AE$5) -> 0 | AF31: =SUMIFS('CF BEST'!$C$9:$C1013, 'CF BEST'!$I$9:$I1013, B31,'CF BEST'!$F$9:$F1013, $AG$5) -> 0 | AG31: =SUMIFS('CF BEST'!$D$9:$D1013, 'CF BEST'!$I$9:$I1013, B31,'CF BEST'!$F$9:$F1013, $AG$5) -> 0 | AH31: =SUMIFS('CF BEST'!$C$9:$C1013, 'CF BEST'!$I$9:$I1013, B31,'CF BEST'!$F$9:$F1013, $AI$5)+AB31+AD31+AF31 -> 0 | AI31: =SUMIFS('CF BEST'!$D$9:$D1013, 'CF BEST'!$I$9:$I1013, B31,'CF BEST'!$F$9:$F1013, $AI$5)+AC31+AE31+AG31 -> 0
A32: =C32/$C$7 -> 0.038203763 | B32: РАЗРАБОТКА | C32: =K32+S32+AA32+AI32 -> 2750000 | D32: =SUMIFS('CF BEST'!$C$9:$C1013, 'CF BEST'!$I$9:$I1013, B32,'CF BEST'!$F$9:$F1013, $E$5) -> 0 | E32: =SUMIFS('CF BEST'!$D$9:$D1013, 'CF BEST'!$I$9:$I1013, B32,'CF BEST'!$F$9:$F1013, $E$5) -> 550000 | F32: =SUMIFS('CF BEST'!$C$9:$C1013, 'CF BEST'!$I$9:$I1013, B32,'CF BEST'!$F$9:$F1013, $G$5) -> 0 | G32: =SUMIFS('CF BEST'!$D$9:$D1013, 'CF BEST'!$I$9:$I1013, B32,'CF BEST'!$F$9:$F1013, $G$5) -> 550000 | H32: =SUMIFS('CF BEST'!$C$9:$C1013, 'CF BEST'!$I$9:$I1013, B32,'CF BEST'!$F$9:$F1013, $I$5) -> 0 | I32: =SUMIFS('CF BEST'!$D$9:$D1013, 'CF BEST'!$I$9:$I1013, B32,'CF BEST'!$F$9:$F1013, $I$5) -> 550000 | J32: =SUMIFS('CF BEST'!$C$9:$C1013, 'CF BEST'!$I$9:$I1013, B32,'CF BEST'!$F$9:$F1013, $K$5)+D32+F32+H32 -> 0 | K32: =SUMIFS('CF BEST'!$D$9:$D1013, 'CF BEST'!$I$9:$I1013, B32,'CF BEST'!$F$9:$F1013, $K$5)+E32+G32+I32 -> 1650000 | L32: =SUMIFS('CF BEST'!$C$9:$C1013, 'CF BEST'!$I$9:$I1013, B32,'CF BEST'!$F$9:$F1013, $M$5) -> 0 | M32: =SUMIFS('CF BEST'!$D$9:$D1013, 'CF BEST'!$I$9:$I1013, B32,'CF BEST'!$F$9:$F1013, $M$5) -> 550000 | N32: =SUMIFS('CF BEST'!$C$9:$C1013, 'CF BEST'!$I$9:$I1013, B32,'CF BEST'!$F$9:$F1013, $O$5) -> 0 | O32: =SUMIFS('CF BEST'!$D$9:$D1013, 'CF BEST'!$I$9:$I1013, B32,'CF BEST'!$F$9:$F1013, $O$5) -> 550000 | P32: =SUMIFS('CF BEST'!$C$9:$C1013, 'CF BEST'!$I$9:$I1013, B32,'CF BEST'!$F$9:$F1013, $Q$5) -> 0 | Q32: =SUMIFS('CF BEST'!$D$9:$D1013, 'CF BEST'!$I$9:$I1013, B32,'CF BEST'!$F$9:$F1013, $Q$5) -> 0 | R32: =SUMIFS('CF BEST'!$C$9:$C1013, 'CF BEST'!$I$9:$I1013, B32,'CF BEST'!$F$9:$F1013, $S$5)+L32+N32+P32 -> 0 | S32: =SUMIFS('CF BEST'!$D$9:$D1013, 'CF BEST'!$I$9:$I1013, B32,'CF BEST'!$F$9:$F1013, $S$5)+M32+O32+Q32 -> 1100000 | T32: =SUMIFS('CF BEST'!$C$9:$C1013, 'CF BEST'!$I$9:$I1013, B32,'CF BEST'!$F$9:$F1013, $U$5) -> 0 | U32: =SUMIFS('CF BEST'!$D$9:$D1013, 'CF BEST'!$I$9:$I1013, B32,'CF BEST'!$F$9:$F1013, $U$5) -> 0 | V32: =SUMIFS('CF BEST'!$C$9:$C1013, 'CF BEST'!$I$9:$I1013, B32,'CF BEST'!$F$9:$F1013, $W$5) -> 0 | W32: =SUMIFS('CF BEST'!$D$9:$D1013, 'CF BEST'!$I$9:$I1013, B32,'CF BEST'!$F$9:$F1013, $W$5) -> 0 | X32: =SUMIFS('CF BEST'!$C$9:$C1013, 'CF BEST'!$I$9:$I1013, B32,'CF BEST'!$F$9:$F1013, $Y$5) -> 0 | Y32: =SUMIFS('CF BEST'!$D$9:$D1013, 'CF BEST'!$I$9:$I1013, B32,'CF BEST'!$F$9:$F1013, $Y$5) -> 0 | Z32: =SUMIFS('CF BEST'!$C$9:$C1013, 'CF BEST'!$I$9:$I1013, B32,'CF BEST'!$F$9:$F1013, $AA$5)+T32+V32+X32 -> 0 | AA32: =SUMIFS('CF BEST'!$D$9:$D1013, 'CF BEST'!$I$9:$I1013, B32,'CF BEST'!$F$9:$F1013, $AA$5)+U32+W32+Y32 -> 0 | AB32: =SUMIFS('CF BEST'!$C$9:$C1013, 'CF BEST'!$I$9:$I1013, B32,'CF BEST'!$F$9:$F1013, $AC$5) -> 0 | AC32: =SUMIFS('CF BEST'!$D$9:$D1013, 'CF BEST'!$I$9:$I1013, B32,'CF BEST'!$F$9:$F1013, $AC$5) -> 0 | AD32: =SUMIFS('CF BEST'!$C$9:$C1013, 'CF BEST'!$I$9:$I1013, B32,'CF BEST'!$F$9:$F1013, $AE$5) -> 0 | AE32: =SUMIFS('CF BEST'!$D$9:$D1013, 'CF BEST'!$I$9:$I1013, B32,'CF BEST'!$F$9:$F1013, $AE$5) -> 0 | AF32: =SUMIFS('CF BEST'!$C$9:$C1013, 'CF BEST'!$I$9:$I1013, B32,'CF BEST'!$F$9:$F1013, $AG$5) -> 0 | AG32: =SUMIFS('CF BEST'!$D$9:$D1013, 'CF BEST'!$I$9:$I1013, B32,'CF BEST'!$F$9:$F1013, $AG$5) -> 0 | AH32: =SUMIFS('CF BEST'!$C$9:$C1013, 'CF BEST'!$I$9:$I1013, B32,'CF BEST'!$F$9:$F1013, $AI$5)+AB32+AD32+AF32 -> 0 | AI32: =SUMIFS('CF BEST'!$D$9:$D1013, 'CF BEST'!$I$9:$I1013, B32,'CF BEST'!$F$9:$F1013, $AI$5)+AC32+AE32+AG32 -> 0
A33: =C33/$C$7 -> 0.031588638 | B33: IT | C33: =K33+S33+AA33+AI33 -> 2273827.1 | D33: =SUMIFS('CF BEST'!$C$9:$C1013, 'CF BEST'!$I$9:$I1013, B33,'CF BEST'!$F$9:$F1013, $E$5) -> 0 | E33: =SUMIFS('CF BEST'!$D$9:$D1013, 'CF BEST'!$I$9:$I1013, B33,'CF BEST'!$F$9:$F1013, $E$5) -> 402165 | F33: =SUMIFS('CF BEST'!$C$9:$C1013, 'CF BEST'!$I$9:$I1013, B33,'CF BEST'!$F$9:$F1013, $G$5) -> 0 | G33: =SUMIFS('CF BEST'!$D$9:$D1013, 'CF BEST'!$I$9:$I1013, B33,'CF BEST'!$F$9:$F1013, $G$5) -> 450068.69 | H33: =SUMIFS('CF BEST'!$C$9:$C1013, 'CF BEST'!$I$9:$I1013, B33,'CF BEST'!$F$9:$F1013, $I$5) -> 0 | I33: =SUMIFS('CF BEST'!$D$9:$D1013, 'CF BEST'!$I$9:$I1013, B33,'CF BEST'!$F$9:$F1013, $I$5) -> 409400 | J33: =SUMIFS('CF BEST'!$C$9:$C1013, 'CF BEST'!$I$9:$I1013, B33,'CF BEST'!$F$9:$F1013, $K$5)+D33+F33+H33 -> 0 | K33: =SUMIFS('CF BEST'!$D$9:$D1013, 'CF BEST'!$I$9:$I1013, B33,'CF BEST'!$F$9:$F1013, $K$5)+E33+G33+I33 -> 1261633.7 | L33: =SUMIFS('CF BEST'!$C$9:$C1013, 'CF BEST'!$I$9:$I1013, B33,'CF BEST'!$F$9:$F1013, $M$5) -> 0 | M33: =SUMIFS('CF BEST'!$D$9:$D1013, 'CF BEST'!$I$9:$I1013, B33,'CF BEST'!$F$9:$F1013, $M$5) -> 446393.45 | N33: =SUMIFS('CF BEST'!$C$9:$C1013, 'CF BEST'!$I$9:$I1013, B33,'CF BEST'!$F$9:$F1013, $O$5) -> 0 | O33: =SUMIFS('CF BEST'!$D$9:$D1013, 'CF BEST'!$I$9:$I1013, B33,'CF BEST'!$F$9:$F1013, $O$5) -> 565800 | P33: =SUMIFS('CF BEST'!$C$9:$C1013, 'CF BEST'!$I$9:$I1013, B33,'CF BEST'!$F$9:$F1013, $Q$5) -> 0 | Q33: =SUMIFS('CF BEST'!$D$9:$D1013, 'CF BEST'!$I$9:$I1013, B33,'CF BEST'!$F$9:$F1013, $Q$5) -> 0 | R33: =SUMIFS('CF BEST'!$C$9:$C1013, 'CF BEST'!$I$9:$I1013, B33,'CF BEST'!$F$9:$F1013, $S$5)+L33+N33+P33 -> 0 | S33: =SUMIFS('CF BEST'!$D$9:$D1013, 'CF BEST'!$I$9:$I1013, B33,'CF BEST'!$F$9:$F1013, $S$5)+M33+O33+Q33 -> 1012193.4 | T33: =SUMIFS('CF BEST'!$C$9:$C1013, 'CF BEST'!$I$9:$I1013, B33,'CF BEST'!$F$9:$F1013, $U$5) -> 0 | U33: =SUMIFS('CF BEST'!$D$9:$D1013, 'CF BEST'!$I$9:$I1013, B33,'CF BEST'!$F$9:$F1013, $U$5) -> 0 | V33: =SUMIFS('CF BEST'!$C$9:$C1013, 'CF BEST'!$I$9:$I1013, B33,'CF BEST'!$F$9:$F1013, $W$5) -> 0 | W33: =SUMIFS('CF BEST'!$D$9:$D1013, 'CF BEST'!$I$9:$I1013, B33,'CF BEST'!$F$9:$F1013, $W$5) -> 0 | X33: =SUMIFS('CF BEST'!$C$9:$C1013, 'CF BEST'!$I$9:$I1013, B33,'CF BEST'!$F$9:$F1013, $Y$5) -> 0 | Y33: =SUMIFS('CF BEST'!$D$9:$D1013, 'CF BEST'!$I$9:$I1013, B33,'CF BEST'!$F$9:$F1013, $Y$5) -> 0 | Z33: =SUMIFS('CF BEST'!$C$9:$C1013, 'CF BEST'!$I$9:$I1013, B33,'CF BEST'!$F$9:$F1013, $AA$5)+T33+V33+X33 -> 0 | AA33: =SUMIFS('CF BEST'!$D$9:$D1013, 'CF BEST'!$I$9:$I1013, B33,'CF BEST'!$F$9:$F1013, $AA$5)+U33+W33+Y33 -> 0 | AB33: =SUMIFS('CF BEST'!$C$9:$C1013, 'CF BEST'!$I$9:$I1013, B33,'CF BEST'!$F$9:$F1013, $AC$5) -> 0 | AC33: =SUMIFS('CF BEST'!$D$9:$D1013, 'CF BEST'!$I$9:$I1013, B33,'CF BEST'!$F$9:$F1013, $AC$5) -> 0 | AD33: =SUMIFS('CF BEST'!$C$9:$C1013, 'CF BEST'!$I$9:$I1013, B33,'CF BEST'!$F$9:$F1013, $AE$5) -> 0 | AE33: =SUMIFS('CF BEST'!$D$9:$D1013, 'CF BEST'!$I$9:$I1013, B33,'CF BEST'!$F$9:$F1013, $AE$5) -> 0 | AF33: =SUMIFS('CF BEST'!$C$9:$C1013, 'CF BEST'!$I$9:$I1013, B33,'CF BEST'!$F$9:$F1013, $AG$5) -> 0 | AG33: =SUMIFS('CF BEST'!$D$9:$D1013, 'CF BEST'!$I$9:$I1013, B33,'CF BEST'!$F$9:$F1013, $AG$5) -> 0 | AH33: =SUMIFS('CF BEST'!$C$9:$C1013, 'CF BEST'!$I$9:$I1013, B33,'CF BEST'!$F$9:$F1013, $AI$5)+AB33+AD33+AF33 -> 0 | AI33: =SUMIFS('CF BEST'!$D$9:$D1013, 'CF BEST'!$I$9:$I1013, B33,'CF BEST'!$F$9:$F1013, $AI$5)+AC33+AE33+AG33 -> 0
A34: =C34/$C$7 -> 0.023289207 | B34: ОФИС | C34: =K34+S34+AA34+AI34 -> 1676413.9 | D34: =SUMIFS('CF BEST'!$C$9:$C1013, 'CF BEST'!$I$9:$I1013, B34,'CF BEST'!$F$9:$F1013, $E$5) -> 0 | E34: =SUMIFS('CF BEST'!$D$9:$D1013, 'CF BEST'!$I$9:$I1013, B34,'CF BEST'!$F$9:$F1013, $E$5) -> 72349.31 | F34: =SUMIFS('CF BEST'!$C$9:$C1013, 'CF BEST'!$I$9:$I1013, B34,'CF BEST'!$F$9:$F1013, $G$5) -> 0 | G34: =SUMIFS('CF BEST'!$D$9:$D1013, 'CF BEST'!$I$9:$I1013, B34,'CF BEST'!$F$9:$F1013, $G$5) -> 358520.75 | H34: =SUMIFS('CF BEST'!$C$9:$C1013, 'CF BEST'!$I$9:$I1013, B34,'CF BEST'!$F$9:$F1013, $I$5) -> 0 | I34: =SUMIFS('CF BEST'!$D$9:$D1013, 'CF BEST'!$I$9:$I1013, B34,'CF BEST'!$F$9:$F1013, $I$5) -> 336736.52 | J34: =SUMIFS('CF BEST'!$C$9:$C1013, 'CF BEST'!$I$9:$I1013, B34,'CF BEST'!$F$9:$F1013, $K$5)+D34+F34+H34 -> 0 | K34: =SUMIFS('CF BEST'!$D$9:$D1013, 'CF BEST'!$I$9:$I1013, B34,'CF BEST'!$F$9:$F1013, $K$5)+E34+G34+I34 -> 767606.58 | L34: =SUMIFS('CF BEST'!$C$9:$C1013, 'CF BEST'!$I$9:$I1013, B34,'CF BEST'!$F$9:$F1013, $M$5) -> 0 | M34: =SUMIFS('CF BEST'!$D$9:$D1013, 'CF BEST'!$I$9:$I1013, B34,'CF BEST'!$F$9:$F1013, $M$5) -> 318790.97 | N34: =SUMIFS('CF BEST'!$C$9:$C1013, 'CF BEST'!$I$9:$I1013, B34,'CF BEST'!$F$9:$F1013, $O$5) -> 0 | O34: =SUMIFS('CF BEST'!$D$9:$D1013, 'CF BEST'!$I$9:$I1013, B34,'CF BEST'!$F$9:$F1013, $O$5) -> 302508.18 | P34: =SUMIFS('CF BEST'!$C$9:$C1013, 'CF BEST'!$I$9:$I1013, B34,'CF BEST'!$F$9:$F1013, $Q$5) -> 0 | Q34: =SUMIFS('CF BEST'!$D$9:$D1013, 'CF BEST'!$I$9:$I1013, B34,'CF BEST'!$F$9:$F1013, $Q$5) -> 287508.18 | R34: =SUMIFS('CF BEST'!$C$9:$C1013, 'CF BEST'!$I$9:$I1013, B34,'CF BEST'!$F$9:$F1013, $S$5)+L34+N34+P34 -> 0 | S34: =SUMIFS('CF BEST'!$D$9:$D1013, 'CF BEST'!$I$9:$I1013, B34,'CF BEST'!$F$9:$F1013, $S$5)+M34+O34+Q34 -> 908807.33 | T34: =SUMIFS('CF BEST'!$C$9:$C1013, 'CF BEST'!$I$9:$I1013, B34,'CF BEST'!$F$9:$F1013, $U$5) -> 0 | U34: =SUMIFS('CF BEST'!$D$9:$D1013, 'CF BEST'!$I$9:$I1013, B34,'CF BEST'!$F$9:$F1013, $U$5) -> 0 | V34: =SUMIFS('CF BEST'!$C$9:$C1013, 'CF BEST'!$I$9:$I1013, B34,'CF BEST'!$F$9:$F1013, $W$5) -> 0 | W34: =SUMIFS('CF BEST'!$D$9:$D1013, 'CF BEST'!$I$9:$I1013, B34,'CF BEST'!$F$9:$F1013, $W$5) -> 0 | X34: =SUMIFS('CF BEST'!$C$9:$C1013, 'CF BEST'!$I$9:$I1013, B34,'CF BEST'!$F$9:$F1013, $Y$5) -> 0 | Y34: =SUMIFS('CF BEST'!$D$9:$D1013, 'CF BEST'!$I$9:$I1013, B34,'CF BEST'!$F$9:$F1013, $Y$5) -> 0 | Z34: =SUMIFS('CF BEST'!$C$9:$C1013, 'CF BEST'!$I$9:$I1013, B34,'CF BEST'!$F$9:$F1013, $AA$5)+T34+V34+X34 -> 0 | AA34: =SUMIFS('CF BEST'!$D$9:$D1013, 'CF BEST'!$I$9:$I1013, B34,'CF BEST'!$F$9:$F1013, $AA$5)+U34+W34+Y34 -> 0 | AB34: =SUMIFS('CF BEST'!$C$9:$C1013, 'CF BEST'!$I$9:$I1013, B34,'CF BEST'!$F$9:$F1013, $AC$5) -> 0 | AC34: =SUMIFS('CF BEST'!$D$9:$D1013, 'CF BEST'!$I$9:$I1013, B34,'CF BEST'!$F$9:$F1013, $AC$5) -> 0 | AD34: =SUMIFS('CF BEST'!$C$9:$C1013, 'CF BEST'!$I$9:$I1013, B34,'CF BEST'!$F$9:$F1013, $AE$5) -> 0 | AE34: =SUMIFS('CF BEST'!$D$9:$D1013, 'CF BEST'!$I$9:$I1013, B34,'CF BEST'!$F$9:$F1013, $AE$5) -> 0 | AF34: =SUMIFS('CF BEST'!$C$9:$C1013, 'CF BEST'!$I$9:$I1013, B34,'CF BEST'!$F$9:$F1013, $AG$5) -> 0 | AG34: =SUMIFS('CF BEST'!$D$9:$D1013, 'CF BEST'!$I$9:$I1013, B34,'CF BEST'!$F$9:$F1013, $AG$5) -> 0 | AH34: =SUMIFS('CF BEST'!$C$9:$C1013, 'CF BEST'!$I$9:$I1013, B34,'CF BEST'!$F$9:$F1013, $AI$5)+AB34+AD34+AF34 -> 0 | AI34: =SUMIFS('CF BEST'!$D$9:$D1013, 'CF BEST'!$I$9:$I1013, B34,'CF BEST'!$F$9:$F1013, $AI$5)+AC34+AE34+AG34 -> 0
A35: =C35/$C$7 -> 0.0090169216 | B35: ПРЕДСТАВИТЕЛЬСКИЕ | C35: =K35+S35+AA35+AI35 -> 649060 | D35: =SUMIFS('CF BEST'!$C$9:$C1013, 'CF BEST'!$I$9:$I1013, B35,'CF BEST'!$F$9:$F1013, $E$5) -> 0 | E35: =SUMIFS('CF BEST'!$D$9:$D1013, 'CF BEST'!$I$9:$I1013, B35,'CF BEST'!$F$9:$F1013, $E$5) -> 10000 | F35: =SUMIFS('CF BEST'!$C$9:$C1013, 'CF BEST'!$I$9:$I1013, B35,'CF BEST'!$F$9:$F1013, $G$5) -> 0 | G35: =SUMIFS('CF BEST'!$D$9:$D1013, 'CF BEST'!$I$9:$I1013, B35,'CF BEST'!$F$9:$F1013, $G$5) -> 135900 | H35: =SUMIFS('CF BEST'!$C$9:$C1013, 'CF BEST'!$I$9:$I1013, B35,'CF BEST'!$F$9:$F1013, $I$5) -> 0 | I35: =SUMIFS('CF BEST'!$D$9:$D1013, 'CF BEST'!$I$9:$I1013, B35,'CF BEST'!$F$9:$F1013, $I$5) -> 132165 | J35: =SUMIFS('CF BEST'!$C$9:$C1013, 'CF BEST'!$I$9:$I1013, B35,'CF BEST'!$F$9:$F1013, $K$5)+D35+F35+H35 -> 0 | K35: =SUMIFS('CF BEST'!$D$9:$D1013, 'CF BEST'!$I$9:$I1013, B35,'CF BEST'!$F$9:$F1013, $K$5)+E35+G35+I35 -> 278065 | L35: =SUMIFS('CF BEST'!$C$9:$C1013, 'CF BEST'!$I$9:$I1013, B35,'CF BEST'!$F$9:$F1013, $M$5) -> 0 | M35: =SUMIFS('CF BEST'!$D$9:$D1013, 'CF BEST'!$I$9:$I1013, B35,'CF BEST'!$F$9:$F1013, $M$5) -> 303440 | N35: =SUMIFS('CF BEST'!$C$9:$C1013, 'CF BEST'!$I$9:$I1013, B35,'CF BEST'!$F$9:$F1013, $O$5) -> 0 | O35: =SUMIFS('CF BEST'!$D$9:$D1013, 'CF BEST'!$I$9:$I1013, B35,'CF BEST'!$F$9:$F1013, $O$5) -> 67555 | P35: =SUMIFS('CF BEST'!$C$9:$C1013, 'CF BEST'!$I$9:$I1013, B35,'CF BEST'!$F$9:$F1013, $Q$5) -> 0 | Q35: =SUMIFS('CF BEST'!$D$9:$D1013, 'CF BEST'!$I$9:$I1013, B35,'CF BEST'!$F$9:$F1013, $Q$5) -> 0 | R35: =SUMIFS('CF BEST'!$C$9:$C1013, 'CF BEST'!$I$9:$I1013, B35,'CF BEST'!$F$9:$F1013, $S$5)+L35+N35+P35 -> 0 | S35: =SUMIFS('CF BEST'!$D$9:$D1013, 'CF BEST'!$I$9:$I1013, B35,'CF BEST'!$F$9:$F1013, $S$5)+M35+O35+Q35 -> 370995 | T35: =SUMIFS('CF BEST'!$C$9:$C1013, 'CF BEST'!$I$9:$I1013, B35,'CF BEST'!$F$9:$F1013, $U$5) -> 0 | U35: =SUMIFS('CF BEST'!$D$9:$D1013, 'CF BEST'!$I$9:$I1013, B35,'CF BEST'!$F$9:$F1013, $U$5) -> 0 | V35: =SUMIFS('CF BEST'!$C$9:$C1013, 'CF BEST'!$I$9:$I1013, B35,'CF BEST'!$F$9:$F1013, $W$5) -> 0 | W35: =SUMIFS('CF BEST'!$D$9:$D1013, 'CF BEST'!$I$9:$I1013, B35,'CF BEST'!$F$9:$F1013, $W$5) -> 0 | X35: =SUMIFS('CF BEST'!$C$9:$C1013, 'CF BEST'!$I$9:$I1013, B35,'CF BEST'!$F$9:$F1013, $Y$5) -> 0 | Y35: =SUMIFS('CF BEST'!$D$9:$D1013, 'CF BEST'!$I$9:$I1013, B35,'CF BEST'!$F$9:$F1013, $Y$5) -> 0 | Z35: =SUMIFS('CF BEST'!$C$9:$C1013, 'CF BEST'!$I$9:$I1013, B35,'CF BEST'!$F$9:$F1013, $AA$5)+T35+V35+X35 -> 0 | AA35: =SUMIFS('CF BEST'!$D$9:$D1013, 'CF BEST'!$I$9:$I1013, B35,'CF BEST'!$F$9:$F1013, $AA$5)+U35+W35+Y35 -> 0 | AB35: =SUMIFS('CF BEST'!$C$9:$C1013, 'CF BEST'!$I$9:$I1013, B35,'CF BEST'!$F$9:$F1013, $AC$5) -> 0 | AC35: =SUMIFS('CF BEST'!$D$9:$D1013, 'CF BEST'!$I$9:$I1013, B35,'CF BEST'!$F$9:$F1013, $AC$5) -> 0 | AD35: =SUMIFS('CF BEST'!$C$9:$C1013, 'CF BEST'!$I$9:$I1013, B35,'CF BEST'!$F$9:$F1013, $AE$5) -> 0 | AE35: =SUMIFS('CF BEST'!$D$9:$D1013, 'CF BEST'!$I$9:$I1013, B35,'CF BEST'!$F$9:$F1013, $AE$5) -> 0 | AF35: =SUMIFS('CF BEST'!$C$9:$C1013, 'CF BEST'!$I$9:$I1013, B35,'CF BEST'!$F$9:$F1013, $AG$5) -> 0 | AG35: =SUMIFS('CF BEST'!$D$9:$D1013, 'CF BEST'!$I$9:$I1013, B35,'CF BEST'!$F$9:$F1013, $AG$5) -> 0 | AH35: =SUMIFS('CF BEST'!$C$9:$C1013, 'CF BEST'!$I$9:$I1013, B35,'CF BEST'!$F$9:$F1013, $AI$5)+AB35+AD35+AF35 -> 0 | AI35: =SUMIFS('CF BEST'!$D$9:$D1013, 'CF BEST'!$I$9:$I1013, B35,'CF BEST'!$F$9:$F1013, $AI$5)+AC35+AE35+AG35 -> 0
A36: =C36/$C$7 -> 0.0072106199 | B36: МЕРОПРИЯТИЯ | C36: =K36+S36+AA36+AI36 -> 519038 | D36: =SUMIFS('CF BEST'!$C$9:$C1013, 'CF BEST'!$I$9:$I1013, B36,'CF BEST'!$F$9:$F1013, $E$5) -> 0 | E36: =SUMIFS('CF BEST'!$D$9:$D1013, 'CF BEST'!$I$9:$I1013, B36,'CF BEST'!$F$9:$F1013, $E$5) -> 0 | F36: =SUMIFS('CF BEST'!$C$9:$C1013, 'CF BEST'!$I$9:$I1013, B36,'CF BEST'!$F$9:$F1013, $G$5) -> 0 | G36: =SUMIFS('CF BEST'!$D$9:$D1013, 'CF BEST'!$I$9:$I1013, B36,'CF BEST'!$F$9:$F1013, $G$5) -> 335938 | H36: =SUMIFS('CF BEST'!$C$9:$C1013, 'CF BEST'!$I$9:$I1013, B36,'CF BEST'!$F$9:$F1013, $I$5) -> 0 | I36: =SUMIFS('CF BEST'!$D$9:$D1013, 'CF BEST'!$I$9:$I1013, B36,'CF BEST'!$F$9:$F1013, $I$5) -> 151000 | J36: =SUMIFS('CF BEST'!$C$9:$C1013, 'CF BEST'!$I$9:$I1013, B36,'CF BEST'!$F$9:$F1013, $K$5)+D36+F36+H36 -> 0 | K36: =SUMIFS('CF BEST'!$D$9:$D1013, 'CF BEST'!$I$9:$I1013, B36,'CF BEST'!$F$9:$F1013, $K$5)+E36+G36+I36 -> 486938 | L36: =SUMIFS('CF BEST'!$C$9:$C1013, 'CF BEST'!$I$9:$I1013, B36,'CF BEST'!$F$9:$F1013, $M$5) -> 0 | M36: =SUMIFS('CF BEST'!$D$9:$D1013, 'CF BEST'!$I$9:$I1013, B36,'CF BEST'!$F$9:$F1013, $M$5) -> 0 | N36: =SUMIFS('CF BEST'!$C$9:$C1013, 'CF BEST'!$I$9:$I1013, B36,'CF BEST'!$F$9:$F1013, $O$5) -> 57500 | O36: =SUMIFS('CF BEST'!$D$9:$D1013, 'CF BEST'!$I$9:$I1013, B36,'CF BEST'!$F$9:$F1013, $O$5) -> 32100 | P36: =SUMIFS('CF BEST'!$C$9:$C1013, 'CF BEST'!$I$9:$I1013, B36,'CF BEST'!$F$9:$F1013, $Q$5) -> 0 | Q36: =SUMIFS('CF BEST'!$D$9:$D1013, 'CF BEST'!$I$9:$I1013, B36,'CF BEST'!$F$9:$F1013, $Q$5) -> 0 | R36: =SUMIFS('CF BEST'!$C$9:$C1013, 'CF BEST'!$I$9:$I1013, B36,'CF BEST'!$F$9:$F1013, $S$5)+L36+N36+P36 -> 57500 | S36: =SUMIFS('CF BEST'!$D$9:$D1013, 'CF BEST'!$I$9:$I1013, B36,'CF BEST'!$F$9:$F1013, $S$5)+M36+O36+Q36 -> 32100 | T36: =SUMIFS('CF BEST'!$C$9:$C1013, 'CF BEST'!$I$9:$I1013, B36,'CF BEST'!$F$9:$F1013, $U$5) -> 0 | U36: =SUMIFS('CF BEST'!$D$9:$D1013, 'CF BEST'!$I$9:$I1013, B36,'CF BEST'!$F$9:$F1013, $U$5) -> 0 | V36: =SUMIFS('CF BEST'!$C$9:$C1013, 'CF BEST'!$I$9:$I1013, B36,'CF BEST'!$F$9:$F1013, $W$5) -> 0 | W36: =SUMIFS('CF BEST'!$D$9:$D1013, 'CF BEST'!$I$9:$I1013, B36,'CF BEST'!$F$9:$F1013, $W$5) -> 0 | X36: =SUMIFS('CF BEST'!$C$9:$C1013, 'CF BEST'!$I$9:$I1013, B36,'CF BEST'!$F$9:$F1013, $Y$5) -> 0 | Y36: =SUMIFS('CF BEST'!$D$9:$D1013, 'CF BEST'!$I$9:$I1013, B36,'CF BEST'!$F$9:$F1013, $Y$5) -> 0 | Z36: =SUMIFS('CF BEST'!$C$9:$C1013, 'CF BEST'!$I$9:$I1013, B36,'CF BEST'!$F$9:$F1013, $AA$5)+T36+V36+X36 -> 0 | AA36: =SUMIFS('CF BEST'!$D$9:$D1013, 'CF BEST'!$I$9:$I1013, B36,'CF BEST'!$F$9:$F1013, $AA$5)+U36+W36+Y36 -> 0 | AB36: =SUMIFS('CF BEST'!$C$9:$C1013, 'CF BEST'!$I$9:$I1013, B36,'CF BEST'!$F$9:$F1013, $AC$5) -> 0 | AC36: =SUMIFS('CF BEST'!$D$9:$D1013, 'CF BEST'!$I$9:$I1013, B36,'CF BEST'!$F$9:$F1013, $AC$5) -> 0 | AD36: =SUMIFS('CF BEST'!$C$9:$C1013, 'CF BEST'!$I$9:$I1013, B36,'CF BEST'!$F$9:$F1013, $AE$5) -> 0 | AE36: =SUMIFS('CF BEST'!$D$9:$D1013, 'CF BEST'!$I$9:$I1013, B36,'CF BEST'!$F$9:$F1013, $AE$5) -> 0 | AF36: =SUMIFS('CF BEST'!$C$9:$C1013, 'CF BEST'!$I$9:$I1013, B36,'CF BEST'!$F$9:$F1013, $AG$5) -> 0 | AG36: =SUMIFS('CF BEST'!$D$9:$D1013, 'CF BEST'!$I$9:$I1013, B36,'CF BEST'!$F$9:$F1013, $AG$5) -> 0 | AH36: =SUMIFS('CF BEST'!$C$9:$C1013, 'CF BEST'!$I$9:$I1013, B36,'CF BEST'!$F$9:$F1013, $AI$5)+AB36+AD36+AF36 -> 0 | AI36: =SUMIFS('CF BEST'!$D$9:$D1013, 'CF BEST'!$I$9:$I1013, B36,'CF BEST'!$F$9:$F1013, $AI$5)+AC36+AE36+AG36 -> 0
A37: =C37/$C$7 -> 0 | B37: ГОЛЬФ | C37: =K37+S37+AA37+AI37 -> 0 | D37: =SUMIFS('CF BEST'!$C$9:$C1013, 'CF BEST'!$I$9:$I1013, B37,'CF BEST'!$F$9:$F1013, $E$5) -> 0 | E37: =SUMIFS('CF BEST'!$D$9:$D1013, 'CF BEST'!$I$9:$I1013, B37,'CF BEST'!$F$9:$F1013, $E$5) -> 0 | F37: =SUMIFS('CF BEST'!$C$9:$C1013, 'CF BEST'!$I$9:$I1013, B37,'CF BEST'!$F$9:$F1013, $G$5) -> 0 | G37: =SUMIFS('CF BEST'!$D$9:$D1013, 'CF BEST'!$I$9:$I1013, B37,'CF BEST'!$F$9:$F1013, $G$5) -> 0 | H37: =SUMIFS('CF BEST'!$C$9:$C1013, 'CF BEST'!$I$9:$I1013, B37,'CF BEST'!$F$9:$F1013, $I$5) -> 0 | I37: =SUMIFS('CF BEST'!$D$9:$D1013, 'CF BEST'!$I$9:$I1013, B37,'CF BEST'!$F$9:$F1013, $I$5) -> 0 | J37: =SUMIFS('CF BEST'!$C$9:$C1013, 'CF BEST'!$I$9:$I1013, B37,'CF BEST'!$F$9:$F1013, $K$5)+D37+F37+H37 -> 0 | K37: =SUMIFS('CF BEST'!$D$9:$D1013, 'CF BEST'!$I$9:$I1013, B37,'CF BEST'!$F$9:$F1013, $K$5)+E37+G37+I37 -> 0 | L37: =SUMIFS('CF BEST'!$C$9:$C1013, 'CF BEST'!$I$9:$I1013, B37,'CF BEST'!$F$9:$F1013, $M$5) -> 0 | M37: =SUMIFS('CF BEST'!$D$9:$D1013, 'CF BEST'!$I$9:$I1013, B37,'CF BEST'!$F$9:$F1013, $M$5) -> 0 | N37: =SUMIFS('CF BEST'!$C$9:$C1013, 'CF BEST'!$I$9:$I1013, B37,'CF BEST'!$F$9:$F1013, $O$5) -> 0 | O37: =SUMIFS('CF BEST'!$D$9:$D1013, 'CF BEST'!$I$9:$I1013, B37,'CF BEST'!$F$9:$F1013, $O$5) -> 0 | P37: =SUMIFS('CF BEST'!$C$9:$C1013, 'CF BEST'!$I$9:$I1013, B37,'CF BEST'!$F$9:$F1013, $Q$5) -> 0 | Q37: =SUMIFS('CF BEST'!$D$9:$D1013, 'CF BEST'!$I$9:$I1013, B37,'CF BEST'!$F$9:$F1013, $Q$5) -> 0 | R37: =SUMIFS('CF BEST'!$C$9:$C1013, 'CF BEST'!$I$9:$I1013, B37,'CF BEST'!$F$9:$F1013, $S$5)+L37+N37+P37 -> 0 | S37: =SUMIFS('CF BEST'!$D$9:$D1013, 'CF BEST'!$I$9:$I1013, B37,'CF BEST'!$F$9:$F1013, $S$5)+M37+O37+Q37 -> 0 | T37: =SUMIFS('CF BEST'!$C$9:$C1013, 'CF BEST'!$I$9:$I1013, B37,'CF BEST'!$F$9:$F1013, $U$5) -> 0 | U37: =SUMIFS('CF BEST'!$D$9:$D1013, 'CF BEST'!$I$9:$I1013, B37,'CF BEST'!$F$9:$F1013, $U$5) -> 0 | V37: =SUMIFS('CF BEST'!$C$9:$C1013, 'CF BEST'!$I$9:$I1013, B37,'CF BEST'!$F$9:$F1013, $W$5) -> 0 | W37: =SUMIFS('CF BEST'!$D$9:$D1013, 'CF BEST'!$I$9:$I1013, B37,'CF BEST'!$F$9:$F1013, $W$5) -> 0 | X37: =SUMIFS('CF BEST'!$C$9:$C1013, 'CF BEST'!$I$9:$I1013, B37,'CF BEST'!$F$9:$F1013, $Y$5) -> 0 | Y37: =SUMIFS('CF BEST'!$D$9:$D1013, 'CF BEST'!$I$9:$I1013, B37,'CF BEST'!$F$9:$F1013, $Y$5) -> 0 | Z37: =SUMIFS('CF BEST'!$C$9:$C1013, 'CF BEST'!$I$9:$I1013, B37,'CF BEST'!$F$9:$F1013, $AA$5)+T37+V37+X37 -> 0 | AA37: =SUMIFS('CF BEST'!$D$9:$D1013, 'CF BEST'!$I$9:$I1013, B37,'CF BEST'!$F$9:$F1013, $AA$5)+U37+W37+Y37 -> 0 | AB37: =SUMIFS('CF BEST'!$C$9:$C1013, 'CF BEST'!$I$9:$I1013, B37,'CF BEST'!$F$9:$F1013, $AC$5) -> 0 | AC37: =SUMIFS('CF BEST'!$D$9:$D1013, 'CF BEST'!$I$9:$I1013, B37,'CF BEST'!$F$9:$F1013, $AC$5) -> 0 | AD37: =SUMIFS('CF BEST'!$C$9:$C1013, 'CF BEST'!$I$9:$I1013, B37,'CF BEST'!$F$9:$F1013, $AE$5) -> 0 | AE37: =SUMIFS('CF BEST'!$D$9:$D1013, 'CF BEST'!$I$9:$I1013, B37,'CF BEST'!$F$9:$F1013, $AE$5) -> 0 | AF37: =SUMIFS('CF BEST'!$C$9:$C1013, 'CF BEST'!$I$9:$I1013, B37,'CF BEST'!$F$9:$F1013, $AG$5) -> 0 | AG37: =SUMIFS('CF BEST'!$D$9:$D1013, 'CF BEST'!$I$9:$I1013, B37,'CF BEST'!$F$9:$F1013, $AG$5) -> 0 | AH37: =SUMIFS('CF BEST'!$C$9:$C1013, 'CF BEST'!$I$9:$I1013, B37,'CF BEST'!$F$9:$F1013, $AI$5)+AB37+AD37+AF37 -> 0 | AI37: =SUMIFS('CF BEST'!$D$9:$D1013, 'CF BEST'!$I$9:$I1013, B37,'CF BEST'!$F$9:$F1013, $AI$5)+AC37+AE37+AG37 -> 0
A38: =C38/$C$7 -> 0.0031257624 | B38: PR | C38: =K38+S38+AA38+AI38 -> 225000 | D38: =SUMIFS('CF BEST'!$C$9:$C1013, 'CF BEST'!$I$9:$I1013, B38,'CF BEST'!$F$9:$F1013, $E$5) -> 0 | E38: =SUMIFS('CF BEST'!$D$9:$D1013, 'CF BEST'!$I$9:$I1013, B38,'CF BEST'!$F$9:$F1013, $E$5) -> 0 | F38: =SUMIFS('CF BEST'!$C$9:$C1013, 'CF BEST'!$I$9:$I1013, B38,'CF BEST'!$F$9:$F1013, $G$5) -> 0 | G38: =SUMIFS('CF BEST'!$D$9:$D1013, 'CF BEST'!$I$9:$I1013, B38,'CF BEST'!$F$9:$F1013, $G$5) -> 225000 | H38: =SUMIFS('CF BEST'!$C$9:$C1013, 'CF BEST'!$I$9:$I1013, B38,'CF BEST'!$F$9:$F1013, $I$5) -> 0 | I38: =SUMIFS('CF BEST'!$D$9:$D1013, 'CF BEST'!$I$9:$I1013, B38,'CF BEST'!$F$9:$F1013, $I$5) -> 0 | J38: =SUMIFS('CF BEST'!$C$9:$C1013, 'CF BEST'!$I$9:$I1013, B38,'CF BEST'!$F$9:$F1013, $K$5)+D38+F38+H38 -> 0 | K38: =SUMIFS('CF BEST'!$D$9:$D1013, 'CF BEST'!$I$9:$I1013, B38,'CF BEST'!$F$9:$F1013, $K$5)+E38+G38+I38 -> 225000 | L38: =SUMIFS('CF BEST'!$C$9:$C1013, 'CF BEST'!$I$9:$I1013, B38,'CF BEST'!$F$9:$F1013, $M$5) -> 0 | M38: =SUMIFS('CF BEST'!$D$9:$D1013, 'CF BEST'!$I$9:$I1013, B38,'CF BEST'!$F$9:$F1013, $M$5) -> 0 | N38: =SUMIFS('CF BEST'!$C$9:$C1013, 'CF BEST'!$I$9:$I1013, B38,'CF BEST'!$F$9:$F1013, $O$5) -> 0 | O38: =SUMIFS('CF BEST'!$D$9:$D1013, 'CF BEST'!$I$9:$I1013, B38,'CF BEST'!$F$9:$F1013, $O$5) -> 0 | P38: =SUMIFS('CF BEST'!$C$9:$C1013, 'CF BEST'!$I$9:$I1013, B38,'CF BEST'!$F$9:$F1013, $Q$5) -> 0 | Q38: =SUMIFS('CF BEST'!$D$9:$D1013, 'CF BEST'!$I$9:$I1013, B38,'CF BEST'!$F$9:$F1013, $Q$5) -> 0 | R38: =SUMIFS('CF BEST'!$C$9:$C1013, 'CF BEST'!$I$9:$I1013, B38,'CF BEST'!$F$9:$F1013, $S$5)+L38+N38+P38 -> 0 | S38: =SUMIFS('CF BEST'!$D$9:$D1013, 'CF BEST'!$I$9:$I1013, B38,'CF BEST'!$F$9:$F1013, $S$5)+M38+O38+Q38 -> 0 | T38: =SUMIFS('CF BEST'!$C$9:$C1013, 'CF BEST'!$I$9:$I1013, B38,'CF BEST'!$F$9:$F1013, $U$5) -> 0 | U38: =SUMIFS('CF BEST'!$D$9:$D1013, 'CF BEST'!$I$9:$I1013, B38,'CF BEST'!$F$9:$F1013, $U$5) -> 0 | V38: =SUMIFS('CF BEST'!$C$9:$C1013, 'CF BEST'!$I$9:$I1013, B38,'CF BEST'!$F$9:$F1013, $W$5) -> 0 | W38: =SUMIFS('CF BEST'!$D$9:$D1013, 'CF BEST'!$I$9:$I1013, B38,'CF BEST'!$F$9:$F1013, $W$5) -> 0 | X38: =SUMIFS('CF BEST'!$C$9:$C1013, 'CF BEST'!$I$9:$I1013, B38,'CF BEST'!$F$9:$F1013, $Y$5) -> 0 | Y38: =SUMIFS('CF BEST'!$D$9:$D1013, 'CF BEST'!$I$9:$I1013, B38,'CF BEST'!$F$9:$F1013, $Y$5) -> 0 | Z38: =SUMIFS('CF BEST'!$C$9:$C1013, 'CF BEST'!$I$9:$I1013, B38,'CF BEST'!$F$9:$F1013, $AA$5)+T38+V38+X38 -> 0 | AA38: =SUMIFS('CF BEST'!$D$9:$D1013, 'CF BEST'!$I$9:$I1013, B38,'CF BEST'!$F$9:$F1013, $AA$5)+U38+W38+Y38 -> 0 | AB38: =SUMIFS('CF BEST'!$C$9:$C1013, 'CF BEST'!$I$9:$I1013, B38,'CF BEST'!$F$9:$F1013, $AC$5) -> 0 | AC38: =SUMIFS('CF BEST'!$D$9:$D1013, 'CF BEST'!$I$9:$I1013, B38,'CF BEST'!$F$9:$F1013, $AC$5) -> 0 | AD38: =SUMIFS('CF BEST'!$C$9:$C1013, 'CF BEST'!$I$9:$I1013, B38,'CF BEST'!$F$9:$F1013, $AE$5) -> 0 | AE38: =SUMIFS('CF BEST'!$D$9:$D1013, 'CF BEST'!$I$9:$I1013, B38,'CF BEST'!$F$9:$F1013, $AE$5) -> 0 | AF38: =SUMIFS('CF BEST'!$C$9:$C1013, 'CF BEST'!$I$9:$I1013, B38,'CF BEST'!$F$9:$F1013, $AG$5) -> 0 | AG38: =SUMIFS('CF BEST'!$D$9:$D1013, 'CF BEST'!$I$9:$I1013, B38,'CF BEST'!$F$9:$F1013, $AG$5) -> 0 | AH38: =SUMIFS('CF BEST'!$C$9:$C1013, 'CF BEST'!$I$9:$I1013, B38,'CF BEST'!$F$9:$F1013, $AI$5)+AB38+AD38+AF38 -> 0 | AI38: =SUMIFS('CF BEST'!$D$9:$D1013, 'CF BEST'!$I$9:$I1013, B38,'CF BEST'!$F$9:$F1013, $AI$5)+AC38+AE38+AG38 -> 0
A39: =C39/$C$7 -> 0 | B39: ДОЛГ | C39: =K39+S39+AA39+AI39 -> 0 | D39: =SUMIFS('CF BEST'!$C$9:$C1013, 'CF BEST'!$I$9:$I1013, B39,'CF BEST'!$F$9:$F1013, $E$5) -> 0 | E39: =SUMIFS('CF BEST'!$D$9:$D1013, 'CF BEST'!$I$9:$I1013, B39,'CF BEST'!$F$9:$F1013, $E$5) -> 0 | F39: =SUMIFS('CF BEST'!$C$9:$C1013, 'CF BEST'!$I$9:$I1013, B39,'CF BEST'!$F$9:$F1013, $G$5) -> 0 | G39: =SUMIFS('CF BEST'!$D$9:$D1013, 'CF BEST'!$I$9:$I1013, B39,'CF BEST'!$F$9:$F1013, $G$5) -> 0 | H39: =SUMIFS('CF BEST'!$C$9:$C1013, 'CF BEST'!$I$9:$I1013, B39,'CF BEST'!$F$9:$F1013, $I$5) -> 0 | I39: =SUMIFS('CF BEST'!$D$9:$D1013, 'CF BEST'!$I$9:$I1013, B39,'CF BEST'!$F$9:$F1013, $I$5) -> 0 | J39: =SUMIFS('CF BEST'!$C$9:$C1013, 'CF BEST'!$I$9:$I1013, B39,'CF BEST'!$F$9:$F1013, $K$5)+D39+F39+H39 -> 0 | K39: =SUMIFS('CF BEST'!$D$9:$D1013, 'CF BEST'!$I$9:$I1013, B39,'CF BEST'!$F$9:$F1013, $K$5)+E39+G39+I39 -> 0 | L39: =SUMIFS('CF BEST'!$C$9:$C1013, 'CF BEST'!$I$9:$I1013, B39,'CF BEST'!$F$9:$F1013, $M$5) -> 0 | M39: =SUMIFS('CF BEST'!$D$9:$D1013, 'CF BEST'!$I$9:$I1013, B39,'CF BEST'!$F$9:$F1013, $M$5) -> 0 | N39: =SUMIFS('CF BEST'!$C$9:$C1013, 'CF BEST'!$I$9:$I1013, B39,'CF BEST'!$F$9:$F1013, $O$5) -> 0 | O39: =SUMIFS('CF BEST'!$D$9:$D1013, 'CF BEST'!$I$9:$I1013, B39,'CF BEST'!$F$9:$F1013, $O$5) -> 0 | P39: =SUMIFS('CF BEST'!$C$9:$C1013, 'CF BEST'!$I$9:$I1013, B39,'CF BEST'!$F$9:$F1013, $Q$5) -> 0 | Q39: =SUMIFS('CF BEST'!$D$9:$D1013, 'CF BEST'!$I$9:$I1013, B39,'CF BEST'!$F$9:$F1013, $Q$5) -> 0 | R39: =SUMIFS('CF BEST'!$C$9:$C1013, 'CF BEST'!$I$9:$I1013, B39,'CF BEST'!$F$9:$F1013, $S$5)+L39+N39+P39 -> 0 | S39: =SUMIFS('CF BEST'!$D$9:$D1013, 'CF BEST'!$I$9:$I1013, B39,'CF BEST'!$F$9:$F1013, $S$5)+M39+O39+Q39 -> 0 | T39: =SUMIFS('CF BEST'!$C$9:$C1013, 'CF BEST'!$I$9:$I1013, B39,'CF BEST'!$F$9:$F1013, $U$5) -> 0 | U39: =SUMIFS('CF BEST'!$D$9:$D1013, 'CF BEST'!$I$9:$I1013, B39,'CF BEST'!$F$9:$F1013, $U$5) -> 0 | V39: =SUMIFS('CF BEST'!$C$9:$C1013, 'CF BEST'!$I$9:$I1013, B39,'CF BEST'!$F$9:$F1013, $W$5) -> 0 | W39: =SUMIFS('CF BEST'!$D$9:$D1013, 'CF BEST'!$I$9:$I1013, B39,'CF BEST'!$F$9:$F1013, $W$5) -> 0 | X39: =SUMIFS('CF BEST'!$C$9:$C1013, 'CF BEST'!$I$9:$I1013, B39,'CF BEST'!$F$9:$F1013, $Y$5) -> 0 | Y39: =SUMIFS('CF BEST'!$D$9:$D1013, 'CF BEST'!$I$9:$I1013, B39,'CF BEST'!$F$9:$F1013, $Y$5) -> 0 | Z39: =SUMIFS('CF BEST'!$C$9:$C1013, 'CF BEST'!$I$9:$I1013, B39,'CF BEST'!$F$9:$F1013, $AA$5)+T39+V39+X39 -> 0 | AA39: =SUMIFS('CF BEST'!$D$9:$D1013, 'CF BEST'!$I$9:$I1013, B39,'CF BEST'!$F$9:$F1013, $AA$5)+U39+W39+Y39 -> 0 | AB39: =SUMIFS('CF BEST'!$C$9:$C1013, 'CF BEST'!$I$9:$I1013, B39,'CF BEST'!$F$9:$F1013, $AC$5) -> 0 | AC39: =SUMIFS('CF BEST'!$D$9:$D1013, 'CF BEST'!$I$9:$I1013, B39,'CF BEST'!$F$9:$F1013, $AC$5) -> 0 | AD39: =SUMIFS('CF BEST'!$C$9:$C1013, 'CF BEST'!$I$9:$I1013, B39,'CF BEST'!$F$9:$F1013, $AE$5) -> 0 | AE39: =SUMIFS('CF BEST'!$D$9:$D1013, 'CF BEST'!$I$9:$I1013, B39,'CF BEST'!$F$9:$F1013, $AE$5) -> 0 | AF39: =SUMIFS('CF BEST'!$C$9:$C1013, 'CF BEST'!$I$9:$I1013, B39,'CF BEST'!$F$9:$F1013, $AG$5) -> 0 | AG39: =SUMIFS('CF BEST'!$D$9:$D1013, 'CF BEST'!$I$9:$I1013, B39,'CF BEST'!$F$9:$F1013, $AG$5) -> 0 | AH39: =SUMIFS('CF BEST'!$C$9:$C1013, 'CF BEST'!$I$9:$I1013, B39,'CF BEST'!$F$9:$F1013, $AI$5)+AB39+AD39+AF39 -> 0 | AI39: =SUMIFS('CF BEST'!$D$9:$D1013, 'CF BEST'!$I$9:$I1013, B39,'CF BEST'!$F$9:$F1013, $AI$5)+AC39+AE39+AG39 -> 0
A40: =C40/$C$7 -> 0.0059297822 | B40: ПОДПИСКИ | C40: =K40+S40+AA40+AI40 -> 426840.18 | D40: =SUMIFS('CF BEST'!$C$9:$C1013, 'CF BEST'!$I$9:$I1013, B40,'CF BEST'!$F$9:$F1013, $E$5) -> 0 | E40: =SUMIFS('CF BEST'!$D$9:$D1013, 'CF BEST'!$I$9:$I1013, B40,'CF BEST'!$F$9:$F1013, $E$5) -> 0 | F40: =SUMIFS('CF BEST'!$C$9:$C1013, 'CF BEST'!$I$9:$I1013, B40,'CF BEST'!$F$9:$F1013, $G$5) -> 0 | G40: =SUMIFS('CF BEST'!$D$9:$D1013, 'CF BEST'!$I$9:$I1013, B40,'CF BEST'!$F$9:$F1013, $G$5) -> 51900 | H40: =SUMIFS('CF BEST'!$C$9:$C1013, 'CF BEST'!$I$9:$I1013, B40,'CF BEST'!$F$9:$F1013, $I$5) -> 0 | I40: =SUMIFS('CF BEST'!$D$9:$D1013, 'CF BEST'!$I$9:$I1013, B40,'CF BEST'!$F$9:$F1013, $I$5) -> 51900 | J40: =SUMIFS('CF BEST'!$C$9:$C1013, 'CF BEST'!$I$9:$I1013, B40,'CF BEST'!$F$9:$F1013, $K$5)+D40+F40+H40 -> 0 | K40: =SUMIFS('CF BEST'!$D$9:$D1013, 'CF BEST'!$I$9:$I1013, B40,'CF BEST'!$F$9:$F1013, $K$5)+E40+G40+I40 -> 103800 | L40: =SUMIFS('CF BEST'!$C$9:$C1013, 'CF BEST'!$I$9:$I1013, B40,'CF BEST'!$F$9:$F1013, $M$5) -> 0 | M40: =SUMIFS('CF BEST'!$D$9:$D1013, 'CF BEST'!$I$9:$I1013, B40,'CF BEST'!$F$9:$F1013, $M$5) -> 171704.98 | N40: =SUMIFS('CF BEST'!$C$9:$C1013, 'CF BEST'!$I$9:$I1013, B40,'CF BEST'!$F$9:$F1013, $O$5) -> 0 | O40: =SUMIFS('CF BEST'!$D$9:$D1013, 'CF BEST'!$I$9:$I1013, B40,'CF BEST'!$F$9:$F1013, $O$5) -> 1000 | P40: =SUMIFS('CF BEST'!$C$9:$C1013, 'CF BEST'!$I$9:$I1013, B40,'CF BEST'!$F$9:$F1013, $Q$5) -> 0 | Q40: =SUMIFS('CF BEST'!$D$9:$D1013, 'CF BEST'!$I$9:$I1013, B40,'CF BEST'!$F$9:$F1013, $Q$5) -> 150335.2 | R40: =SUMIFS('CF BEST'!$C$9:$C1013, 'CF BEST'!$I$9:$I1013, B40,'CF BEST'!$F$9:$F1013, $S$5)+L40+N40+P40 -> 0 | S40: =SUMIFS('CF BEST'!$D$9:$D1013, 'CF BEST'!$I$9:$I1013, B40,'CF BEST'!$F$9:$F1013, $S$5)+M40+O40+Q40 -> 323040.18 | T40: =SUMIFS('CF BEST'!$C$9:$C1013, 'CF BEST'!$I$9:$I1013, B40,'CF BEST'!$F$9:$F1013, $U$5) -> 0 | U40: =SUMIFS('CF BEST'!$D$9:$D1013, 'CF BEST'!$I$9:$I1013, B40,'CF BEST'!$F$9:$F1013, $U$5) -> 0 | V40: =SUMIFS('CF BEST'!$C$9:$C1013, 'CF BEST'!$I$9:$I1013, B40,'CF BEST'!$F$9:$F1013, $W$5) -> 0 | W40: =SUMIFS('CF BEST'!$D$9:$D1013, 'CF BEST'!$I$9:$I1013, B40,'CF BEST'!$F$9:$F1013, $W$5) -> 0 | X40: =SUMIFS('CF BEST'!$C$9:$C1013, 'CF BEST'!$I$9:$I1013, B40,'CF BEST'!$F$9:$F1013, $Y$5) -> 0 | Y40: =SUMIFS('CF BEST'!$D$9:$D1013, 'CF BEST'!$I$9:$I1013, B40,'CF BEST'!$F$9:$F1013, $Y$5) -> 0 | Z40: =SUMIFS('CF BEST'!$C$9:$C1013, 'CF BEST'!$I$9:$I1013, B40,'CF BEST'!$F$9:$F1013, $AA$5)+T40+V40+X40 -> 0 | AA40: =SUMIFS('CF BEST'!$D$9:$D1013, 'CF BEST'!$I$9:$I1013, B40,'CF BEST'!$F$9:$F1013, $AA$5)+U40+W40+Y40 -> 0 | AB40: =SUMIFS('CF BEST'!$C$9:$C1013, 'CF BEST'!$I$9:$I1013, B40,'CF BEST'!$F$9:$F1013, $AC$5) -> 0 | AC40: =SUMIFS('CF BEST'!$D$9:$D1013, 'CF BEST'!$I$9:$I1013, B40,'CF BEST'!$F$9:$F1013, $AC$5) -> 0 | AD40: =SUMIFS('CF BEST'!$C$9:$C1013, 'CF BEST'!$I$9:$I1013, B40,'CF BEST'!$F$9:$F1013, $AE$5) -> 0 | AE40: =SUMIFS('CF BEST'!$D$9:$D1013, 'CF BEST'!$I$9:$I1013, B40,'CF BEST'!$F$9:$F1013, $AE$5) -> 0 | AF40: =SUMIFS('CF BEST'!$C$9:$C1013, 'CF BEST'!$I$9:$I1013, B40,'CF BEST'!$F$9:$F1013, $AG$5) -> 0 | AG40: =SUMIFS('CF BEST'!$D$9:$D1013, 'CF BEST'!$I$9:$I1013, B40,'CF BEST'!$F$9:$F1013, $AG$5) -> 0 | AH40: =SUMIFS('CF BEST'!$C$9:$C1013, 'CF BEST'!$I$9:$I1013, B40,'CF BEST'!$F$9:$F1013, $AI$5)+AB40+AD40+AF40 -> 0 | AI40: =SUMIFS('CF BEST'!$D$9:$D1013, 'CF BEST'!$I$9:$I1013, B40,'CF BEST'!$F$9:$F1013, $AI$5)+AC40+AE40+AG40 -> 0
A41: =C41/$C$7 -> 0.00029173783 | B41: ПРОЧЕЕ | C41: =K41+S41+AA41+AI41 -> 21000 | D41: =SUMIFS('CF BEST'!$C$9:$C1013, 'CF BEST'!$I$9:$I1013, B41,'CF BEST'!$F$9:$F1013, $E$5) -> 0 | E41: =SUMIFS('CF BEST'!$D$9:$D1013, 'CF BEST'!$I$9:$I1013, B41,'CF BEST'!$F$9:$F1013, $E$5) -> 0 | F41: =SUMIFS('CF BEST'!$C$9:$C1013, 'CF BEST'!$I$9:$I1013, B41,'CF BEST'!$F$9:$F1013, $G$5) -> 0 | G41: =SUMIFS('CF BEST'!$D$9:$D1013, 'CF BEST'!$I$9:$I1013, B41,'CF BEST'!$F$9:$F1013, $G$5) -> 0 | H41: =SUMIFS('CF BEST'!$C$9:$C1013, 'CF BEST'!$I$9:$I1013, B41,'CF BEST'!$F$9:$F1013, $I$5) -> 1386266 | I41: =SUMIFS('CF BEST'!$D$9:$D1013, 'CF BEST'!$I$9:$I1013, B41,'CF BEST'!$F$9:$F1013, $I$5) -> 21000 | J41: =SUMIFS('CF BEST'!$C$9:$C1013, 'CF BEST'!$I$9:$I1013, B41,'CF BEST'!$F$9:$F1013, $K$5)+D41+F41+H41 -> 1386266 | K41: =SUMIFS('CF BEST'!$D$9:$D1013, 'CF BEST'!$I$9:$I1013, B41,'CF BEST'!$F$9:$F1013, $K$5)+E41+G41+I41 -> 21000 | L41: =SUMIFS('CF BEST'!$C$9:$C1013, 'CF BEST'!$I$9:$I1013, B41,'CF BEST'!$F$9:$F1013, $M$5) -> 0 | M41: =SUMIFS('CF BEST'!$D$9:$D1013, 'CF BEST'!$I$9:$I1013, B41,'CF BEST'!$F$9:$F1013, $M$5) -> 0 | N41: =SUMIFS('CF BEST'!$C$9:$C1013, 'CF BEST'!$I$9:$I1013, B41,'CF BEST'!$F$9:$F1013, $O$5) -> 0 | O41: =SUMIFS('CF BEST'!$D$9:$D1013, 'CF BEST'!$I$9:$I1013, B41,'CF BEST'!$F$9:$F1013, $O$5) -> 0 | P41: =SUMIFS('CF BEST'!$C$9:$C1013, 'CF BEST'!$I$9:$I1013, B41,'CF BEST'!$F$9:$F1013, $Q$5) -> 0 | Q41: =SUMIFS('CF BEST'!$D$9:$D1013, 'CF BEST'!$I$9:$I1013, B41,'CF BEST'!$F$9:$F1013, $Q$5) -> 0 | R41: =SUMIFS('CF BEST'!$C$9:$C1013, 'CF BEST'!$I$9:$I1013, B41,'CF BEST'!$F$9:$F1013, $S$5)+L41+N41+P41 -> 0 | S41: =SUMIFS('CF BEST'!$D$9:$D1013, 'CF BEST'!$I$9:$I1013, B41,'CF BEST'!$F$9:$F1013, $S$5)+M41+O41+Q41 -> 0 | T41: =SUMIFS('CF BEST'!$C$9:$C1013, 'CF BEST'!$I$9:$I1013, B41,'CF BEST'!$F$9:$F1013, $U$5) -> 0 | U41: =SUMIFS('CF BEST'!$D$9:$D1013, 'CF BEST'!$I$9:$I1013, B41,'CF BEST'!$F$9:$F1013, $U$5) -> 0 | V41: =SUMIFS('CF BEST'!$C$9:$C1013, 'CF BEST'!$I$9:$I1013, B41,'CF BEST'!$F$9:$F1013, $W$5) -> 0 | W41: =SUMIFS('CF BEST'!$D$9:$D1013, 'CF BEST'!$I$9:$I1013, B41,'CF BEST'!$F$9:$F1013, $W$5) -> 0 | X41: =SUMIFS('CF BEST'!$C$9:$C1013, 'CF BEST'!$I$9:$I1013, B41,'CF BEST'!$F$9:$F1013, $Y$5) -> 0 | Y41: =SUMIFS('CF BEST'!$D$9:$D1013, 'CF BEST'!$I$9:$I1013, B41,'CF BEST'!$F$9:$F1013, $Y$5) -> 0 | Z41: =SUMIFS('CF BEST'!$C$9:$C1013, 'CF BEST'!$I$9:$I1013, B41,'CF BEST'!$F$9:$F1013, $AA$5)+T41+V41+X41 -> 0 | AA41: =SUMIFS('CF BEST'!$D$9:$D1013, 'CF BEST'!$I$9:$I1013, B41,'CF BEST'!$F$9:$F1013, $AA$5)+U41+W41+Y41 -> 0 | AB41: =SUMIFS('CF BEST'!$C$9:$C1013, 'CF BEST'!$I$9:$I1013, B41,'CF BEST'!$F$9:$F1013, $AC$5) -> 0 | AC41: =SUMIFS('CF BEST'!$D$9:$D1013, 'CF BEST'!$I$9:$I1013, B41,'CF BEST'!$F$9:$F1013, $AC$5) -> 0 | AD41: =SUMIFS('CF BEST'!$C$9:$C1013, 'CF BEST'!$I$9:$I1013, B41,'CF BEST'!$F$9:$F1013, $AE$5) -> 0 | AE41: =SUMIFS('CF BEST'!$D$9:$D1013, 'CF BEST'!$I$9:$I1013, B41,'CF BEST'!$F$9:$F1013, $AE$5) -> 0 | AF41: =SUMIFS('CF BEST'!$C$9:$C1013, 'CF BEST'!$I$9:$I1013, B41,'CF BEST'!$F$9:$F1013, $AG$5) -> 0 | AG41: =SUMIFS('CF BEST'!$D$9:$D1013, 'CF BEST'!$I$9:$I1013, B41,'CF BEST'!$F$9:$F1013, $AG$5) -> 0 | AH41: =SUMIFS('CF BEST'!$C$9:$C1013, 'CF BEST'!$I$9:$I1013, B41,'CF BEST'!$F$9:$F1013, $AI$5)+AB41+AD41+AF41 -> 0 | AI41: =SUMIFS('CF BEST'!$D$9:$D1013, 'CF BEST'!$I$9:$I1013, B41,'CF BEST'!$F$9:$F1013, $AI$5)+AC41+AE41+AG41 -> 0
B43: СК | C43: =(C8+C9)/C1 -> 0.17124768 | D43: =(E8+E9)/D1 -> 0 | F43: =(G8+G9)/F1 -> 0 | H43: =(I8+I9)/H1 -> 0 | J43: =(K8+K9)/J1 -> 0.151459 | L43: =(M8+M9)/L1 -> 0.26528706 | N43: =(O8+O9)/N1 -> 0 | P43: =(Q8+Q9)/P1 -> 0 | R43: =(S8+S9)/R1 -> 0.22555044 | T43: =(U8+U9)/T1 -> #DIV/0! | V43: =(W8+W9)/V1 -> #DIV/0! | X43: =(Y8+Y9)/X1 -> #DIV/0! | Z43: =(AA8+AA9)/Z1 -> #DIV/0! | AB43: =(AC8+AC9)/AB1 -> 0 | AD43: =(AE8+AE9)/AD1 -> #DIV/0! | AF43: =(AG8+AG9)/AF1 -> #DIV/0! | AH43: =(AI8+AI9)/AH1 -> 0
B44: ПЛОЩАДКИ | C44: =(C10+C11)/C1 -> 0.26581597 | D44: =(E10+E11)/D1 -> 0.40108099 | F44: =(G10+G11)/F1 -> 0.2524372 | H44: =(I10+I11)/H1 -> 0.28050995 | J44: =(K10+K11)/J1 -> 0.28011022 | L44: =(M10+M11)/L1 -> 0.18418328 | N44: =(O10+O11)/N1 -> 22.239592 | P44: =(Q10+Q11)/P1 -> 0.05 | R44: =(S10+S11)/R1 -> 0.22659089 | T44: =(U10+U11)/T1 -> #DIV/0! | V44: =(W10+W11)/V1 -> #DIV/0! | X44: =(Y10+Y11)/X1 -> #DIV/0! | Z44: =(AA10+AA11)/Z1 -> #DIV/0! | AB44: =(AC10+AC11)/AB1 -> 0 | AD44: =(AE10+AE11)/AD1 -> #DIV/0! | AF44: =(AG10+AG11)/AF1 -> #DIV/0! | AH44: =(AI10+AI11)/AH1 -> 0
B45: ПРОЕКТНЫЕ РАСХОДЫ | C45: =(C12+C13+C14)/C1 -> 0.056896557 | D45: =(E12+E13+E14)/D1 -> 0.21087833 | F45: =(G12+G13+G14)/F1 -> 0.039222852 | H45: =(I12+I13+I14)/H1 -> 0.018352188 | J45: =(K12+K13+K14)/J1 -> 0.042770954 | L45: =(M12+M13+M14)/L1 -> 0.085736461 | N45: =(O12+O13+O14)/N1 -> 8.0814249 | P45: =(Q12+Q13+Q14)/P1 -> 0 | R45: =(S12+S13+S14)/R1 -> 0.095659049 | T45: =(U12+U13+U14)/T1 -> #DIV/0! | V45: =(W12+W13+W14)/V1 -> #DIV/0! | X45: =(Y12+Y13+Y14)/X1 -> #DIV/0! | Z45: =(AA12+AA13+AA14)/Z1 -> #DIV/0! | AB45: =(AC12+AC13+AC14)/AB1 -> 0 | AD45: =(AE12+AE13+AE14)/AD1 -> #DIV/0! | AF45: =(AG12+AG13+AG14)/AF1 -> #DIV/0! | AH45: =(AI12+AI13+AI14)/AH1 -> 0
B46: ФОТ | C46: =(C16+C17+C18+C19)/C1 -> 0.23313681 | D46: =(E16+E17+E18+E19)/D1 -> 0.52753008 | F46: =(G16+G17+G18+G19)/F1 -> 0.16373638 | H46: =(I16+I17+I18+I19)/H1 -> 0.1242098 | J46: =(K16+K17+K18+K19)/J1 -> 0.18242016 | L46: =(M16+M17+M18+M19)/L1 -> 0.20981375 | N46: =(O16+O17+O18+O19)/N1 -> 63.673033 | P46: =(Q16+Q17+Q18+Q19)/P1 -> 0.099074713 | R46: =(S16+S17+S18+S19)/R1 -> 0.37230991 | T46: =(U16+U17+U18+U19)/T1 -> #DIV/0! | V46: =(W16+W17+W18+W19)/V1 -> #DIV/0! | X46: =(Y16+Y17+Y18+Y19)/X1 -> #DIV/0! | Z46: =(AA16+AA17+AA18+AA19)/Z1 -> #DIV/0! | AB46: =(AC16+AC17+AC18+AC19)/AB1 -> 0 | AD46: =(AE16+AE17+AE18+AE19)/AD1 -> #DIV/0! | AF46: =(AG16+AG17+AG18+AG19)/AF1 -> #DIV/0! | AH46: =(AI16+AI17+AI18+AI19)/AH1 -> 0
B47: НАЛОГИ | C47: =C22/C1 -> 0.058413562 | D47: =E22/D1 -> 0 | F47: =G22/F1 -> 8.4801755e-06 | H47: =I22/H1 -> 0.00024600258 | J47: =K22/J1 -> 0.077809153 | L47: =M22/L1 -> 0 | N47: =O22/N1 -> 0 | P47: =Q22/P1 -> 0 | R47: =S22/R1 -> 0.0051896198 | T47: =U22/T1 -> #DIV/0! | V47: =W22/V1 -> #DIV/0! | X47: =Y22/X1 -> #DIV/0! | Z47: =AA22/Z1 -> #DIV/0! | AB47: =AC22/AB1 -> 0 | AD47: =AE22/AD1 -> #DIV/0! | AF47: =AG22/AF1 -> #DIV/0! | AH47: =AI22/AH1 -> 0
B48: РАЗРАБОТКА и IT | C48: =(C32+C33)/C1 -> 0.065734344 | D48: =(E32+E33)/D1 -> 0.19884418 | F48: =(G32+G33)/F1 -> 0.04681105 | H48: =(I32+I33)/H1 -> 0.032128352 | J48: =(K32+K33)/J1 -> 0.051980539 | L48: =(M32+M33)/L1 -> 0.057413182 | N48: =(O32+O33)/N1 -> 19.405217 | P48: =(Q32+Q33)/P1 -> 0 | R48: =(S32+S33)/R1 -> 0.10347658 | T48: =(U32+U33)/T1 -> #DIV/0! | V48: =(W32+W33)/V1 -> #DIV/0! | X48: =(Y32+Y33)/X1 -> #DIV/0! | Z48: =(AA32+AA33)/Z1 -> #DIV/0! | AB48: =(AC32+AC33)/AB1 -> 0 | AD48: =(AE32+AE33)/AD1 -> #DIV/0! | AF48: =(AG32+AG33)/AF1 -> #DIV/0! | AH48: =(AI32+AI33)/AH1 -> 0
B49: ОФИС | C49: =C34/C1 -> 0.021935064 | D49: =(E34)/D1 -> 0.015108977 | F49: =(G34)/F1 -> 0.01678158 | H49: =(I34)/H1 -> 0.01127662 | J49: =(K34)/J1 -> 0.013703854 | L49: =(M34)/L1 -> 0.018369053 | N49: =(O34)/N1 -> 5.2610118 | P49: =(Q34)/P1 -> 0.09583606 | R49: =(S34)/R1 -> 0.044522566 | T49: =(U34)/T1 -> #DIV/0! | V49: =(W34)/V1 -> #DIV/0! | X49: =(Y34)/X1 -> #DIV/0! | Z49: =(AA34)/Z1 -> #DIV/0! | AB49: =(AC34)/AB1 -> 0 | AD49: =(AE34)/AD1 -> #DIV/0! | AF49: =(AG34)/AF1 -> #DIV/0! | AH49: =(AI34)/AH1 -> 0
B50: ТРАНЗИТ | C50: =C29/C1 -> 0.026962123 | D50: =(E29-D29)/D1 -> 0.18795037 | F50: =(G29-F29)/F1 -> 0 | H50: =(I29-H29)/H1 -> 0.016476078 | J50: =(K29-J29)/J1 -> 0.024850966 | L50: =(M29-L29)/L1 -> 0 | N50: =(O29-N29)/N1 -> 11.628261 | P50: =(Q29-P29)/P1 -> 0 | R50: =(S29-R29)/R1 -> 0.032756009 | T50: =(U29-T29)/T1 -> #DIV/0! | V50: =(W29-V29)/V1 -> #DIV/0! | X50: =(Y29-X29)/X1 -> #DIV/0! | Z50: =(AA29-Z29)/Z1 -> #DIV/0! | AB50: =(AC29-AB29)/AB1 -> -1 | AD50: =(AE29-AD29)/AD1 -> #DIV/0! | AF50: =(AG29-AF29)/AF1 -> #DIV/0! | AH50: =(AI29-AH29)/AH1 -> -1
B51: прочее | C51: =100%-sum(C43:C50) -> 0.099857884
C53: =(C7-C8-C9-C10-C11-C12-C13-C14)/C7 -> 0.47554555
C55: =7200000/0.35 -> 20571429

Sheet БДДС 2025
A1: РЕАЛИЗАЦИЯ | B1: =SUM(I1+Q1+Y1+AG1) -> 341517384 | C1: =SUM(C7:C41) -> 18833527 | E1: =SUM(E7:E41) -> 28493016 | G1: =SUM(G7:G41) -> 35132673 | I1: =SUM(I7:I41) -> 82459215 | K1: =SUM(K7:K41) -> 35496221 | M1: =SUM(M7:M41) -> 25298279 | O1: =SUM(O7:O41) -> 22239691 | Q1: =SUM(Q7:Q41) -> 83034191 | S1: =SUM(S7:S41) -> 15416326 | U1: =SUM(U7:U41) -> 14990267 | W1: =SUM(W7:W41) -> 23900347 | Y1: =SUM(Y7:Y41) -> 54306940 | AA1: =SUM(AA7:AA41) -> 35139051 | AC1: =SUM(AC7:AC41) -> 41080401 | AE1: =SUM(AE7:AE41) -> 45497586 | AG1: =SUM(AG7:AG41) -> 1.2171704e+08
A2: РАСХОДЫ | B2: =SUM(I2+Q2+Y2+AG2) -> 3.4151007e+08 | C2: =SUM(D7:D41)-D15-D22 -> 15826835 | E2: =SUM(F7:F41)-F15-F22 -> 25813711 | G2: =SUM(H7:H41)-H15-H22 -> 29653238 | I2: =SUM(J7:J41)-J15-J22 -> 89138308 | K2: =SUM(L7:L41)-L15-L22 -> 30822660 | M2: =SUM(N7:N41)-N15-N22 -> 18586131 | O2: =SUM(P7:P41)-P15-P22 -> 17779035 | Q2: =SUM(R7:R41)-R15-R22 -> 76429110 | S2: =SUM(T7:T41)-T15-T22 -> 20073373 | U2: =SUM(V7:V41)-V15-V22 -> 16659955 | W2: =SUM(X7:X41)-X15-X22 -> 21780616 | Y2: =SUM(Z7:Z41)-Z15-Z22 -> 67752404 | AA2: =SUM(AB7:AB41)-AB15-AB22 -> 22728450 | AC2: =SUM(AD7:AD41)-AD15-AD22 -> 20154181 | AE2: =SUM(AF7:AF41)-AF15-AF22 -> 22285382 | AG2: =SUM(AH7:AH41)-AH15-AH22 -> 1.0819025e+08
A3: Дельта | B3: =SUM(I3+Q3+Y3+AG3) -> 7309.1561 | C3: =C1-C2 -> 3006691.3 | E3: =E1-E2 -> 2679304.5 | G3: =G1-G2 -> 5479435 | I3: =I1-I2 -> -6679093.7 | K3: =K1-K2 -> 4673560.6 | M3: =M1-M2 -> 6712147.4 | O3: =O1-O2 -> 4460655.9 | Q3: =Q1-Q2 -> 6605080.5 | S3: =S1-S2 -> -4657047.5 | U3: =U1-U2 -> -1669688.5 | W3: =W1-W2 -> 2119731.4 | Y3: =Y1-Y2 -> -13445465 | AA3: =AA1-AA2 -> 12410601 | AC3: =AC1-AC2 -> 20926220 | AE3: =AE1-AE2 -> 23212205 | AG3: =AG1-AG2 -> 13526787
B5: 2025 год | D5: ЯНВАРЬ 2025 | F5: ФЕВРАЛЬ 2025 | H5: МАРТ 2025 | J5: 1 квартал 2025 | L5: АПРЕЛЬ 2025 | N5: МАЙ 2025 | P5: ИЮНЬ 2025 | R5: 2 квартал 2025 | T5: ИЮЛЬ 2025 | V5: АВГУСТ 2025 | X5: СЕНТЯБРЬ 2025 | Z5: 3 квартал 2025 | AB5: Октябрь 2025 | AD5: НОЯБРЬ 2025 | AF5: ДЕКАБРЬ 2025 | AH5: 4 квартал 2025
C6: поступления | D6: расходы | E6: поступления | F6: расходы | G6: поступления | H6: расходы | I6: поступления | J6: расходы | K6: поступления | L6: расходы | M6: поступления | N6: расходы | O6: поступления | P6: расходы | Q6: поступления | R6: расходы | S6: поступления | T6: расходы | U6: поступления | V6: расходы | W6: поступления | X6: расходы | Y6: поступления | Z6: расходы | AA6: поступления | AB6: расходы | AC6: поступления | AD6: расходы | AE6: поступления | AF6: расходы | AG6: поступления | AH6: расходы
A7: РЕАЛИЗАЦИЯ | B7: =I7+Q7+Y7+AG7 -> 3.3297654e+08 | C7: =SUMIFS('CF BEST'!$C$9:$C1013, 'CF BEST'!$I$9:$I1013, A7,'CF BEST'!$F$9:$F1013, $D$5) -> 18833527 | D7: =SUMIFS('CF BEST'!$D$9:$D1013, 'CF BEST'!$I$9:$I1013, A7,'CF BEST'!$F$9:$F1013, $D$5) -> 0 | E7: =SUMIFS('CF BEST'!$C$9:$C1013, 'CF BEST'!$I$9:$I1013, A7,'CF BEST'!$F$9:$F1013, $F$5) -> 28493016 | F7: =SUMIFS('CF BEST'!$D$9:$D1013, 'CF BEST'!$I$9:$I1013, A7,'CF BEST'!$F$9:$F1013, $F$5) -> 0 | G7: =SUMIFS('CF BEST'!$C$9:$C1013, 'CF BEST'!$I$9:$I1013, A7,'CF BEST'!$F$9:$F1013, $H$5) -> 35132673 | H7: =SUMIFS('CF BEST'!$D$9:$D1013, 'CF BEST'!$I$9:$I1013, A7,'CF BEST'!$F$9:$F1013, $H$5) -> 0 | I7: =SUMIFS('CF BEST'!$C$9:$C1013, 'CF BEST'!$I$9:$I1013, A7,'CF BEST'!$F$9:$F1013, $J$5)+C7+E7+G7 -> 82459215 | J7: =SUMIFS('CF BEST'!$D$9:$D1013, 'CF BEST'!$I$9:$I1013, A7,'CF BEST'!$F$9:$F1013, $J$5)+D7+F7+H7 -> 0 | K7: =SUMIFS('CF BEST'!$C$9:$C1013, 'CF BEST'!$I$9:$I1013, A7,'CF BEST'!$F$9:$F1013, $L$5) -> 35296221 | L7: =SUMIFS('CF BEST'!$D$9:$D1013, 'CF BEST'!$I$9:$I1013, A7,'CF BEST'!$F$9:$F1013, $L$5) -> 0 | M7: =SUMIFS('CF BEST'!$C$9:$C1013, 'CF BEST'!$I$9:$I1013, A7,'CF BEST'!$F$9:$F1013, $N$5) -> 25298279 | N7: =SUMIFS('CF BEST'!$D$9:$D1013, 'CF BEST'!$I$9:$I1013, A7,'CF BEST'!$F$9:$F1013, $N$5) -> 0 | O7: =SUMIFS('CF BEST'!$C$9:$C1013, 'CF BEST'!$I$9:$I1013, A7,'CF BEST'!$F$9:$F1013, $P$5) -> 22239691 | P7: =SUMIFS('CF BEST'!$D$9:$D1013, 'CF BEST'!$I$9:$I1013, A7,'CF BEST'!$F$9:$F1013, $P$5) -> 0 | Q7: =SUMIFS('CF BEST'!$C$9:$C1013, 'CF BEST'!$I$9:$I1013, A7,'CF BEST'!$F$9:$F1013, $R$5)+K7+M7+O7 -> 82834191 | R7: =SUMIFS('CF BEST'!$D$9:$D1013, 'CF BEST'!$I$9:$I1013, A7,'CF BEST'!$F$9:$F1013, $R$5)+L7+N7+P7 -> 0 | S7: =SUMIFS('CF BEST'!$C$9:$C1013, 'CF BEST'!$I$9:$I1013, A7,'CF BEST'!$F$9:$F1013, $T$5) -> 15416326 | T7: =SUMIFS('CF BEST'!$D$9:$D1013, 'CF BEST'!$I$9:$I1013, A7,'CF BEST'!$F$9:$F1013, $T$5) -> 0 | U7: =SUMIFS('CF BEST'!$C$9:$C1013, 'CF BEST'!$I$9:$I1013, A7,'CF BEST'!$F$9:$F1013, $V$5) -> 14990267 | V7: =SUMIFS('CF BEST'!$D$9:$D1013, 'CF BEST'!$I$9:$I1013, A7,'CF BEST'!$F$9:$F1013, $V$5) -> 0 | W7: =SUMIFS('CF BEST'!$C$9:$C1013, 'CF BEST'!$I$9:$I1013, A7,'CF BEST'!$F$9:$F1013, $X$5) -> 23900347 | X7: =SUMIFS('CF BEST'!$D$9:$D1013, 'CF BEST'!$I$9:$I1013, A7,'CF BEST'!$F$9:$F1013, $X$5) -> 0 | Y7: =SUMIFS('CF BEST'!$C$9:$C1013, 'CF BEST'!$I$9:$I1013, A7,'CF BEST'!$F$9:$F1013, $Z$5)+S7+U7+W7 -> 54306940 | Z7: =SUMIFS('CF BEST'!$D$9:$D1013, 'CF BEST'!$I$9:$I1013, A7,'CF BEST'!$F$9:$F1013, $Z$5)+T7+V7+X7 -> 0 | AA7: =SUMIFS('CF BEST'!$C$9:$C1013, 'CF BEST'!$I$9:$I1013, A7,'CF BEST'!$F$9:$F1013, $AB$5) -> 35139039 | AB7: =SUMIFS('CF BEST'!$D$9:$D1013, 'CF BEST'!$I$9:$I1013, A7,'CF BEST'!$F$9:$F1013, $AB$5) -> 0 | AC7: =SUMIFS('CF BEST'!$C$9:$C1013, 'CF BEST'!$I$9:$I1013, A7,'CF BEST'!$F$9:$F1013, $AD$5) -> 36992586 | AD7: =SUMIFS('CF BEST'!$D$9:$D1013, 'CF BEST'!$I$9:$I1013, A7,'CF BEST'!$F$9:$F1013, $AD$5) -> 0 | AE7: =SUMIFS('CF BEST'!$C$9:$C1013, 'CF BEST'!$I$9:$I1013, A7,'CF BEST'!$F$9:$F1013, $AF$5) -> 41244566 | AF7: =SUMIFS('CF BEST'!$D$9:$D1013, 'CF BEST'!$I$9:$I1013, A7,'CF BEST'!$F$9:$F1013, $AF$5) -> 0 | AG7: =SUMIFS('CF BEST'!$C$9:$C1013, 'CF BEST'!$I$9:$I1013, A7,'CF BEST'!$F$9:$F1013, $AH$5)+AA7+AC7+AE7 -> 1.1337619e+08 | AH7: =SUMIFS('CF BEST'!$D$9:$D1013, 'CF BEST'!$I$9:$I1013, A7,'CF BEST'!$F$9:$F1013, $AH$5)+AB7+AD7+AF7 -> 0
A8: СК АГЕНТСКАЯ | B8: =J8+R8+Z8+AH8 -> 59194492 | C8: =SUMIFS('CF BEST'!$C$9:$C1013, 'CF BEST'!$I$9:$I1013, A8,'CF BEST'!$F$9:$F1013, $D$5) -> 0 | D8: =SUMIFS('CF BEST'!$D$9:$D1013, 'CF BEST'!$I$9:$I1013, A8,'CF BEST'!$F$9:$F1013, $D$5) -> 0 | E8: =SUMIFS('CF BEST'!$C$9:$C1013, 'CF BEST'!$I$9:$I1013, A8,'CF BEST'!$F$9:$F1013, $F$5) -> 0 | F8: =SUMIFS('CF BEST'!$D$9:$D1013, 'CF BEST'!$I$9:$I1013, A8,'CF BEST'!$F$9:$F1013, $F$5) -> 0 | G8: =SUMIFS('CF BEST'!$C$9:$C1013, 'CF BEST'!$I$9:$I1013, A8,'CF BEST'!$F$9:$F1013, $H$5) -> 0 | H8: =SUMIFS('CF BEST'!$D$9:$D1013, 'CF BEST'!$I$9:$I1013, A8,'CF BEST'!$F$9:$F1013, $H$5) -> 106000 | I8: =SUMIFS('CF BEST'!$C$9:$C1013, 'CF BEST'!$I$9:$I1013, A8,'CF BEST'!$F$9:$F1013, $J$5)+C8+E8+G8 -> 0 | J8: =SUMIFS('CF BEST'!$D$9:$D1013, 'CF BEST'!$I$9:$I1013, A8,'CF BEST'!$F$9:$F1013, $J$5)+D8+F8+H8 -> 17290125 | K8: =SUMIFS('CF BEST'!$C$9:$C1013, 'CF BEST'!$I$9:$I1013, A8,'CF BEST'!$F$9:$F1013, $L$5) -> 0 | L8: =SUMIFS('CF BEST'!$D$9:$D1013, 'CF BEST'!$I$9:$I1013, A8,'CF BEST'!$F$9:$F1013, $L$5) -> 675100 | M8: =SUMIFS('CF BEST'!$C$9:$C1013, 'CF BEST'!$I$9:$I1013, A8,'CF BEST'!$F$9:$F1013, $N$5) -> 0 | N8: =SUMIFS('CF BEST'!$D$9:$D1013, 'CF BEST'!$I$9:$I1013, A8,'CF BEST'!$F$9:$F1013, $N$5) -> 0 | O8: =SUMIFS('CF BEST'!$C$9:$C1013, 'CF BEST'!$I$9:$I1013, A8,'CF BEST'!$F$9:$F1013, $P$5) -> 0 | P8: =SUMIFS('CF BEST'!$D$9:$D1013, 'CF BEST'!$I$9:$I1013, A8,'CF BEST'!$F$9:$F1013, $P$5) -> 0 | Q8: =SUMIFS('CF BEST'!$C$9:$C1013, 'CF BEST'!$I$9:$I1013, A8,'CF BEST'!$F$9:$F1013, $R$5)+K8+M8+O8 -> 0 | R8: =SUMIFS('CF BEST'!$D$9:$D1013, 'CF BEST'!$I$9:$I1013, A8,'CF BEST'!$F$9:$F1013, $R$5)+L8+N8+P8 -> 9484223.4 | S8: =SUMIFS('CF BEST'!$C$9:$C1013, 'CF BEST'!$I$9:$I1013, A8,'CF BEST'!$F$9:$F1013, $T$5) -> 0 | T8: =SUMIFS('CF BEST'!$D$9:$D1013, 'CF BEST'!$I$9:$I1013, A8,'CF BEST'!$F$9:$F1013, $T$5) -> 0 | U8: =SUMIFS('CF BEST'!$C$9:$C1013, 'CF BEST'!$I$9:$I1013, A8,'CF BEST'!$F$9:$F1013, $V$5) -> 0 | V8: =SUMIFS('CF BEST'!$D$9:$D1013, 'CF BEST'!$I$9:$I1013, A8,'CF BEST'!$F$9:$F1013, $V$5) -> 0 | W8: =SUMIFS('CF BEST'!$C$9:$C1013, 'CF BEST'!$I$9:$I1013, A8,'CF BEST'!$F$9:$F1013, $X$5) -> 0 | X8: =SUMIFS('CF BEST'!$D$9:$D1013, 'CF BEST'!$I$9:$I1013, A8,'CF BEST'!$F$9:$F1013, $X$5) -> 0 | Y8: =SUMIFS('CF BEST'!$C$9:$C1013, 'CF BEST'!$I$9:$I1013, A8,'CF BEST'!$F$9:$F1013, $Z$5)+S8+U8+W8 -> 0 | Z8: =SUMIFS('CF BEST'!$D$9:$D1013, 'CF BEST'!$I$9:$I1013, A8,'CF BEST'!$F$9:$F1013, $Z$5)+T8+V8+X8 -> 7527832.8 | AA8: =SUMIFS('CF BEST'!$C$9:$C1013, 'CF BEST'!$I$9:$I1013, A8,'CF BEST'!$F$9:$F1013, $AB$5) -> 0 | AB8: =SUMIFS('CF BEST'!$D$9:$D1013, 'CF BEST'!$I$9:$I1013, A8,'CF BEST'!$F$9:$F1013, $AB$5) -> 0 | AC8: =SUMIFS('CF BEST'!$C$9:$C1013, 'CF BEST'!$I$9:$I1013, A8,'CF BEST'!$F$9:$F1013, $AD$5) -> 0 | AD8: =SUMIFS('CF BEST'!$D$9:$D1013, 'CF BEST'!$I$9:$I1013, A8,'CF BEST'!$F$9:$F1013, $AD$5) -> 0 | AE8: =SUMIFS('CF BEST'!$C$9:$C1013, 'CF BEST'!$I$9:$I1013, A8,'CF BEST'!$F$9:$F1013, $AF$5) -> 0 | AF8: =SUMIFS('CF BEST'!$D$9:$D1013, 'CF BEST'!$I$9:$I1013, A8,'CF BEST'!$F$9:$F1013, $AF$5) -> 0 | AG8: =SUMIFS('CF BEST'!$C$9:$C1013, 'CF BEST'!$I$9:$I1013, A8,'CF BEST'!$F$9:$F1013, $AH$5)+AA8+AC8+AE8 -> 0 | AH8: =SUMIFS('CF BEST'!$D$9:$D1013, 'CF BEST'!$I$9:$I1013, A8,'CF BEST'!$F$9:$F1013, $AH$5)+AB8+AD8+AF8 -> 24892311
A9: СК ПАРТНЕРСКАЯ | B9: =J9+R9+Z9+AH9 -> 16324500 | C9: =SUMIFS('CF BEST'!$C$9:$C1013, 'CF BEST'!$I$9:$I1013, A9,'CF BEST'!$F$9:$F1013, $D$5) -> 0 | D9: =SUMIFS('CF BEST'!$D$9:$D1013, 'CF BEST'!$I$9:$I1013, A9,'CF BEST'!$F$9:$F1013, $D$5) -> 1547805 | E9: =SUMIFS('CF BEST'!$C$9:$C1013, 'CF BEST'!$I$9:$I1013, A9,'CF BEST'!$F$9:$F1013, $F$5) -> 0 | F9: =SUMIFS('CF BEST'!$D$9:$D1013, 'CF BEST'!$I$9:$I1013, A9,'CF BEST'!$F$9:$F1013, $F$5) -> 1398735 | G9: =SUMIFS('CF BEST'!$C$9:$C1013, 'CF BEST'!$I$9:$I1013, A9,'CF BEST'!$F$9:$F1013, $H$5) -> 0 | H9: =SUMIFS('CF BEST'!$D$9:$D1013, 'CF BEST'!$I$9:$I1013, A9,'CF BEST'!$F$9:$F1013, $H$5) -> 2222709.1 | I9: =SUMIFS('CF BEST'!$C$9:$C1013, 'CF BEST'!$I$9:$I1013, A9,'CF BEST'!$F$9:$F1013, $J$5)+C9+E9+G9 -> 0 | J9: =SUMIFS('CF BEST'!$D$9:$D1013, 'CF BEST'!$I$9:$I1013, A9,'CF BEST'!$F$9:$F1013, $J$5)+D9+F9+H9 -> 5169249.1 | K9: =SUMIFS('CF BEST'!$C$9:$C1013, 'CF BEST'!$I$9:$I1013, A9,'CF BEST'!$F$9:$F1013, $L$5) -> 0 | L9: =SUMIFS('CF BEST'!$D$9:$D1013, 'CF BEST'!$I$9:$I1013, A9,'CF BEST'!$F$9:$F1013, $L$5) -> 1237828 | M9: =SUMIFS('CF BEST'!$C$9:$C1013, 'CF BEST'!$I$9:$I1013, A9,'CF BEST'!$F$9:$F1013, $N$5) -> 0 | N9: =SUMIFS('CF BEST'!$D$9:$D1013, 'CF BEST'!$I$9:$I1013, A9,'CF BEST'!$F$9:$F1013, $N$5) -> 768635.9 | O9: =SUMIFS('CF BEST'!$C$9:$C1013, 'CF BEST'!$I$9:$I1013, A9,'CF BEST'!$F$9:$F1013, $P$5) -> 0 | P9: =SUMIFS('CF BEST'!$D$9:$D1013, 'CF BEST'!$I$9:$I1013, A9,'CF BEST'!$F$9:$F1013, $P$5) -> 1006127.5 | Q9: =SUMIFS('CF BEST'!$C$9:$C1013, 'CF BEST'!$I$9:$I1013, A9,'CF BEST'!$F$9:$F1013, $R$5)+K9+M9+O9 -> 0 | R9: =SUMIFS('CF BEST'!$D$9:$D1013, 'CF BEST'!$I$9:$I1013, A9,'CF BEST'!$F$9:$F1013, $R$5)+L9+N9+P9 -> 3012591.4 | S9: =SUMIFS('CF BEST'!$C$9:$C1013, 'CF BEST'!$I$9:$I1013, A9,'CF BEST'!$F$9:$F1013, $T$5) -> 0 | T9: =SUMIFS('CF BEST'!$D$9:$D1013, 'CF BEST'!$I$9:$I1013, A9,'CF BEST'!$F$9:$F1013, $T$5) -> 1309498.7 | U9: =SUMIFS('CF BEST'!$C$9:$C1013, 'CF BEST'!$I$9:$I1013, A9,'CF BEST'!$F$9:$F1013, $V$5) -> 0 | V9: =SUMIFS('CF BEST'!$D$9:$D1013, 'CF BEST'!$I$9:$I1013, A9,'CF BEST'!$F$9:$F1013, $V$5) -> 765120 | W9: =SUMIFS('CF BEST'!$C$9:$C1013, 'CF BEST'!$I$9:$I1013, A9,'CF BEST'!$F$9:$F1013, $X$5) -> 0 | X9: =SUMIFS('CF BEST'!$D$9:$D1013, 'CF BEST'!$I$9:$I1013, A9,'CF BEST'!$F$9:$F1013, $X$5) -> 1562205.3 | Y9: =SUMIFS('CF BEST'!$C$9:$C1013, 'CF BEST'!$I$9:$I1013, A9,'CF BEST'!$F$9:$F1013, $Z$5)+S9+U9+W9 -> 0 | Z9: =SUMIFS('CF BEST'!$D$9:$D1013, 'CF BEST'!$I$9:$I1013, A9,'CF BEST'!$F$9:$F1013, $Z$5)+T9+V9+X9 -> 3636824 | AA9: =SUMIFS('CF BEST'!$C$9:$C1013, 'CF BEST'!$I$9:$I1013, A9,'CF BEST'!$F$9:$F1013, $AB$5) -> 0 | AB9: =SUMIFS('CF BEST'!$D$9:$D1013, 'CF BEST'!$I$9:$I1013, A9,'CF BEST'!$F$9:$F1013, $AB$5) -> 1589321.9 | AC9: =SUMIFS('CF BEST'!$C$9:$C1013, 'CF BEST'!$I$9:$I1013, A9,'CF BEST'!$F$9:$F1013, $AD$5) -> 0 | AD9: =SUMIFS('CF BEST'!$D$9:$D1013, 'CF BEST'!$I$9:$I1013, A9,'CF BEST'!$F$9:$F1013, $AD$5) -> 923452.5 | AE9: =SUMIFS('CF BEST'!$C$9:$C1013, 'CF BEST'!$I$9:$I1013, A9,'CF BEST'!$F$9:$F1013, $AF$5) -> 0 | AF9: =SUMIFS('CF BEST'!$D$9:$D1013, 'CF BEST'!$I$9:$I1013, A9,'CF BEST'!$F$9:$F1013, $AF$5) -> 1643060.7 | AG9: =SUMIFS('CF BEST'!$C$9:$C1013, 'CF BEST'!$I$9:$I1013, A9,'CF BEST'!$F$9:$F1013, $AH$5)+AA9+AC9+AE9 -> 0 | AH9: =SUMIFS('CF BEST'!$D$9:$D1013, 'CF BEST'!$I$9:$I1013, A9,'CF BEST'!$F$9:$F1013, $AH$5)+AB9+AD9+AF9 -> 4505835.1
A10: АПТЕКА | B10: =J10+R10+Z10+AH10 -> 99128625 | C10: =SUMIFS('CF BEST'!$C$9:$C1013, 'CF BEST'!$I$9:$I1013, A10,'CF BEST'!$F$9:$F1013, $D$5) -> 0 | D10: =SUMIFS('CF BEST'!$D$9:$D1013, 'CF BEST'!$I$9:$I1013, A10,'CF BEST'!$F$9:$F1013, $D$5) -> 5221343 | E10: =SUMIFS('CF BEST'!$C$9:$C1013, 'CF BEST'!$I$9:$I1013, A10,'CF BEST'!$F$9:$F1013, $F$5) -> 0 | F10: =SUMIFS('CF BEST'!$D$9:$D1013, 'CF BEST'!$I$9:$I1013, A10,'CF BEST'!$F$9:$F1013, $F$5) -> 8884397.1 | G10: =SUMIFS('CF BEST'!$C$9:$C1013, 'CF BEST'!$I$9:$I1013, A10,'CF BEST'!$F$9:$F1013, $H$5) -> 0 | H10: =SUMIFS('CF BEST'!$D$9:$D1013, 'CF BEST'!$I$9:$I1013, A10,'CF BEST'!$F$9:$F1013, $H$5) -> 16197463 | I10: =SUMIFS('CF BEST'!$C$9:$C1013, 'CF BEST'!$I$9:$I1013, A10,'CF BEST'!$F$9:$F1013, $J$5)+C10+E10+G10 -> 0 | J10: =SUMIFS('CF BEST'!$D$9:$D1013, 'CF BEST'!$I$9:$I1013, A10,'CF BEST'!$F$9:$F1013, $J$5)+D10+F10+H10 -> 30303203 | K10: =SUMIFS('CF BEST'!$C$9:$C1013, 'CF BEST'!$I$9:$I1013, A10,'CF BEST'!$F$9:$F1013, $L$5) -> 0 | L10: =SUMIFS('CF BEST'!$D$9:$D1013, 'CF BEST'!$I$9:$I1013, A10,'CF BEST'!$F$9:$F1013, $L$5) -> 13233936 | M10: =SUMIFS('CF BEST'!$C$9:$C1013, 'CF BEST'!$I$9:$I1013, A10,'CF BEST'!$F$9:$F1013, $N$5) -> 0 | N10: =SUMIFS('CF BEST'!$D$9:$D1013, 'CF BEST'!$I$9:$I1013, A10,'CF BEST'!$F$9:$F1013, $N$5) -> 7534431.9 | O10: =SUMIFS('CF BEST'!$C$9:$C1013, 'CF BEST'!$I$9:$I1013, A10,'CF BEST'!$F$9:$F1013, $P$5) -> 0 | P10: =SUMIFS('CF BEST'!$D$9:$D1013, 'CF BEST'!$I$9:$I1013, A10,'CF BEST'!$F$9:$F1013, $P$5) -> 7127560 | Q10: =SUMIFS('CF BEST'!$C$9:$C1013, 'CF BEST'!$I$9:$I1013, A10,'CF BEST'!$F$9:$F1013, $R$5)+K10+M10+O10 -> 0 | R10: =SUMIFS('CF BEST'!$D$9:$D1013, 'CF BEST'!$I$9:$I1013, A10,'CF BEST'!$F$9:$F1013, $R$5)+L10+N10+P10 -> 27895928 | S10: =SUMIFS('CF BEST'!$C$9:$C1013, 'CF BEST'!$I$9:$I1013, A10,'CF BEST'!$F$9:$F1013, $T$5) -> 0 | T10: =SUMIFS('CF BEST'!$D$9:$D1013, 'CF BEST'!$I$9:$I1013, A10,'CF BEST'!$F$9:$F1013, $T$5) -> 4959589.3 | U10: =SUMIFS('CF BEST'!$C$9:$C1013, 'CF BEST'!$I$9:$I1013, A10,'CF BEST'!$F$9:$F1013, $V$5) -> 0 | V10: =SUMIFS('CF BEST'!$D$9:$D1013, 'CF BEST'!$I$9:$I1013, A10,'CF BEST'!$F$9:$F1013, $V$5) -> 4012790.9 | W10: =SUMIFS('CF BEST'!$C$9:$C1013, 'CF BEST'!$I$9:$I1013, A10,'CF BEST'!$F$9:$F1013, $X$5) -> 0 | X10: =SUMIFS('CF BEST'!$D$9:$D1013, 'CF BEST'!$I$9:$I1013, A10,'CF BEST'!$F$9:$F1013, $X$5) -> 6529515.4 | Y10: =SUMIFS('CF BEST'!$C$9:$C1013, 'CF BEST'!$I$9:$I1013, A10,'CF BEST'!$F$9:$F1013, $Z$5)+S10+U10+W10 -> 0 | Z10: =SUMIFS('CF BEST'!$D$9:$D1013, 'CF BEST'!$I$9:$I1013, A10,'CF BEST'!$F$9:$F1013, $Z$5)+T10+V10+X10 -> 15501896 | AA10: =SUMIFS('CF BEST'!$C$9:$C1013, 'CF BEST'!$I$9:$I1013, A10,'CF BEST'!$F$9:$F1013, $AB$5) -> 0 | AB10: =SUMIFS('CF BEST'!$D$9:$D1013, 'CF BEST'!$I$9:$I1013, A10,'CF BEST'!$F$9:$F1013, $AB$5) -> 8202672.9 | AC10: =SUMIFS('CF BEST'!$C$9:$C1013, 'CF BEST'!$I$9:$I1013, A10,'CF BEST'!$F$9:$F1013, $AD$5) -> 0 | AD10: =SUMIFS('CF BEST'!$D$9:$D1013, 'CF BEST'!$I$9:$I1013, A10,'CF BEST'!$F$9:$F1013, $AD$5) -> 9404755.9 | AE10: =SUMIFS('CF BEST'!$C$9:$C1013, 'CF BEST'!$I$9:$I1013, A10,'CF BEST'!$F$9:$F1013, $AF$5) -> 0 | AF10: =SUMIFS('CF BEST'!$D$9:$D1013, 'CF BEST'!$I$9:$I1013, A10,'CF BEST'!$F$9:$F1013, $AF$5) -> 7820169.4 | AG10: =SUMIFS('CF BEST'!$C$9:$C1013, 'CF BEST'!$I$9:$I1013, A10,'CF BEST'!$F$9:$F1013, $AH$5)+AA10+AC10+AE10 -> 0 | AH10: =SUMIFS('CF BEST'!$D$9:$D1013, 'CF BEST'!$I$9:$I1013, A10,'CF BEST'!$F$9:$F1013, $AH$5)+AB10+AD10+AF10 -> 25427598
A11: ПАБЛИШЕР | B11: =J11+R11+Z11+AH11 -> 9263915.2 | C11: =SUMIFS('CF BEST'!$C$9:$C1013, 'CF BEST'!$I$9:$I1013, A11,'CF BEST'!$F$9:$F1013, $D$5) -> 0 | D11: =SUMIFS('CF BEST'!$D$9:$D1013, 'CF BEST'!$I$9:$I1013, A11,'CF BEST'!$F$9:$F1013, $D$5) -> 0 | E11: =SUMIFS('CF BEST'!$C$9:$C1013, 'CF BEST'!$I$9:$I1013, A11,'CF BEST'!$F$9:$F1013, $F$5) -> 0 | F11: =SUMIFS('CF BEST'!$D$9:$D1013, 'CF BEST'!$I$9:$I1013, A11,'CF BEST'!$F$9:$F1013, $F$5) -> 0 | G11: =SUMIFS('CF BEST'!$C$9:$C1013, 'CF BEST'!$I$9:$I1013, A11,'CF BEST'!$F$9:$F1013, $H$5) -> 0 | H11: =SUMIFS('CF BEST'!$D$9:$D1013, 'CF BEST'!$I$9:$I1013, A11,'CF BEST'!$F$9:$F1013, $H$5) -> 0 | I11: =SUMIFS('CF BEST'!$C$9:$C1013, 'CF BEST'!$I$9:$I1013, A11,'CF BEST'!$F$9:$F1013, $J$5)+C11+E11+G11 -> 0 | J11: =SUMIFS('CF BEST'!$D$9:$D1013, 'CF BEST'!$I$9:$I1013, A11,'CF BEST'!$F$9:$F1013, $J$5)+D11+F11+H11 -> 0 | K11: =SUMIFS('CF BEST'!$C$9:$C1013, 'CF BEST'!$I$9:$I1013, A11,'CF BEST'!$F$9:$F1013, $L$5) -> 0 | L11: =SUMIFS('CF BEST'!$D$9:$D1013, 'CF BEST'!$I$9:$I1013, A11,'CF BEST'!$F$9:$F1013, $L$5) -> 0 | M11: =SUMIFS('CF BEST'!$C$9:$C1013, 'CF BEST'!$I$9:$I1013, A11,'CF BEST'!$F$9:$F1013, $N$5) -> 0 | N11: =SUMIFS('CF BEST'!$D$9:$D1013, 'CF BEST'!$I$9:$I1013, A11,'CF BEST'!$F$9:$F1013, $N$5) -> 146432.5 | O11: =SUMIFS('CF BEST'!$C$9:$C1013, 'CF BEST'!$I$9:$I1013, A11,'CF BEST'!$F$9:$F1013, $P$5) -> 0 | P11: =SUMIFS('CF BEST'!$D$9:$D1013, 'CF BEST'!$I$9:$I1013, A11,'CF BEST'!$F$9:$F1013, $P$5) -> 156882.1 | Q11: =SUMIFS('CF BEST'!$C$9:$C1013, 'CF BEST'!$I$9:$I1013, A11,'CF BEST'!$F$9:$F1013, $R$5)+K11+M11+O11 -> 0 | R11: =SUMIFS('CF BEST'!$D$9:$D1013, 'CF BEST'!$I$9:$I1013, A11,'CF BEST'!$F$9:$F1013, $R$5)+L11+N11+P11 -> 303314.6 | S11: =SUMIFS('CF BEST'!$C$9:$C1013, 'CF BEST'!$I$9:$I1013, A11,'CF BEST'!$F$9:$F1013, $T$5) -> 0 | T11: =SUMIFS('CF BEST'!$D$9:$D1013, 'CF BEST'!$I$9:$I1013, A11,'CF BEST'!$F$9:$F1013, $T$5) -> 445832.7 | U11: =SUMIFS('CF BEST'!$C$9:$C1013, 'CF BEST'!$I$9:$I1013, A11,'CF BEST'!$F$9:$F1013, $V$5) -> 0 | V11: =SUMIFS('CF BEST'!$D$9:$D1013, 'CF BEST'!$I$9:$I1013, A11,'CF BEST'!$F$9:$F1013, $V$5) -> 360960 | W11: =SUMIFS('CF BEST'!$C$9:$C1013, 'CF BEST'!$I$9:$I1013, A11,'CF BEST'!$F$9:$F1013, $X$5) -> 0 | X11: =SUMIFS('CF BEST'!$D$9:$D1013, 'CF BEST'!$I$9:$I1013, A11,'CF BEST'!$F$9:$F1013, $X$5) -> 693624.69 | Y11: =SUMIFS('CF BEST'!$C$9:$C1013, 'CF BEST'!$I$9:$I1013, A11,'CF BEST'!$F$9:$F1013, $Z$5)+S11+U11+W11 -> 0 | Z11: =SUMIFS('CF BEST'!$D$9:$D1013, 'CF BEST'!$I$9:$I1013, A11,'CF BEST'!$F$9:$F1013, $Z$5)+T11+V11+X11 -> 1500417.4 | AA11: =SUMIFS('CF BEST'!$C$9:$C1013, 'CF BEST'!$I$9:$I1013, A11,'CF BEST'!$F$9:$F1013, $AB$5) -> 0 | AB11: =SUMIFS('CF BEST'!$D$9:$D1013, 'CF BEST'!$I$9:$I1013, A11,'CF BEST'!$F$9:$F1013, $AB$5) -> 1360789.3 | AC11: =SUMIFS('CF BEST'!$C$9:$C1013, 'CF BEST'!$I$9:$I1013, A11,'CF BEST'!$F$9:$F1013, $AD$5) -> 0 | AD11: =SUMIFS('CF BEST'!$D$9:$D1013, 'CF BEST'!$I$9:$I1013, A11,'CF BEST'!$F$9:$F1013, $AD$5) -> 1599161.7 | AE11: =SUMIFS('CF BEST'!$C$9:$C1013, 'CF BEST'!$I$9:$I1013, A11,'CF BEST'!$F$9:$F1013, $AF$5) -> 0 | AF11: =SUMIFS('CF BEST'!$D$9:$D1013, 'CF BEST'!$I$9:$I1013, A11,'CF BEST'!$F$9:$F1013, $AF$5) -> 4500232.2 | AG11: =SUMIFS('CF BEST'!$C$9:$C1013, 'CF BEST'!$I$9:$I1013, A11,'CF BEST'!$F$9:$F1013, $AH$5)+AA11+AC11+AE11 -> 0 | AH11: =SUMIFS('CF BEST'!$D$9:$D1013, 'CF BEST'!$I$9:$I1013, A11,'CF BEST'!$F$9:$F1013, $AH$5)+AB11+AD11+AF11 -> 7460183.2
A12: БАННЕРЫ | B12: =J12+R12+Z12+AH12 -> 1749200 | C12: =SUMIFS('CF BEST'!$C$9:$C1013, 'CF BEST'!$I$9:$I1013, A12,'CF BEST'!$F$9:$F1013, $D$5) -> 0 | D12: =SUMIFS('CF BEST'!$D$9:$D1013, 'CF BEST'!$I$9:$I1013, A12,'CF BEST'!$F$9:$F1013, $D$5) -> 94000 | E12: =SUMIFS('CF BEST'!$C$9:$C1013, 'CF BEST'!$I$9:$I1013, A12,'CF BEST'!$F$9:$F1013, $F$5) -> 0 | F12: =SUMIFS('CF BEST'!$D$9:$D1013, 'CF BEST'!$I$9:$I1013, A12,'CF BEST'!$F$9:$F1013, $F$5) -> 136000 | G12: =SUMIFS('CF BEST'!$C$9:$C1013, 'CF BEST'!$I$9:$I1013, A12,'CF BEST'!$F$9:$F1013, $H$5) -> 0 | H12: =SUMIFS('CF BEST'!$D$9:$D1013, 'CF BEST'!$I$9:$I1013, A12,'CF BEST'!$F$9:$F1013, $H$5) -> 185400 | I12: =SUMIFS('CF BEST'!$C$9:$C1013, 'CF BEST'!$I$9:$I1013, A12,'CF BEST'!$F$9:$F1013, $J$5)+C12+E12+G12 -> 0 | J12: =SUMIFS('CF BEST'!$D$9:$D1013, 'CF BEST'!$I$9:$I1013, A12,'CF BEST'!$F$9:$F1013, $J$5)+D12+F12+H12 -> 415400 | K12: =SUMIFS('CF BEST'!$C$9:$C1013, 'CF BEST'!$I$9:$I1013, A12,'CF BEST'!$F$9:$F1013, $L$5) -> 0 | L12: =SUMIFS('CF BEST'!$D$9:$D1013, 'CF BEST'!$I$9:$I1013, A12,'CF BEST'!$F$9:$F1013, $L$5) -> 177300 | M12: =SUMIFS('CF BEST'!$C$9:$C1013, 'CF BEST'!$I$9:$I1013, A12,'CF BEST'!$F$9:$F1013, $N$5) -> 0 | N12: =SUMIFS('CF BEST'!$D$9:$D1013, 'CF BEST'!$I$9:$I1013, A12,'CF BEST'!$F$9:$F1013, $N$5) -> 134000 | O12: =SUMIFS('CF BEST'!$C$9:$C1013, 'CF BEST'!$I$9:$I1013, A12,'CF BEST'!$F$9:$F1013, $P$5) -> 0 | P12: =SUMIFS('CF BEST'!$D$9:$D1013, 'CF BEST'!$I$9:$I1013, A12,'CF BEST'!$F$9:$F1013, $P$5) -> 114000 | Q12: =SUMIFS('CF BEST'!$C$9:$C1013, 'CF BEST'!$I$9:$I1013, A12,'CF BEST'!$F$9:$F1013, $R$5)+K12+M12+O12 -> 0 | R12: =SUMIFS('CF BEST'!$D$9:$D1013, 'CF BEST'!$I$9:$I1013, A12,'CF BEST'!$F$9:$F1013, $R$5)+L12+N12+P12 -> 425300 | S12: =SUMIFS('CF BEST'!$C$9:$C1013, 'CF BEST'!$I$9:$I1013, A12,'CF BEST'!$F$9:$F1013, $T$5) -> 0 | T12: =SUMIFS('CF BEST'!$D$9:$D1013, 'CF BEST'!$I$9:$I1013, A12,'CF BEST'!$F$9:$F1013, $T$5) -> 30900 | U12: =SUMIFS('CF BEST'!$C$9:$C1013, 'CF BEST'!$I$9:$I1013, A12,'CF BEST'!$F$9:$F1013, $V$5) -> 0 | V12: =SUMIFS('CF BEST'!$D$9:$D1013, 'CF BEST'!$I$9:$I1013, A12,'CF BEST'!$F$9:$F1013, $V$5) -> 88000 | W12: =SUMIFS('CF BEST'!$C$9:$C1013, 'CF BEST'!$I$9:$I1013, A12,'CF BEST'!$F$9:$F1013, $X$5) -> 0 | X12: =SUMIFS('CF BEST'!$D$9:$D1013, 'CF BEST'!$I$9:$I1013, A12,'CF BEST'!$F$9:$F1013, $X$5) -> 140000 | Y12: =SUMIFS('CF BEST'!$C$9:$C1013, 'CF BEST'!$I$9:$I1013, A12,'CF BEST'!$F$9:$F1013, $Z$5)+S12+U12+W12 -> 0 | Z12: =SUMIFS('CF BEST'!$D$9:$D1013, 'CF BEST'!$I$9:$I1013, A12,'CF BEST'!$F$9:$F1013, $Z$5)+T12+V12+X12 -> 258900 | AA12: =SUMIFS('CF BEST'!$C$9:$C1013, 'CF BEST'!$I$9:$I1013, A12,'CF BEST'!$F$9:$F1013, $AB$5) -> 0 | AB12: =SUMIFS('CF BEST'!$D$9:$D1013, 'CF BEST'!$I$9:$I1013, A12,'CF BEST'!$F$9:$F1013, $AB$5) -> 243450 | AC12: =SUMIFS('CF BEST'!$C$9:$C1013, 'CF BEST'!$I$9:$I1013, A12,'CF BEST'!$F$9:$F1013, $AD$5) -> 0 | AD12: =SUMIFS('CF BEST'!$D$9:$D1013, 'CF BEST'!$I$9:$I1013, A12,'CF BEST'!$F$9:$F1013, $AD$5) -> 157950 | AE12: =SUMIFS('CF BEST'!$C$9:$C1013, 'CF BEST'!$I$9:$I1013, A12,'CF BEST'!$F$9:$F1013, $AF$5) -> 0 | AF12: =SUMIFS('CF BEST'!$D$9:$D1013, 'CF BEST'!$I$9:$I1013, A12,'CF BEST'!$F$9:$F1013, $AF$5) -> 248200 | AG12: =SUMIFS('CF BEST'!$C$9:$C1013, 'CF BEST'!$I$9:$I1013, A12,'CF BEST'!$F$9:$F1013, $AH$5)+AA12+AC12+AE12 -> 0 | AH12: =SUMIFS('CF BEST'!$D$9:$D1013, 'CF BEST'!$I$9:$I1013, A12,'CF BEST'!$F$9:$F1013, $AH$5)+AB12+AD12+AF12 -> 649600
A13: ОРД | B13: =J13+R13+Z13+AH13 -> 2834562.9 | C13: =SUMIFS('CF BEST'!$C$9:$C1013, 'CF BEST'!$I$9:$I1013, A13,'CF BEST'!$F$9:$F1013, $D$5) -> 0 | D13: =SUMIFS('CF BEST'!$D$9:$D1013, 'CF BEST'!$I$9:$I1013, A13,'CF BEST'!$F$9:$F1013, $D$5) -> 1200 | E13: =SUMIFS('CF BEST'!$C$9:$C1013, 'CF BEST'!$I$9:$I1013, A13,'CF BEST'!$F$9:$F1013, $F$5) -> 0 | F13: =SUMIFS('CF BEST'!$D$9:$D1013, 'CF BEST'!$I$9:$I1013, A13,'CF BEST'!$F$9:$F1013, $F$5) -> 521679.54 | G13: =SUMIFS('CF BEST'!$C$9:$C1013, 'CF BEST'!$I$9:$I1013, A13,'CF BEST'!$F$9:$F1013, $H$5) -> 0 | H13: =SUMIFS('CF BEST'!$D$9:$D1013, 'CF BEST'!$I$9:$I1013, A13,'CF BEST'!$F$9:$F1013, $H$5) -> 301109.92 | I13: =SUMIFS('CF BEST'!$C$9:$C1013, 'CF BEST'!$I$9:$I1013, A13,'CF BEST'!$F$9:$F1013, $J$5)+C13+E13+G13 -> 0 | J13: =SUMIFS('CF BEST'!$D$9:$D1013, 'CF BEST'!$I$9:$I1013, A13,'CF BEST'!$F$9:$F1013, $J$5)+D13+F13+H13 -> 823989.46 | K13: =SUMIFS('CF BEST'!$C$9:$C1013, 'CF BEST'!$I$9:$I1013, A13,'CF BEST'!$F$9:$F1013, $L$5) -> 0 | L13: =SUMIFS('CF BEST'!$D$9:$D1013, 'CF BEST'!$I$9:$I1013, A13,'CF BEST'!$F$9:$F1013, $L$5) -> 314435.84 | M13: =SUMIFS('CF BEST'!$C$9:$C1013, 'CF BEST'!$I$9:$I1013, A13,'CF BEST'!$F$9:$F1013, $N$5) -> 0 | N13: =SUMIFS('CF BEST'!$D$9:$D1013, 'CF BEST'!$I$9:$I1013, A13,'CF BEST'!$F$9:$F1013, $N$5) -> 319713.64 | O13: =SUMIFS('CF BEST'!$C$9:$C1013, 'CF BEST'!$I$9:$I1013, A13,'CF BEST'!$F$9:$F1013, $P$5) -> 0 | P13: =SUMIFS('CF BEST'!$D$9:$D1013, 'CF BEST'!$I$9:$I1013, A13,'CF BEST'!$F$9:$F1013, $P$5) -> 237913.9 | Q13: =SUMIFS('CF BEST'!$C$9:$C1013, 'CF BEST'!$I$9:$I1013, A13,'CF BEST'!$F$9:$F1013, $R$5)+K13+M13+O13 -> 0 | R13: =SUMIFS('CF BEST'!$D$9:$D1013, 'CF BEST'!$I$9:$I1013, A13,'CF BEST'!$F$9:$F1013, $R$5)+L13+N13+P13 -> 872063.38 | S13: =SUMIFS('CF BEST'!$C$9:$C1013, 'CF BEST'!$I$9:$I1013, A13,'CF BEST'!$F$9:$F1013, $T$5) -> 0 | T13: =SUMIFS('CF BEST'!$D$9:$D1013, 'CF BEST'!$I$9:$I1013, A13,'CF BEST'!$F$9:$F1013, $T$5) -> 244469.58 | U13: =SUMIFS('CF BEST'!$C$9:$C1013, 'CF BEST'!$I$9:$I1013, A13,'CF BEST'!$F$9:$F1013, $V$5) -> 0 | V13: =SUMIFS('CF BEST'!$D$9:$D1013, 'CF BEST'!$I$9:$I1013, A13,'CF BEST'!$F$9:$F1013, $V$5) -> 160885.26 | W13: =SUMIFS('CF BEST'!$C$9:$C1013, 'CF BEST'!$I$9:$I1013, A13,'CF BEST'!$F$9:$F1013, $X$5) -> 0 | X13: =SUMIFS('CF BEST'!$D$9:$D1013, 'CF BEST'!$I$9:$I1013, A13,'CF BEST'!$F$9:$F1013, $X$5) -> 1200 | Y13: =SUMIFS('CF BEST'!$C$9:$C1013, 'CF BEST'!$I$9:$I1013, A13,'CF BEST'!$F$9:$F1013, $Z$5)+S13+U13+W13 -> 0 | Z13: =SUMIFS('CF BEST'!$D$9:$D1013, 'CF BEST'!$I$9:$I1013, A13,'CF BEST'!$F$9:$F1013, $Z$5)+T13+V13+X13 -> 406554.84 | AA13: =SUMIFS('CF BEST'!$C$9:$C1013, 'CF BEST'!$I$9:$I1013, A13,'CF BEST'!$F$9:$F1013, $AB$5) -> 0 | AB13: =SUMIFS('CF BEST'!$D$9:$D1013, 'CF BEST'!$I$9:$I1013, A13,'CF BEST'!$F$9:$F1013, $AB$5) -> 366922.42 | AC13: =SUMIFS('CF BEST'!$C$9:$C1013, 'CF BEST'!$I$9:$I1013, A13,'CF BEST'!$F$9:$F1013, $AD$5) -> 0 | AD13: =SUMIFS('CF BEST'!$D$9:$D1013, 'CF BEST'!$I$9:$I1013, A13,'CF BEST'!$F$9:$F1013, $AD$5) -> 365032.78 | AE13: =SUMIFS('CF BEST'!$C$9:$C1013, 'CF BEST'!$I$9:$I1013, A13,'CF BEST'!$F$9:$F1013, $AF$5) -> 0 | AF13: =SUMIFS('CF BEST'!$D$9:$D1013, 'CF BEST'!$I$9:$I1013, A13,'CF BEST'!$F$9:$F1013, $AF$5) -> 0 | AG13: =SUMIFS('CF BEST'!$C$9:$C1013, 'CF BEST'!$I$9:$I1013, A13,'CF BEST'!$F$9:$F1013, $AH$5)+AA13+AC13+AE13 -> 0 | AH13: =SUMIFS('CF BEST'!$D$9:$D1013, 'CF BEST'!$I$9:$I1013, A13,'CF BEST'!$F$9:$F1013, $AH$5)+AB13+AD13+AF13 -> 731955.2
A14: ПОДРЯДЧИКИ | B14: =J14+R14+Z14+AH14 -> 20174774 | C14: =SUMIFS('CF BEST'!$C$9:$C1013, 'CF BEST'!$I$9:$I1013, A14,'CF BEST'!$F$9:$F1013, $D$5) -> 0 | D14: =SUMIFS('CF BEST'!$D$9:$D1013, 'CF BEST'!$I$9:$I1013, A14,'CF BEST'!$F$9:$F1013, $D$5) -> 837689.27 | E14: =SUMIFS('CF BEST'!$C$9:$C1013, 'CF BEST'!$I$9:$I1013, A14,'CF BEST'!$F$9:$F1013, $F$5) -> 0 | F14: =SUMIFS('CF BEST'!$D$9:$D1013, 'CF BEST'!$I$9:$I1013, A14,'CF BEST'!$F$9:$F1013, $F$5) -> 1385684.1 | G14: =SUMIFS('CF BEST'!$C$9:$C1013, 'CF BEST'!$I$9:$I1013, A14,'CF BEST'!$F$9:$F1013, $H$5) -> 0 | H14: =SUMIFS('CF BEST'!$D$9:$D1013, 'CF BEST'!$I$9:$I1013, A14,'CF BEST'!$F$9:$F1013, $H$5) -> 2924822.3 | I14: =SUMIFS('CF BEST'!$C$9:$C1013, 'CF BEST'!$I$9:$I1013, A14,'CF BEST'!$F$9:$F1013, $J$5)+C14+E14+G14 -> 0 | J14: =SUMIFS('CF BEST'!$D$9:$D1013, 'CF BEST'!$I$9:$I1013, A14,'CF BEST'!$F$9:$F1013, $J$5)+D14+F14+H14 -> 5148195.7 | K14: =SUMIFS('CF BEST'!$C$9:$C1013, 'CF BEST'!$I$9:$I1013, A14,'CF BEST'!$F$9:$F1013, $L$5) -> 0 | L14: =SUMIFS('CF BEST'!$D$9:$D1013, 'CF BEST'!$I$9:$I1013, A14,'CF BEST'!$F$9:$F1013, $L$5) -> 3865126.5 | M14: =SUMIFS('CF BEST'!$C$9:$C1013, 'CF BEST'!$I$9:$I1013, A14,'CF BEST'!$F$9:$F1013, $N$5) -> 0 | N14: =SUMIFS('CF BEST'!$D$9:$D1013, 'CF BEST'!$I$9:$I1013, A14,'CF BEST'!$F$9:$F1013, $N$5) -> 982375.84 | O14: =SUMIFS('CF BEST'!$C$9:$C1013, 'CF BEST'!$I$9:$I1013, A14,'CF BEST'!$F$9:$F1013, $P$5) -> 0 | P14: =SUMIFS('CF BEST'!$D$9:$D1013, 'CF BEST'!$I$9:$I1013, A14,'CF BEST'!$F$9:$F1013, $P$5) -> 984092.97 | Q14: =SUMIFS('CF BEST'!$C$9:$C1013, 'CF BEST'!$I$9:$I1013, A14,'CF BEST'!$F$9:$F1013, $R$5)+K14+M14+O14 -> 0 | R14: =SUMIFS('CF BEST'!$D$9:$D1013, 'CF BEST'!$I$9:$I1013, A14,'CF BEST'!$F$9:$F1013, $R$5)+L14+N14+P14 -> 5831595.3 | S14: =SUMIFS('CF BEST'!$C$9:$C1013, 'CF BEST'!$I$9:$I1013, A14,'CF BEST'!$F$9:$F1013, $T$5) -> 0 | T14: =SUMIFS('CF BEST'!$D$9:$D1013, 'CF BEST'!$I$9:$I1013, A14,'CF BEST'!$F$9:$F1013, $T$5) -> 878889.58 | U14: =SUMIFS('CF BEST'!$C$9:$C1013, 'CF BEST'!$I$9:$I1013, A14,'CF BEST'!$F$9:$F1013, $V$5) -> 0 | V14: =SUMIFS('CF BEST'!$D$9:$D1013, 'CF BEST'!$I$9:$I1013, A14,'CF BEST'!$F$9:$F1013, $V$5) -> 1717983 | W14: =SUMIFS('CF BEST'!$C$9:$C1013, 'CF BEST'!$I$9:$I1013, A14,'CF BEST'!$F$9:$F1013, $X$5) -> 0 | X14: =SUMIFS('CF BEST'!$D$9:$D1013, 'CF BEST'!$I$9:$I1013, A14,'CF BEST'!$F$9:$F1013, $X$5) -> 1438772.8 | Y14: =SUMIFS('CF BEST'!$C$9:$C1013, 'CF BEST'!$I$9:$I1013, A14,'CF BEST'!$F$9:$F1013, $Z$5)+S14+U14+W14 -> 0 | Z14: =SUMIFS('CF BEST'!$D$9:$D1013, 'CF BEST'!$I$9:$I1013, A14,'CF BEST'!$F$9:$F1013, $Z$5)+T14+V14+X14 -> 4035645.4 | AA14: =SUMIFS('CF BEST'!$C$9:$C1013, 'CF BEST'!$I$9:$I1013, A14,'CF BEST'!$F$9:$F1013, $AB$5) -> 0 | AB14: =SUMIFS('CF BEST'!$D$9:$D1013, 'CF BEST'!$I$9:$I1013, A14,'CF BEST'!$F$9:$F1013, $AB$5) -> 3504685.2 | AC14: =SUMIFS('CF BEST'!$C$9:$C1013, 'CF BEST'!$I$9:$I1013, A14,'CF BEST'!$F$9:$F1013, $AD$5) -> 0 | AD14: =SUMIFS('CF BEST'!$D$9:$D1013, 'CF BEST'!$I$9:$I1013, A14,'CF BEST'!$F$9:$F1013, $AD$5) -> 1020681.4 | AE14: =SUMIFS('CF BEST'!$C$9:$C1013, 'CF BEST'!$I$9:$I1013, A14,'CF BEST'!$F$9:$F1013, $AF$5) -> 0 | AF14: =SUMIFS('CF BEST'!$D$9:$D1013, 'CF BEST'!$I$9:$I1013, A14,'CF BEST'!$F$9:$F1013, $AF$5) -> 633971.16 | AG14: =SUMIFS('CF BEST'!$C$9:$C1013, 'CF BEST'!$I$9:$I1013, A14,'CF BEST'!$F$9:$F1013, $AH$5)+AA14+AC14+AE14 -> 0 | AH14: =SUMIFS('CF BEST'!$D$9:$D1013, 'CF BEST'!$I$9:$I1013, A14,'CF BEST'!$F$9:$F1013, $AH$5)+AB14+AD14+AF14 -> 5159337.8
A15: СОТРУДНИКИ | C15: =SUM(C16:C21) -> 0 | D15: =SUM(D16:D21) -> 2259676.4 | E15: =SUM(E16:E21) -> 0 | F15: =SUM(F16:F21) -> 2981657.1 | G15: =SUM(G16:G21) -> 0 | H15: =SUM(H16:H21) -> 2632583.2 | I15: =SUM(I16:I21) -> 0 | J15: =SUM(J16:J21) -> 8534316.8 | ... AH15: =SUM(AH16:AH21) -> 14853001
A16: АВАНС | B16: =J16+R16+Z16+AH16 -> 9159875.6 | C16: =SUMIFS('CF BEST'!$C$9:$C1013, 'CF BEST'!$I$9:$I1013, A16,'CF BEST'!$F$9:$F1013, $D$5) -> 0 | D16: =SUMIFS('CF BEST'!$D$9:$D1013, 'CF BEST'!$I$9:$I1013, A16,'CF BEST'!$F$9:$F1013, $D$5) -> 396349 | E16: =SUMIFS('CF BEST'!$C$9:$C1013, 'CF BEST'!$I$9:$I1013, A16,'CF BEST'!$F$9:$F1013, $F$5) -> 0 | F16: =SUMIFS('CF BEST'!$D$9:$D1013, 'CF BEST'!$I$9:$I1013, A16,'CF BEST'!$F$9:$F1013, $F$5) -> 543344 | G16: =SUMIFS('CF BEST'!$C$9:$C1013, 'CF BEST'!$I$9:$I1013, A16,'CF BEST'!$F$9:$F1013, $H$5) -> 0 | H16: =SUMIFS('CF BEST'!$D$9:$D1013, 'CF BEST'!$I$9:$I1013, A16,'CF BEST'!$F$9:$F1013, $H$5) -> 370587.43 | I16: =SUMIFS('CF BEST'!$C$9:$C1013, 'CF BEST'!$I$9:$I1013, A16,'CF BEST'!$F$9:$F1013, $J$5)+C16+E16+G16 -> 0 | J16: =SUMIFS('CF BEST'!$D$9:$D1013, 'CF BEST'!$I$9:$I1013, A16,'CF BEST'!$F$9:$F1013, $J$5)+D16+F16+H16 -> 1310280.4 | K16: =SUMIFS('CF BEST'!$C$9:$C1013, 'CF BEST'!$I$9:$I1013, A16,'CF BEST'!$F$9:$F1013, $L$5) -> 0 | L16: =SUMIFS('CF BEST'!$D$9:$D1013, 'CF BEST'!$I$9:$I1013, A16,'CF BEST'!$F$9:$F1013, $L$5) -> 422597.47 | M16: =SUMIFS('CF BEST'!$C$9:$C1013, 'CF BEST'!$I$9:$I1013, A16,'CF BEST'!$F$9:$F1013, $N$5) -> 0 | N16: =SUMIFS('CF BEST'!$D$9:$D1013, 'CF BEST'!$I$9:$I1013, A16,'CF BEST'!$F$9:$F1013, $N$5) -> 432867.17 | O16: =SUMIFS('CF BEST'!$C$9:$C1013, 'CF BEST'!$I$9:$I1013, A16,'CF BEST'!$F$9:$F1013, $P$5) -> 0 | P16: =SUMIFS('CF BEST'!$D$9:$D1013, 'CF BEST'!$I$9:$I1013, A16,'CF BEST'!$F$9:$F1013, $P$5) -> 638653 | Q16: =SUMIFS('CF BEST'!$C$9:$C1013, 'CF BEST'!$I$9:$I1013, A16,'CF BEST'!$F$9:$F1013, $R$5)+K16+M16+O16 -> 0 | R16: =SUMIFS('CF BEST'!$D$9:$D1013, 'CF BEST'!$I$9:$I1013, A16,'CF BEST'!$F$9:$F1013, $R$5)+L16+N16+P16 -> 1494117.6 | S16: =SUMIFS('CF BEST'!$C$9:$C1013, 'CF BEST'!$I$9:$I1013, A16,'CF BEST'!$F$9:$F1013, $T$5) -> 0 | T16: =SUMIFS('CF BEST'!$D$9:$D1013, 'CF BEST'!$I$9:$I1013, A16,'CF BEST'!$F$9:$F1013, $T$5) -> 0 | U16: =SUMIFS('CF BEST'!$C$9:$C1013, 'CF BEST'!$I$9:$I1013, A16,'CF BEST'!$F$9:$F1013, $V$5) -> 0 | V16: =SUMIFS('CF BEST'!$D$9:$D1013, 'CF BEST'!$I$9:$I1013, A16,'CF BEST'!$F$9:$F1013, $V$5) -> 1444897 | W16: =SUMIFS('CF BEST'!$C$9:$C1013, 'CF BEST'!$I$9:$I1013, A16,'CF BEST'!$F$9:$F1013, $X$5) -> 0 | X16: =SUMIFS('CF BEST'!$D$9:$D1013, 'CF BEST'!$I$9:$I1013, A16,'CF BEST'!$F$9:$F1013, $X$5) -> 0 | Y16: =SUMIFS('CF BEST'!$C$9:$C1013, 'CF BEST'!$I$9:$I1013, A16,'CF BEST'!$F$9:$F1013, $Z$5)+S16+U16+W16 -> 0 | Z16: =SUMIFS('CF BEST'!$D$9:$D1013, 'CF BEST'!$I$9:$I1013, A16,'CF BEST'!$F$9:$F1013, $Z$5)+T16+V16+X16 -> 1444897 | AA16: =SUMIFS('CF BEST'!$C$9:$C1013, 'CF BEST'!$I$9:$I1013, A16,'CF BEST'!$F$9:$F1013, $AB$5) -> 0 | AB16: =SUMIFS('CF BEST'!$D$9:$D1013, 'CF BEST'!$I$9:$I1013, A16,'CF BEST'!$F$9:$F1013, $AB$5) -> 1168800.1 | AC16: =SUMIFS('CF BEST'!$C$9:$C1013, 'CF BEST'!$I$9:$I1013, A16,'CF BEST'!$F$9:$F1013, $AD$5) -> 0 | AD16: =SUMIFS('CF BEST'!$D$9:$D1013, 'CF BEST'!$I$9:$I1013, A16,'CF BEST'!$F$9:$F1013, $AD$5) -> 1207396.4 | AE16: =SUMIFS('CF BEST'!$C$9:$C1013, 'CF BEST'!$I$9:$I1013, A16,'CF BEST'!$F$9:$F1013, $AF$5) -> 0 | AF16: =SUMIFS('CF BEST'!$D$9:$D1013, 'CF BEST'!$I$9:$I1013, A16,'CF BEST'!$F$9:$F1013, $AF$5) -> 2534384.1 | AG16: =SUMIFS('CF BEST'!$C$9:$C1013, 'CF BEST'!$I$9:$I1013, A16,'CF BEST'!$F$9:$F1013, $AH$5)+AA16+AC16+AE16 -> 0 | AH16: =SUMIFS('CF BEST'!$D$9:$D1013, 'CF BEST'!$I$9:$I1013, A16,'CF BEST'!$F$9:$F1013, $AH$5)+AB16+AD16+AF16 -> 4910580.5
A17: ФОТ | B17: =J17+R17+Z17+AH17 -> 14520630 | C17: =SUMIFS('CF BEST'!$C$9:$C1013, 'CF BEST'!$I$9:$I1013, A17,'CF BEST'!$F$9:$F1013, $D$5) -> 0 | D17: =SUMIFS('CF BEST'!$D$9:$D1013, 'CF BEST'!$I$9:$I1013, A17,'CF BEST'!$F$9:$F1013, $D$5) -> 670661.54 | E17: =SUMIFS('CF BEST'!$C$9:$C1013, 'CF BEST'!$I$9:$I1013, A17,'CF BEST'!$F$9:$F1013, $F$5) -> 0 | F17: =SUMIFS('CF BEST'!$D$9:$D1013, 'CF BEST'!$I$9:$I1013, A17,'CF BEST'!$F$9:$F1013, $F$5) -> 543837.65 | G17: =SUMIFS('CF BEST'!$C$9:$C1013, 'CF BEST'!$I$9:$I1013, A17,'CF BEST'!$F$9:$F1013, $H$5) -> 0 | H17: =SUMIFS('CF BEST'!$D$9:$D1013, 'CF BEST'!$I$9:$I1013, A17,'CF BEST'!$F$9:$F1013, $H$5) -> 812742.83 | I17: =SUMIFS('CF BEST'!$C$9:$C1013, 'CF BEST'!$I$9:$I1013, A17,'CF BEST'!$F$9:$F1013, $J$5)+C17+E17+G17 -> 0 | J17: =SUMIFS('CF BEST'!$D$9:$D1013, 'CF BEST'!$I$9:$I1013, A17,'CF BEST'!$F$9:$F1013, $J$5)+D17+F17+H17 -> 2027242 | K17: =SUMIFS('CF BEST'!$C$9:$C1013, 'CF BEST'!$I$9:$I1013, A17,'CF BEST'!$F$9:$F1013, $L$5) -> 0 | L17: =SUMIFS('CF BEST'!$D$9:$D1013, 'CF BEST'!$I$9:$I1013, A17,'CF BEST'!$F$9:$F1013, $L$5) -> 1434107.6 | M17: =SUMIFS('CF BEST'!$C$9:$C1013, 'CF BEST'!$I$9:$I1013, A17,'CF BEST'!$F$9:$F1013, $N$5) -> 0 | N17: =SUMIFS('CF BEST'!$D$9:$D1013, 'CF BEST'!$I$9:$I1013, A17,'CF BEST'!$F$9:$F1013, $N$5) -> 1643267.3 | O17: =SUMIFS('CF BEST'!$C$9:$C1013, 'CF BEST'!$I$9:$I1013, A17,'CF BEST'!$F$9:$F1013, $P$5) -> 0 | P17: =SUMIFS('CF BEST'!$D$9:$D1013, 'CF BEST'!$I$9:$I1013, A17,'CF BEST'!$F$9:$F1013, $P$5) -> 957937.68 | Q17: =SUMIFS('CF BEST'!$C$9:$C1013, 'CF BEST'!$I$9:$I1013, A17,'CF BEST'!$F$9:$F1013, $R$5)+K17+M17+O17 -> 0 | R17: =SUMIFS('CF BEST'!$D$9:$D1013, 'CF BEST'!$I$9:$I1013, A17,'CF BEST'!$F$9:$F1013, $R$5)+L17+N17+P17 -> 4035312.6 | S17: =SUMIFS('CF BEST'!$C$9:$C1013, 'CF BEST'!$I$9:$I1013, A17,'CF BEST'!$F$9:$F1013, $T$5) -> 0 | T17: =SUMIFS('CF BEST'!$D$9:$D1013, 'CF BEST'!$I$9:$I1013, A17,'CF BEST'!$F$9:$F1013, $T$5) -> 2611780.7 | U17: =SUMIFS('CF BEST'!$C$9:$C1013, 'CF BEST'!$I$9:$I1013, A17,'CF BEST'!$F$9:$F1013, $V$5) -> 0 | V17: =SUMIFS('CF BEST'!$D$9:$D1013, 'CF BEST'!$I$9:$I1013, A17,'CF BEST'!$F$9:$F1013, $V$5) -> 276598.8 | W17: =SUMIFS('CF BEST'!$C$9:$C1013, 'CF BEST'!$I$9:$I1013, A17,'CF BEST'!$F$9:$F1013, $X$5) -> 0 | X17: =SUMIFS('CF BEST'!$D$9:$D1013, 'CF BEST'!$I$9:$I1013, A17,'CF BEST'!$F$9:$F1013, $X$5) -> 0 | Y17: =SUMIFS('CF BEST'!$C$9:$C1013, 'CF BEST'!$I$9:$I1013, A17,'CF BEST'!$F$9:$F1013, $Z$5)+S17+U17+W17 -> 0 | Z17: =SUMIFS('CF BEST'!$D$9:$D1013, 'CF BEST'!$I$9:$I1013, A17,'CF BEST'!$F$9:$F1013, $Z$5)+T17+V17+X17 -> 2888379.5 | AA17: =SUMIFS('CF BEST'!$C$9:$C1013, 'CF BEST'!$I$9:$I1013, A17,'CF BEST'!$F$9:$F1013, $AB$5) -> 0 | AB17: =SUMIFS('CF BEST'!$D$9:$D1013, 'CF BEST'!$I$9:$I1013, A17,'CF BEST'!$F$9:$F1013, $AB$5) -> 1846174.6 | AC17: =SUMIFS('CF BEST'!$C$9:$C1013, 'CF BEST'!$I$9:$I1013, A17,'CF BEST'!$F$9:$F1013, $AD$5) -> 0 | AD17: =SUMIFS('CF BEST'!$D$9:$D1013, 'CF BEST'!$I$9:$I1013, A17,'CF BEST'!$F$9:$F1013, $AD$5) -> 1839812.3 | AE17: =SUMIFS('CF BEST'!$C$9:$C1013, 'CF BEST'!$I$9:$I1013, A17,'CF BEST'!$F$9:$F1013, $AF$5) -> 0 | AF17: =SUMIFS('CF BEST'!$D$9:$D1013, 'CF BEST'!$I$9:$I1013, A17,'CF BEST'!$F$9:$F1013, $AF$5) -> 1883708.9 | AG17: =SUMIFS('CF BEST'!$C$9:$C1013, 'CF BEST'!$I$9:$I1013, A17,'CF BEST'!$F$9:$F1013, $AH$5)+AA17+AC17+AE17 -> 0 | AH17: =SUMIFS('CF BEST'!$D$9:$D1013, 'CF BEST'!$I$9:$I1013, A17,'CF BEST'!$F$9:$F1013, $AH$5)+AB17+AD17+AF17 -> 5569695.8
A18: ПРЕМИЯ | B18: =J18+R18+Z18+AH18 -> 7223862 | C18: =SUMIFS('CF BEST'!$C$9:$C1013, 'CF BEST'!$I$9:$I1013, A18,'CF BEST'!$F$9:$F1013, $D$5) -> 0 | D18: =SUMIFS('CF BEST'!$D$9:$D1013, 'CF BEST'!$I$9:$I1013, A18,'CF BEST'!$F$9:$F1013, $D$5) -> 905000 | E18: =SUMIFS('CF BEST'!$C$9:$C1013, 'CF BEST'!$I$9:$I1013, A18,'CF BEST'!$F$9:$F1013, $F$5) -> 0 | F18: =SUMIFS('CF BEST'!$D$9:$D1013, 'CF BEST'!$I$9:$I1013, A18,'CF BEST'!$F$9:$F1013, $F$5) -> 755000 | G18: =SUMIFS('CF BEST'!$C$9:$C1013, 'CF BEST'!$I$9:$I1013, A18,'CF BEST'!$F$9:$F1013, $H$5) -> 0 | H18: =SUMIFS('CF BEST'!$D$9:$D1013, 'CF BEST'!$I$9:$I1013, A18,'CF BEST'!$F$9:$F1013, $H$5) -> 855640 | I18: =SUMIFS('CF BEST'!$C$9:$C1013, 'CF BEST'!$I$9:$I1013, A18,'CF BEST'!$F$9:$F1013, $J$5)+C18+E18+G18 -> 0 | J18: =SUMIFS('CF BEST'!$D$9:$D1013, 'CF BEST'!$I$9:$I1013, A18,'CF BEST'!$F$9:$F1013, $J$5)+D18+F18+H18 -> 2515640 | K18: =SUMIFS('CF BEST'!$C$9:$C1013, 'CF BEST'!$I$9:$I1013, A18,'CF BEST'!$F$9:$F1013, $L$5) -> 0 | L18: =SUMIFS('CF BEST'!$D$9:$D1013, 'CF BEST'!$I$9:$I1013, A18,'CF BEST'!$F$9:$F1013, $L$5) -> 255500 | M18: =SUMIFS('CF BEST'!$C$9:$C1013, 'CF BEST'!$I$9:$I1013, A18,'CF BEST'!$F$9:$F1013, $N$5) -> 0 | N18: =SUMIFS('CF BEST'!$D$9:$D1013, 'CF BEST'!$I$9:$I1013, A18,'CF BEST'!$F$9:$F1013, $N$5) -> 160000 | O18: =SUMIFS('CF BEST'!$C$9:$C1013, 'CF BEST'!$I$9:$I1013, A18,'CF BEST'!$F$9:$F1013, $P$5) -> 0 | P18: =SUMIFS('CF BEST'!$D$9:$D1013, 'CF BEST'!$I$9:$I1013, A18,'CF BEST'!$F$9:$F1013, $P$5) -> 1735722 | Q18: =SUMIFS('CF BEST'!$C$9:$C1013, 'CF BEST'!$I$9:$I1013, A18,'CF BEST'!$F$9:$F1013, $R$5)+K18+M18+O18 -> 0 | R18: =SUMIFS('CF BEST'!$D$9:$D1013, 'CF BEST'!$I$9:$I1013, A18,'CF BEST'!$F$9:$F1013, $R$5)+L18+N18+P18 -> 2151222 | S18: =SUMIFS('CF BEST'!$C$9:$C1013, 'CF BEST'!$I$9:$I1013, A18,'CF BEST'!$F$9:$F1013, $T$5) -> 0 | T18: =SUMIFS('CF BEST'!$D$9:$D1013, 'CF BEST'!$I$9:$I1013, A18,'CF BEST'!$F$9:$F1013, $T$5) -> 20000 | U18: =SUMIFS('CF BEST'!$C$9:$C1013, 'CF BEST'!$I$9:$I1013, A18,'CF BEST'!$F$9:$F1013, $V$5) -> 0 | V18: =SUMIFS('CF BEST'!$D$9:$D1013, 'CF BEST'!$I$9:$I1013, A18,'CF BEST'!$F$9:$F1013, $V$5) -> 332000 | W18: =SUMIFS('CF BEST'!$C$9:$C1013, 'CF BEST'!$I$9:$I1013, A18,'CF BEST'!$F$9:$F1013, $X$5) -> 0 | X18: =SUMIFS('CF BEST'!$D$9:$D1013, 'CF BEST'!$I$9:$I1013, A18,'CF BEST'!$F$9:$F1013, $X$5) -> 545000 | Y18: =SUMIFS('CF BEST'!$C$9:$C1013, 'CF BEST'!$I$9:$I1013, A18,'CF BEST'!$F$9:$F1013, $Z$5)+S18+U18+W18 -> 0 | Z18: =SUMIFS('CF BEST'!$D$9:$D1013, 'CF BEST'!$I$9:$I1013, A18,'CF BEST'!$F$9:$F1013, $Z$5)+T18+V18+X18 -> 897000 | AA18: =SUMIFS('CF BEST'!$C$9:$C1013, 'CF BEST'!$I$9:$I1013, A18,'CF BEST'!$F$9:$F1013, $AB$5) -> 0 | AB18: =SUMIFS('CF BEST'!$D$9:$D1013, 'CF BEST'!$I$9:$I1013, A18,'CF BEST'!$F$9:$F1013, $AB$5) -> 790000 | AC18: =SUMIFS('CF BEST'!$C$9:$C1013, 'CF BEST'!$I$9:$I1013, A18,'CF BEST'!$F$9:$F1013, $AD$5) -> 0 | AD18: =SUMIFS('CF BEST'!$D$9:$D1013, 'CF BEST'!$I$9:$I1013, A18,'CF BEST'!$F$9:$F1013, $AD$5) -> 340000 | AE18: =SUMIFS('CF BEST'!$C$9:$C1013, 'CF BEST'!$I$9:$I1013, A18,'CF BEST'!$F$9:$F1013, $AF$5) -> 0 | AF18: =SUMIFS('CF BEST'!$D$9:$D1013, 'CF BEST'!$I$9:$I1013, A18,'CF BEST'!$F$9:$F1013, $AF$5) -> 530000 | AG18: =SUMIFS('CF BEST'!$C$9:$C1013, 'CF BEST'!$I$9:$I1013, A18,'CF BEST'!$F$9:$F1013, $AH$5)+AA18+AC18+AE18 -> 0 | AH18: =SUMIFS('CF BEST'!$D$9:$D1013, 'CF BEST'!$I$9:$I1013, A18,'CF BEST'!$F$9:$F1013, $AH$5)+AB18+AD18+AF18 -> 1660000
A19: БОНУСЫ | B19: =J19+R19+Z19+AH19 -> 2654130 | C19: =SUMIFS('CF BEST'!$C$9:$C1013, 'CF BEST'!$I$9:$I1013, A19,'CF BEST'!$F$9:$F1013, $D$5) -> 0 | D19: =SUMIFS('CF BEST'!$D$9:$D1013, 'CF BEST'!$I$9:$I1013, A19,'CF BEST'!$F$9:$F1013, $D$5) -> 0 | E19: =SUMIFS('CF BEST'!$C$9:$C1013, 'CF BEST'!$I$9:$I1013, A19,'CF BEST'!$F$9:$F1013, $F$5) -> 0 | F19: =SUMIFS('CF BEST'!$D$9:$D1013, 'CF BEST'!$I$9:$I1013, A19,'CF BEST'!$F$9:$F1013, $F$5) -> 0 | G19: =SUMIFS('CF BEST'!$C$9:$C1013, 'CF BEST'!$I$9:$I1013, A19,'CF BEST'!$F$9:$F1013, $H$5) -> 0 | H19: =SUMIFS('CF BEST'!$D$9:$D1013, 'CF BEST'!$I$9:$I1013, A19,'CF BEST'!$F$9:$F1013, $H$5) -> 68783 | I19: =SUMIFS('CF BEST'!$C$9:$C1013, 'CF BEST'!$I$9:$I1013, A19,'CF BEST'!$F$9:$F1013, $J$5)+C19+E19+G19 -> 0 | J19: =SUMIFS('CF BEST'!$D$9:$D1013, 'CF BEST'!$I$9:$I1013, A19,'CF BEST'!$F$9:$F1013, $J$5)+D19+F19+H19 -> 729183 | K19: =SUMIFS('CF BEST'!$C$9:$C1013, 'CF BEST'!$I$9:$I1013, A19,'CF BEST'!$F$9:$F1013, $L$5) -> 0 | L19: =SUMIFS('CF BEST'!$D$9:$D1013, 'CF BEST'!$I$9:$I1013, A19,'CF BEST'!$F$9:$F1013, $L$5) -> 0 | M19: =SUMIFS('CF BEST'!$C$9:$C1013, 'CF BEST'!$I$9:$I1013, A19,'CF BEST'!$F$9:$F1013, $N$5) -> 0 | N19: =SUMIFS('CF BEST'!$D$9:$D1013, 'CF BEST'!$I$9:$I1013, A19,'CF BEST'!$F$9:$F1013, $N$5) -> 0 | O19: =SUMIFS('CF BEST'!$C$9:$C1013, 'CF BEST'!$I$9:$I1013, A19,'CF BEST'!$F$9:$F1013, $P$5) -> 0 | P19: =SUMIFS('CF BEST'!$D$9:$D1013, 'CF BEST'!$I$9:$I1013, A19,'CF BEST'!$F$9:$F1013, $P$5) -> 0 | Q19: =SUMIFS('CF BEST'!$C$9:$C1013, 'CF BEST'!$I$9:$I1013, A19,'CF BEST'!$F$9:$F1013, $R$5)+K19+M19+O19 -> 0 | R19: =SUMIFS('CF BEST'!$D$9:$D1013, 'CF BEST'!$I$9:$I1013, A19,'CF BEST'!$F$9:$F1013, $R$5)+L19+N19+P19 -> 429000 | S19: =SUMIFS('CF BEST'!$C$9:$C1013, 'CF BEST'!$I$9:$I1013, A19,'CF BEST'!$F$9:$F1013, $T$5) -> 0 | T19: =SUMIFS('CF BEST'!$D$9:$D1013, 'CF BEST'!$I$9:$I1013, A19,'CF BEST'!$F$9:$F1013, $T$5) -> 0 | U19: =SUMIFS('CF BEST'!$C$9:$C1013, 'CF BEST'!$I$9:$I1013, A19,'CF BEST'!$F$9:$F1013, $V$5) -> 0 | V19: =SUMIFS('CF BEST'!$D$9:$D1013, 'CF BEST'!$I$9:$I1013, A19,'CF BEST'!$F$9:$F1013, $V$5) -> 0 | W19: =SUMIFS('CF BEST'!$C$9:$C1013, 'CF BEST'!$I$9:$I1013, A19,'CF BEST'!$F$9:$F1013, $X$5) -> 0 | X19: =SUMIFS('CF BEST'!$D$9:$D1013, 'CF BEST'!$I$9:$I1013, A19,'CF BEST'!$F$9:$F1013, $X$5) -> 0 | Y19: =SUMIFS('CF BEST'!$C$9:$C1013, 'CF BEST'!$I$9:$I1013, A19,'CF BEST'!$F$9:$F1013, $Z$5)+S19+U19+W19 -> 0 | Z19: =SUMIFS('CF BEST'!$D$9:$D1013, 'CF BEST'!$I$9:$I1013, A19,'CF BEST'!$F$9:$F1013, $Z$5)+T19+V19+X19 -> 611180 | AA19: =SUMIFS('CF BEST'!$C$9:$C1013, 'CF BEST'!$I$9:$I1013, A19,'CF BEST'!$F$9:$F1013, $AB$5) -> 0 | AB19: =SUMIFS('CF BEST'!$D$9:$D1013, 'CF BEST'!$I$9:$I1013, A19,'CF BEST'!$F$9:$F1013, $AB$5) -> 0 | AC19: =SUMIFS('CF BEST'!$C$9:$C1013, 'CF BEST'!$I$9:$I1013, A19,'CF BEST'!$F$9:$F1013, $AD$5) -> 0 | AD19: =SUMIFS('CF BEST'!$D$9:$D1013, 'CF BEST'!$I$9:$I1013, A19,'CF BEST'!$F$9:$F1013, $AD$5) -> 0 | AE19: =SUMIFS('CF BEST'!$C$9:$C1013, 'CF BEST'!$I$9:$I1013, A19,'CF BEST'!$F$9:$F1013, $AF$5) -> 0 | AF19: =SUMIFS('CF BEST'!$D$9:$D1013, 'CF BEST'!$I$9:$I1013, A19,'CF BEST'!$F$9:$F1013, $AF$5) -> 0 | AG19: =SUMIFS('CF BEST'!$C$9:$C1013, 'CF BEST'!$I$9:$I1013, A19,'CF BEST'!$F$9:$F1013, $AH$5)+AA19+AC19+AE19 -> 0 | AH19: =SUMIFS('CF BEST'!$D$9:$D1013, 'CF BEST'!$I$9:$I1013, A19,'CF BEST'!$F$9:$F1013, $AH$5)+AB19+AD19+AF19 -> 884767
A20: НАЛОГИ | НДФЛ | B20: =J20+R20+Z20+AH20 -> 3769351.1 | C20: =SUMIFS('CF BEST'!$C$9:$C1013, 'CF BEST'!$I$9:$I1013, A20,'CF BEST'!$F$9:$F1013, $D$5) -> 0 | D20: =SUMIFS('CF BEST'!$D$9:$D1013, 'CF BEST'!$I$9:$I1013, A20,'CF BEST'!$F$9:$F1013, $D$5) -> 129648 | E20: =SUMIFS('CF BEST'!$C$9:$C1013, 'CF BEST'!$I$9:$I1013, A20,'CF BEST'!$F$9:$F1013, $F$5) -> 0 | F20: =SUMIFS('CF BEST'!$D$9:$D1013, 'CF BEST'!$I$9:$I1013, A20,'CF BEST'!$F$9:$F1013, $F$5) -> 900100 | G20: =SUMIFS('CF BEST'!$C$9:$C1013, 'CF BEST'!$I$9:$I1013, A20,'CF BEST'!$F$9:$F1013, $H$5) -> 0 | H20: =SUMIFS('CF BEST'!$D$9:$D1013, 'CF BEST'!$I$9:$I1013, A20,'CF BEST'!$F$9:$F1013, $H$5) -> 281930 | I20: =SUMIFS('CF BEST'!$C$9:$C1013, 'CF BEST'!$I$9:$I1013, A20,'CF BEST'!$F$9:$F1013, $J$5)+C20+E20+G20 -> 0 | J20: =SUMIFS('CF BEST'!$D$9:$D1013, 'CF BEST'!$I$9:$I1013, A20,'CF BEST'!$F$9:$F1013, $J$5)+D20+F20+H20 -> 1311678 | K20: =SUMIFS('CF BEST'!$C$9:$C1013, 'CF BEST'!$I$9:$I1013, A20,'CF BEST'!$F$9:$F1013, $L$5) -> 0 | L20: =SUMIFS('CF BEST'!$D$9:$D1013, 'CF BEST'!$I$9:$I1013, A20,'CF BEST'!$F$9:$F1013, $L$5) -> 152979.85 | M20: =SUMIFS('CF BEST'!$C$9:$C1013, 'CF BEST'!$I$9:$I1013, A20,'CF BEST'!$F$9:$F1013, $N$5) -> 0 | N20: =SUMIFS('CF BEST'!$D$9:$D1013, 'CF BEST'!$I$9:$I1013, A20,'CF BEST'!$F$9:$F1013, $N$5) -> 148836 | O20: =SUMIFS('CF BEST'!$C$9:$C1013, 'CF BEST'!$I$9:$I1013, A20,'CF BEST'!$F$9:$F1013, $P$5) -> 0 | P20: =SUMIFS('CF BEST'!$D$9:$D1013, 'CF BEST'!$I$9:$I1013, A20,'CF BEST'!$F$9:$F1013, $P$5) -> 109101.22 | Q20: =SUMIFS('CF BEST'!$C$9:$C1013, 'CF BEST'!$I$9:$I1013, A20,'CF BEST'!$F$9:$F1013, $R$5)+K20+M20+O20 -> 0 | R20: =SUMIFS('CF BEST'!$D$9:$D1013, 'CF BEST'!$I$9:$I1013, A20,'CF BEST'!$F$9:$F1013, $R$5)+L20+N20+P20 -> 410917.07 | S20: =SUMIFS('CF BEST'!$C$9:$C1013, 'CF BEST'!$I$9:$I1013, A20,'CF BEST'!$F$9:$F1013, $T$5) -> 0 | T20: =SUMIFS('CF BEST'!$D$9:$D1013, 'CF BEST'!$I$9:$I1013, A20,'CF BEST'!$F$9:$F1013, $T$5) -> 238438 | U20: =SUMIFS('CF BEST'!$C$9:$C1013, 'CF BEST'!$I$9:$I1013, A20,'CF BEST'!$F$9:$F1013, $V$5) -> 0 | V20: =SUMIFS('CF BEST'!$D$9:$D1013, 'CF BEST'!$I$9:$I1013, A20,'CF BEST'!$F$9:$F1013, $V$5) -> 238441 | W20: =SUMIFS('CF BEST'!$C$9:$C1013, 'CF BEST'!$I$9:$I1013, A20,'CF BEST'!$F$9:$F1013, $X$5) -> 0 | X20: =SUMIFS('CF BEST'!$D$9:$D1013, 'CF BEST'!$I$9:$I1013, A20,'CF BEST'!$F$9:$F1013, $X$5) -> 179431 | Y20: =SUMIFS('CF BEST'!$C$9:$C1013, 'CF BEST'!$I$9:$I1013, A20,'CF BEST'!$F$9:$F1013, $Z$5)+S20+U20+W20 -> 0 | Z20: =SUMIFS('CF BEST'!$D$9:$D1013, 'CF BEST'!$I$9:$I1013, A20,'CF BEST'!$F$9:$F1013, $Z$5)+T20+V20+X20 -> 656310 | AA20: =SUMIFS('CF BEST'!$C$9:$C1013, 'CF BEST'!$I$9:$I1013, A20,'CF BEST'!$F$9:$F1013, $AB$5) -> 0 | AB20: =SUMIFS('CF BEST'!$D$9:$D1013, 'CF BEST'!$I$9:$I1013, A20,'CF BEST'!$F$9:$F1013, $AB$5) -> 165412 | AC20: =SUMIFS('CF BEST'!$C$9:$C1013, 'CF BEST'!$I$9:$I1013, A20,'CF BEST'!$F$9:$F1013, $AD$5) -> 0 | AD20: =SUMIFS('CF BEST'!$D$9:$D1013, 'CF BEST'!$I$9:$I1013, A20,'CF BEST'!$F$9:$F1013, $AD$5) -> 477913 | AE20: =SUMIFS('CF BEST'!$C$9:$C1013, 'CF BEST'!$I$9:$I1013, A20,'CF BEST'!$F$9:$F1013, $AF$5) -> 0 | AF20: =SUMIFS('CF BEST'!$D$9:$D1013, 'CF BEST'!$I$9:$I1013, A20,'CF BEST'!$F$9:$F1013, $AF$5) -> 747121 | AG20: =SUMIFS('CF BEST'!$C$9:$C1013, 'CF BEST'!$I$9:$I1013, A20,'CF BEST'!$F$9:$F1013, $AH$5)+AA20+AC20+AE20 -> 0 | AH20: =SUMIFS('CF BEST'!$D$9:$D1013, 'CF BEST'!$I$9:$I1013, A20,'CF BEST'!$F$9:$F1013, $AH$5)+AB20+AD20+AF20 -> 1390446
A21: НАЛОГИ | Страх.Взносы | B21: =J21+R21+Z21+AH21 -> 3020557.1 | C21: =SUMIFS('CF BEST'!$C$9:$C1013, 'CF BEST'!$I$9:$I1013, A21,'CF BEST'!$F$9:$F1013, $D$5) -> 0 | D21: =SUMIFS('CF BEST'!$D$9:$D1013, 'CF BEST'!$I$9:$I1013, A21,'CF BEST'!$F$9:$F1013, $D$5) -> 158017.9 | E21: =SUMIFS('CF BEST'!$C$9:$C1013, 'CF BEST'!$I$9:$I1013, A21,'CF BEST'!$F$9:$F1013, $F$5) -> 0 | F21: =SUMIFS('CF BEST'!$D$9:$D1013, 'CF BEST'!$I$9:$I1013, A21,'CF BEST'!$F$9:$F1013, $F$5) -> 239375.47 | G21: =SUMIFS('CF BEST'!$C$9:$C1013, 'CF BEST'!$I$9:$I1013, A21,'CF BEST'!$F$9:$F1013, $H$5) -> 0 | H21: =SUMIFS('CF BEST'!$D$9:$D1013, 'CF BEST'!$I$9:$I1013, A21,'CF BEST'!$F$9:$F1013, $H$5) -> 242899.97 | I21: =SUMIFS('CF BEST'!$C$9:$C1013, 'CF BEST'!$I$9:$I1013, A21,'CF BEST'!$F$9:$F1013, $J$5)+C21+E21+G21 -> 0 | J21: =SUMIFS('CF BEST'!$D$9:$D1013, 'CF BEST'!$I$9:$I1013, A21,'CF BEST'!$F$9:$F1013, $J$5)+D21+F21+H21 -> 640293.34 | K21: =SUMIFS('CF BEST'!$C$9:$C1013, 'CF BEST'!$I$9:$I1013, A21,'CF BEST'!$F$9:$F1013, $L$5) -> 0 | L21: =SUMIFS('CF BEST'!$D$9:$D1013, 'CF BEST'!$I$9:$I1013, A21,'CF BEST'!$F$9:$F1013, $L$5) -> 208655.47 | M21: =SUMIFS('CF BEST'!$C$9:$C1013, 'CF BEST'!$I$9:$I1013, A21,'CF BEST'!$F$9:$F1013, $N$5) -> 0 | N21: =SUMIFS('CF BEST'!$D$9:$D1013, 'CF BEST'!$I$9:$I1013, A21,'CF BEST'!$F$9:$F1013, $N$5) -> 232032.6 | O21: =SUMIFS('CF BEST'!$C$9:$C1013, 'CF BEST'!$I$9:$I1013, A21,'CF BEST'!$F$9:$F1013, $P$5) -> 0 | P21: =SUMIFS('CF BEST'!$D$9:$D1013, 'CF BEST'!$I$9:$I1013, A21,'CF BEST'!$F$9:$F1013, $P$5) -> 252955.25 | Q21: =SUMIFS('CF BEST'!$C$9:$C1013, 'CF BEST'!$I$9:$I1013, A21,'CF BEST'!$F$9:$F1013, $R$5)+K21+M21+O21 -> 0 | R21: =SUMIFS('CF BEST'!$D$9:$D1013, 'CF BEST'!$I$9:$I1013, A21,'CF BEST'!$F$9:$F1013, $R$5)+L21+N21+P21 -> 693643.32 | S21: =SUMIFS('CF BEST'!$C$9:$C1013, 'CF BEST'!$I$9:$I1013, A21,'CF BEST'!$F$9:$F1013, $T$5) -> 0 | T21: =SUMIFS('CF BEST'!$D$9:$D1013, 'CF BEST'!$I$9:$I1013, A21,'CF BEST'!$F$9:$F1013, $T$5) -> 345808.5 | U21: =SUMIFS('CF BEST'!$C$9:$C1013, 'CF BEST'!$I$9:$I1013, A21,'CF BEST'!$F$9:$F1013, $V$5) -> 0 | V21: =SUMIFS('CF BEST'!$D$9:$D1013, 'CF BEST'!$I$9:$I1013, A21,'CF BEST'!$F$9:$F1013, $V$5) -> 345808 | W21: =SUMIFS('CF BEST'!$C$9:$C1013, 'CF BEST'!$I$9:$I1013, A21,'CF BEST'!$F$9:$F1013, $X$5) -> 0 | X21: =SUMIFS('CF BEST'!$D$9:$D1013, 'CF BEST'!$I$9:$I1013, A21,'CF BEST'!$F$9:$F1013, $X$5) -> 557492.57 | Y21: =SUMIFS('CF BEST'!$C$9:$C1013, 'CF BEST'!$I$9:$I1013, A21,'CF BEST'!$F$9:$F1013, $Z$5)+S21+U21+W21 -> 0 | Z21: =SUMIFS('CF BEST'!$D$9:$D1013, 'CF BEST'!$I$9:$I1013, A21,'CF BEST'!$F$9:$F1013, $Z$5)+T21+V21+X21 -> 1249109.1 | AA21: =SUMIFS('CF BEST'!$C$9:$C1013, 'CF BEST'!$I$9:$I1013, A21,'CF BEST'!$F$9:$F1013, $AB$5) -> 0 | AB21: =SUMIFS('CF BEST'!$D$9:$D1013, 'CF BEST'!$I$9:$I1013, A21,'CF BEST'!$F$9:$F1013, $AB$5) -> 430435.99 | AC21: =SUMIFS('CF BEST'!$C$9:$C1013, 'CF BEST'!$I$9:$I1013, A21,'CF BEST'!$F$9:$F1013, $AD$5) -> 0 | AD21: =SUMIFS('CF BEST'!$D$9:$D1013, 'CF BEST'!$I$9:$I1013, A21,'CF BEST'!$F$9:$F1013, $AD$5) -> 0 | AE21: =SUMIFS('CF BEST'!$C$9:$C1013, 'CF BEST'!$I$9:$I1013, A21,'CF BEST'!$F$9:$F1013, $AF$5) -> 0 | AF21: =SUMIFS('CF BEST'!$D$9:$D1013, 'CF BEST'!$I$9:$I1013, A21,'CF BEST'!$F$9:$F1013, $AF$5) -> 7075.35 | AG21: =SUMIFS('CF BEST'!$C$9:$C1013, 'CF BEST'!$I$9:$I1013, A21,'CF BEST'!$F$9:$F1013, $AH$5)+AA21+AC21+AE21 -> 0 | AH21: =SUMIFS('CF BEST'!$D$9:$D1013, 'CF BEST'!$I$9:$I1013, A21,'CF BEST'!$F$9:$F1013, $AH$5)+AB21+AD21+AF21 -> 437511.34
A22: НАЛОГИ | B22: =J22+R22+Z22+AH22 -> 54913693 | C22: =SUMIFS('CF BEST'!$C$9:$C1013, 'CF BEST'!$I$9:$I1013, A22,'CF BEST'!$F$9:$F1013, $D$5) -> 0 | D22: =SUM(D23:D27) -> 2382685.7 | E22: =SUM(E23:E27) -> 0 | F22: =SUM(F23:F27) -> 2047020 | G22: =SUM(G23:G27) -> 0 | H22: =SUM(H23:H27) -> 2734490 | I22: =SUM(I23:I27) -> 0 | J22: =SUM(J23:J27) -> 7164195.7 | K22: =SUM(K23:K27) -> 0 | ... AH22: =SUM(AH23:AH27) -> 17834732
A23: НАЛОГИ | Прибыль | B23: =J23+R23+Z23+AH23 -> 17398621 | C23: =SUMIFS('CF BEST'!$C$9:$C1013, 'CF BEST'!$I$9:$I1013, A23,'CF BEST'!$F$9:$F1013, $D$5) -> 0 | D23: =SUMIFS('CF BEST'!$D$9:$D1013, 'CF BEST'!$I$9:$I1013, A23,'CF BEST'!$F$9:$F1013, $D$5) -> 685714 | E23: =SUMIFS('CF BEST'!$C$9:$C1013, 'CF BEST'!$I$9:$I1013, A23,'CF BEST'!$F$9:$F1013, $F$5) -> 0 | F23: =SUMIFS('CF BEST'!$D$9:$D1013, 'CF BEST'!$I$9:$I1013, A23,'CF BEST'!$F$9:$F1013, $F$5) -> 348682 | G23: =SUMIFS('CF BEST'!$C$9:$C1013, 'CF BEST'!$I$9:$I1013, A23,'CF BEST'!$F$9:$F1013, $H$5) -> 0 | H23: =SUMIFS('CF BEST'!$D$9:$D1013, 'CF BEST'!$I$9:$I1013, A23,'CF BEST'!$F$9:$F1013, $H$5) -> 0 | I23: =SUMIFS('CF BEST'!$C$9:$C1013, 'CF BEST'!$I$9:$I1013, A23,'CF BEST'!$F$9:$F1013, $J$5)+C23+E23+G23 -> 0 | J23: =SUMIFS('CF BEST'!$D$9:$D1013, 'CF BEST'!$I$9:$I1013, A23,'CF BEST'!$F$9:$F1013, $J$5)+D23+F23+H23 -> 1034396 | K23: =SUMIFS('CF BEST'!$C$9:$C1013, 'CF BEST'!$I$9:$I1013, A23,'CF BEST'!$F$9:$F1013, $L$5) -> 0 | L23: =SUMIFS('CF BEST'!$D$9:$D1013, 'CF BEST'!$I$9:$I1013, A23,'CF BEST'!$F$9:$F1013, $L$5) -> 3645128 | M23: =SUMIFS('CF BEST'!$C$9:$C1013, 'CF BEST'!$I$9:$I1013, A23,'CF BEST'!$F$9:$F1013, $N$5) -> 0 | N23: =SUMIFS('CF BEST'!$D$9:$D1013, 'CF BEST'!$I$9:$I1013, A23,'CF BEST'!$F$9:$F1013, $N$5) -> 2345586 | O23: =SUMIFS('CF BEST'!$C$9:$C1013, 'CF BEST'!$I$9:$I1013, A23,'CF BEST'!$F$9:$F1013, $P$5) -> 0 | P23: =SUMIFS('CF BEST'!$D$9:$D1013, 'CF BEST'!$I$9:$I1013, A23,'CF BEST'!$F$9:$F1013, $P$5) -> 0 | Q23: =SUMIFS('CF BEST'!$C$9:$C1013, 'CF BEST'!$I$9:$I1013, A23,'CF BEST'!$F$9:$F1013, $R$5)+K23+M23+O23 -> 0 | R23: =SUMIFS('CF BEST'!$D$9:$D1013, 'CF BEST'!$I$9:$I1013, A23,'CF BEST'!$F$9:$F1013, $R$5)+L23+N23+P23 -> 5990714 | S23: =SUMIFS('CF BEST'!$C$9:$C1013, 'CF BEST'!$I$9:$I1013, A23,'CF BEST'!$F$9:$F1013, $T$5) -> 0 | T23: =SUMIFS('CF BEST'!$D$9:$D1013, 'CF BEST'!$I$9:$I1013, A23,'CF BEST'!$F$9:$F1013, $T$5) -> 4845598 | U23: =SUMIFS('CF BEST'!$C$9:$C1013, 'CF BEST'!$I$9:$I1013, A23,'CF BEST'!$F$9:$F1013, $V$5) -> 0 | V23: =SUMIFS('CF BEST'!$D$9:$D1013, 'CF BEST'!$I$9:$I1013, A23,'CF BEST'!$F$9:$F1013, $V$5) -> 0 | W23: =SUMIFS('CF BEST'!$C$9:$C1013, 'CF BEST'!$I$9:$I1013, A23,'CF BEST'!$F$9:$F1013, $X$5) -> 0 | X23: =SUMIFS('CF BEST'!$D$9:$D1013, 'CF BEST'!$I$9:$I1013, A23,'CF BEST'!$F$9:$F1013, $X$5) -> 3490133 | Y23: =SUMIFS('CF BEST'!$C$9:$C1013, 'CF BEST'!$I$9:$I1013, A23,'CF BEST'!$F$9:$F1013, $Z$5)+S23+U23+W23 -> 0 | Z23: =SUMIFS('CF BEST'!$D$9:$D1013, 'CF BEST'!$I$9:$I1013, A23,'CF BEST'!$F$9:$F1013, $Z$5)+T23+V23+X23 -> 8335731 | AA23: =SUMIFS('CF BEST'!$C$9:$C1013, 'CF BEST'!$I$9:$I1013, A23,'CF BEST'!$F$9:$F1013, $AB$5) -> 0 | AB23: =SUMIFS('CF BEST'!$D$9:$D1013, 'CF BEST'!$I$9:$I1013, A23,'CF BEST'!$F$9:$F1013, $AB$5) -> 0 | AC23: =SUMIFS('CF BEST'!$C$9:$C1013, 'CF BEST'!$I$9:$I1013, A23,'CF BEST'!$F$9:$F1013, $AD$5) -> 0 | AD23: =SUMIFS('CF BEST'!$D$9:$D1013, 'CF BEST'!$I$9:$I1013, A23,'CF BEST'!$F$9:$F1013, $AD$5) -> 0 | AE23: =SUMIFS('CF BEST'!$C$9:$C1013, 'CF BEST'!$I$9:$I1013, A23,'CF BEST'!$F$9:$F1013, $AF$5) -> 2000000 | AF23: =SUMIFS('CF BEST'!$D$9:$D1013, 'CF BEST'!$I$9:$I1013, A23,'CF BEST'!$F$9:$F1013, $AF$5) -> 0 | AG23: =SUMIFS('CF BEST'!$C$9:$C1013, 'CF BEST'!$I$9:$I1013, A23,'CF BEST'!$F$9:$F1013, $AH$5)+AA23+AC23+AE23 -> 2000000 | AH23: =SUMIFS('CF BEST'!$D$9:$D1013, 'CF BEST'!$I$9:$I1013, A23,'CF BEST'!$F$9:$F1013, $AH$5)+AB23+AD23+AF23 -> 2037780
